Workbook

Sheet Cover Page
B2: {=_xlfn.XLOOKUP(C7, Projects!$A:$A, Projects!$B:$B) & " (" & C7 & ")"} -> Casa Spotify Miami (CSMIA26)
B3: EXECUTIVE PRODUCTION PLAYBOOK & OPERATING SPECIFICATION
B4: GHXSTSHIP Experiential Operating System (XOS 4.0 Standard) • Single Source of Truth (SSOT)
B6: EVENT PARAMETERS & TIMELINE | E6: CREATIVE & MARKETING NARRATIVE | H6: KEY CONTACTS & GOVERNANCE
B7: Project Code | C7: CSMIA26 | E7: Concept & Theme | F7: {=_xlfn.XLOOKUP(C7, Projects!$A:$A, Projects!$S:$S)} -> Art, Music & Technology Convergence in Wynwood; flagship production | H7: Executive Producer | I7: {=_xlfn.XLOOKUP(C7, Projects!$A:$A, Projects!$R:$R) & " (" & LOWER(SUBSTITUTE(_xlfn.XLOOKUP(C7, Projects!$A:$A, Projects!$R:$R), " ", ".")) & "@ghxstship.pro)"} -> Julian Clarkson (julian.clarkson@ghxstship.pro)
B8: Event Title | C8: {=_xlfn.XLOOKUP(C7, Projects!$A:$A, Projects!$B:$B)} -> Casa Spotify Miami | E8: Experience Tier | F8: {=_xlfn.XLOOKUP(C7, Projects!$A:$A, Projects!$J:$J)} -> Tier 06 Theatrical | H8: Organization | I8: {=_xlfn.XLOOKUP(C7, Projects!$A:$A, Projects!$D:$D)} -> GHXSTSHIP
B9: Event Anchor Date (T-0) | C9: {=_xlfn.XLOOKUP(C7, Projects!$A:$A, Projects!$I:$I)} -> 2026-10-16 | D9: (Anchor / Opening Day) | E9: Visual Identity | F9: =IF(C7="CSMIA26", "Wynwood Industrial Brutalism, LED Arrays, Neon", IF(C7="SXSW26", "Rainey Street Industrial, Warm Timber, Neon", IF(C7="EDCLV26", "Kinetic Cathedral, High-SPL LED, Lasers", IF(C7="ABMIA26", "Wynwood Arts Geometric, Minimalist Gallery", "Manhattan Editorial Runway, High-Gloss Monolith")))) -> Wynwood Industrial Brutalism, LED Arrays, Neon | H9: Operating Standard | I9: XOS 4.0 Experiential Operating System
B10: Show Dates | C10: {=TEXT(_xlfn.XLOOKUP(C7, Projects!$A:$A, Projects!$G:$G), "yyyy-mm-dd") & " to " & TEXT(_xlfn.XLOOKUP(C7, Projects!$A:$A, Projects!$H:$H), "yyyy-mm-dd")} -> 2026-08-21 to 2026-10-30 | E10: Audience Target | F10: =IF(C7="CSMIA26", "35,000 Daily Cap / 105,000 Weekend Aggregate", IF(C7="SXSW26", "2,500 Daily Cap / 10,000 Festival Aggregate", IF(C7="EDCLV26", "150,000 Daily Cap / 450,000 Weekend Aggregate", IF(C7="ABMIA26", "15,000 Daily Cap / 60,000 Event Aggregate", "5,000 Daily Cap / 15,000 Runway Aggregate")))) -> 35,000 Daily Cap / 105,000 Weekend Aggregate | H10: Jurisdiction & Code | I10: {=IF(_xlfn.XLOOKUP(C7, Projects!$A:$A, Projects!$F:$F)="Miami, FL", "US-FL-MIAMI-DADE (FBC / NFPA / City of Miami)", IF(_xlfn.XLOOKUP(C7, Projects!$A:$A, Projects!$F:$F)="Austin, TX", "US-TX-TRAVIS (City of Austin / IFC)", IF(_xlfn.XLOOKUP(C7, Projects!$A:$A, Projects!$F:$F)="Las Vegas, NV", "US-NV-CLARK (Clark County / IBC)", "US-NY-NEWYORK (NYC Building Code / FDNY)")))} -> US-FL-MIAMI-DADE (FBC / NFPA / City of Miami)
B11: Venue & Location | C11: {=_xlfn.XLOOKUP(C7, Projects!$A:$A, Projects!$E:$E) & ", " & _xlfn.XLOOKUP(C7, Projects!$A:$A, Projects!$F:$F)} -> Mana Wynwood Convention Center & Grounds, Miami, FL | E11: Acoustic Footprint | F11: =IF(C7="CSMIA26", "Multi-Zone High-SPL Controlled Environments", IF(C7="SXSW26", "Acoustic Showcase & Live Outdoor Stage", IF(C7="EDCLV26", "High-SPL Multi-Point Line Array Stadium Environment", IF(C7="ABMIA26", "Spatial Audio Gallery & Ambient Soundscape", "Runway Surround AVL & Broadcast Feed")))) -> Multi-Zone High-SPL Controlled Environments | H11: Governing Gate | I11: {=_xlfn.XLOOKUP(C7, Projects!$A:$A, Projects!$Q:$Q)} -> Gate 05 Build
B13: STAGE & PRODUCTION FOOTPRINT | E13: CURATED TALENT ROSTER & HIGHLIGHTS | H13: OPERATIONAL EXECUTION CADENCE
B14: =IF(C7="CSMIA26", "Main Stage (Zone B)", "Main Stage") -> Main Stage (Zone B) | C14: =IF(C7="CSMIA26", "60ft x 40ft Proscenium, Flown Line Arrays & 4K LED Backdrop", "Primary Production Footprint") -> 60ft x 40ft Proscenium, Flown Line Arrays & 4K LED Backdrop | E14: Headlining Acts | F14: =IF(C7="CSMIA26", "Latin & Global Headliners (TBA)", "Headlining Talent Roster") -> Latin & Global Headliners (TBA) | H14: Pre-Production Advance | I14: Gates 1–3: Scope, Engage, Advance (T-8W to T-4W)
B15: =IF(C7="CSMIA26", "Stage 2 - Tent Deck", "Secondary Stage") -> Stage 2 - Tent Deck | C15: =IF(C7="CSMIA26", "40ft x 30ft Covered Deck, Moving Head Rig & Cardioid Subs", "Secondary Production Footprint") -> 40ft x 30ft Covered Deck, Moving Head Rig & Cardioid Subs | E15: DJ & Electronic Sets | F15: =IF(C7="CSMIA26", "DJ SWVNLVKE & Resident Electronic Lineup", "Curated DJ & Electronic Sets") -> DJ SWVNLVKE & Resident Electronic Lineup | H15: Site Build & Load-In | I15: Gates 4–6: Procure, Build, Install (T-3W to T-1W)
B16: =IF(C7="CSMIA26", "VIP Oasis Lounge & El Patio", "VIP & Hospitality Lounge") -> VIP Oasis Lounge & El Patio | C16: =IF(C7="CSMIA26", "Curated Hospitality Terrace, Acoustic Salon & DJ Booth", "Hospitality Terrace & Acoustic Salon") -> Curated Hospitality Terrace, Acoustic Salon & DJ Booth | E16: Special Performances | F16: =IF(C7="CSMIA26", "Pop-Up Acoustic Sessions & Featured Artist Showcases", "Special Showcases & Guest Acts") -> Pop-Up Acoustic Sessions & Featured Artist Showcases | H16: Event Operations | I16: Gate 7: Operate (T-0, Live Run)
B17: Activation Compounds | C17: Sponsor brand footprints, retail hubs & food villages | E17: Broadcast & Sensory | F17: =IF(C7="CSMIA26", "Live Multicam 4K Stream, Spatial Audio & Cold-Air Scent", "4K Live Capture, Broadcast & Sensory") -> Live Multicam 4K Stream, Spatial Audio & Cold-Air Scent | H17: Strike & Reconciliation | I17: Gates 8–9: Strike, Amplify, Close (T+1W to T+2W)
B19: EXECUTIVE KPI SCOREBOARD & SYSTEM METRICS
B20: REVISED TOTAL BUDGET | D20: COMMITTED EXPENDITURE | F20: APPROVED CHANGE ORDERS | H20: PRODUCTION SCHEDULE TASKS
B21: {=_xlfn.XLOOKUP(C7, Projects!$A:$A, Projects!$K:$K)} -> 4500000 | D21: {=_xlfn.XLOOKUP(C7, Projects!$A:$A, Projects!$L:$L)} -> 46600 | F21: {=_xlfn.XLOOKUP(C7, Projects!$A:$A, Projects!$N:$N)} -> 1200 | H21: {=_xlfn.XLOOKUP(C7, Projects!$A:$A, Projects!$O:$O)} -> 3
B22: Approved Budget Envelope (Projects!K) | D22: Committed Spend (Projects!L) | F22: Approved Change Orders (Projects!N) | H22: Active Production Tasks (Projects!O)
B23: PROCUREMENT CATALOG ITEMS | D23: CRITICAL PATH MILESTONES | H23: SCHEDULE WORKBACK ENGINE
B24: =COUNTA('Procurement Catalog'!A2:A100) -> 1211 | D24: =COUNTIFS('Production Schedule'!$B:$B, C7, 'Production Schedule'!$R:$R, "Y") -> 20 | H24: =IF(ISBLANK(C9), "Anchor Date Required", "T-0 Locked: " & TEXT(C9, "yyyy-mm-dd") & " (" & IF(C9>TODAY(), "T-" & TEXT(C9-TODAY(), "#,##0") & " Days", IF(C9=TODAY(), "T-0 Live Today", "T+" & TEXT(TODAY()-C9, "#,##0") & " Days")) & ")") -> T-0 Locked: 2026-10-16 (T-8 Days)
B26: SYSTEM MODULE DIRECTORY & WORKBOOK NAVIGATION INDEX
B27: Functional Domain | C27: Primary Module | D27: Secondary Module | E27: Grain & Schema Scope | G27: Posture | H27: Governance & Classification
B28: Executive & Governance | C28: =HYPERLINK("#gid=1000100", "Projects") -> Projects | D28: =HYPERLINK("#gid=771928374", "Activity Log") -> Activity Log | E28: Master project portfolio, executive controls, governing gates & audit log | G28: Active Registry | H28: Executive Governance SSOT
B29: Production Planning & ROS | C29: =HYPERLINK("#gid=0", "Production Schedule") -> Production Schedule | D29: =HYPERLINK("#gid=7001030", "Run of Show") -> Run of Show | E29: 90 gated workback milestones, cue-by-cue run of show, tasks & work orders | G29: Dynamic Engine | H29: Production Operational SSOT
B30: Field Logistics & Assets | C30: =HYPERLINK("#gid=213042857", "Locations") -> Locations | D30: =HYPERLINK("#gid=300941203", "Shipping Manifest") -> Shipping Manifest | E30: Site locations, freight manifests, yard logs, advance hospitality & asset tracking | G30: Active Log | H30: Operational Field SSOT
B31: Workforce & Access | C31: =HYPERLINK("#gid=2117398587", "Personnel Roster") -> Personnel Roster | D31: =HYPERLINK("#gid=7001002", "Credential Issuance") -> Credential Issuance | E31: Staff roster, staffing requisitions, shift logs, rate cards & access grid | G31: Active Roster | H31: Workforce Governance
B32: Financial Controls & Commercial | C32: =HYPERLINK("#gid=900112244", "Budget Expenses") -> Budget Expenses | D32: =HYPERLINK("#gid=7001010", "Purchase Orders") -> Purchase Orders | E32: Cost center x GL x URID expenses, POs, change orders, procurement & vendors | G32: Active Ledger | H32: Fiscal Control Standard
B33: Safety & Compliance | C33: =HYPERLINK("#gid=7001001", "Inspection Compliance") -> Inspection Compliance | D33: =HYPERLINK("#gid=7001006", "Incident CAD Log") -> Incident CAD Log | E33: Agency safety inspections, incident CAD, emergency codes & comms channels | G33: Life Safety Standard | H33: Regulatory Compliance Standard
B34: Master Reference & Standards | C34: =HYPERLINK("#gid=8000101", "GL Accounts") -> GL Accounts | D34: =HYPERLINK("#gid=8000105", "Categories & URID Master") -> Categories & URID Master | E34: Chart of Accounts, 10 departments, 79 canon disciplines & matrix taxonomy | G34: Core Master | H34: Core Architecture Master

Sheet Projects
A1: PROJECT ID | B1: PROJECT NAME | C1: CLIENT NAME | D1: ORGANIZATION | E1: VENUE | F1: LOCATION | G1: START DATE | H1: END DATE | I1: ANCHOR DATE | J1: TIER | K1: BUDGET ENVELOPE | L1: COMMITTED AMOUNT | M1: ACTUAL SPEND | N1: APPROVED CHANGE ORDERS | O1: PRODUCTION TASKS | P1: OPERATIONAL STATE | Q1: GOVERNING GATE | R1: EXECUTIVE PRODUCER | S1: NOTES
A2: CSMIA26 | B2: Casa Spotify Miami | C2: Spotify | D2: GHXSTSHIP | E2: Mana Wynwood Convention Center & Grounds | F2: Miami, FL | G2: 2026-08-21 | H2: 2026-10-30 | I2: 2026-10-16 | J2: Tier 06 Theatrical | K2: 4500000 | L2: =SUMIFS('Budget Expenses'!$X:$X, 'Budget Expenses'!$B:$B, A2) -> 46600 | M2: =SUMIFS('Budget Expenses'!$Z:$Z, 'Budget Expenses'!$B:$B, A2) -> 0 | N2: =SUMIFS('Change Orders'!$M:$M, 'Change Orders'!$B:$B, A2, 'Change Orders'!$W:$W, "Approved") -> 1200 | O2: =COUNTIFS('Production Tasks'!$B:$B, A2, 'Production Tasks'!$V:$V, "Active") -> 3 | P2: Active | Q2: Gate 05 Build | R2: Julian Clarkson | S2: Art, Music & Technology Convergence in Wynwood; flagship production
A3: SXSW26 | B3: Spotify House Austin | C3: Spotify | D3: GHXSTSHIP | E3: Clive Bar & Rainey Footprint | F3: Austin, TX | G3: 2026-02-01 | H3: 2026-03-22 | I3: 2026-03-13 | J3: Tier 05 Experiential | K3: 2800000 | L3: =SUMIFS('Budget Expenses'!$X:$X, 'Budget Expenses'!$B:$B, A3) -> 0 | M3: =SUMIFS('Budget Expenses'!$Z:$Z, 'Budget Expenses'!$B:$B, A3) -> 0 | N3: =SUMIFS('Change Orders'!$M:$M, 'Change Orders'!$B:$B, A3, 'Change Orders'!$W:$W, "Approved") -> 0 | O3: =COUNTIFS('Production Tasks'!$B:$B, A3, 'Production Tasks'!$V:$V, "Active") -> 0 | P3: Complete | Q3: Gate 09 Close | R3: Julian Clarkson | S3: Interactive music showcase and brand activation; archived
A4: EDCLV26 | B4: Electric Daisy Carnival KineticFIELD | C4: Insomniac Events | D4: GHXSTSHIP | E4: Las Vegas Motor Speedway | F4: Las Vegas, NV | G4: 2026-04-10 | H4: 2026-05-25 | I4: 2026-05-15 | J4: Tier 06 Theatrical | K4: 6200000 | L4: =SUMIFS('Budget Expenses'!$X:$X, 'Budget Expenses'!$B:$B, A4) -> 0 | M4: =SUMIFS('Budget Expenses'!$Z:$Z, 'Budget Expenses'!$B:$B, A4) -> 0 | N4: =SUMIFS('Change Orders'!$M:$M, 'Change Orders'!$B:$B, A4, 'Change Orders'!$W:$W, "Approved") -> 0 | O4: =COUNTIFS('Production Tasks'!$B:$B, A4, 'Production Tasks'!$V:$V, "Active") -> 0 | P4: Complete | Q4: Gate 09 Close | R4: Tigre JC | S4: Mainstage scenic production, AVL engineering, and site ops
A5: ABMIA26 | B5: Art Basel Wynwood Experiential Pavilion | C5: Art Basel / UBS | D5: GHXSTSHIP | E5: Wynwood Arts District Pavilion | F5: Miami, FL | G5: 2026-10-01 | H5: 2026-12-10 | I5: 2026-12-03 | J5: Tier 05 Experiential | K5: 3400000 | L5: =SUMIFS('Budget Expenses'!$X:$X, 'Budget Expenses'!$B:$B, A5) -> 0 | M5: =SUMIFS('Budget Expenses'!$Z:$Z, 'Budget Expenses'!$B:$B, A5) -> 0 | N5: =SUMIFS('Change Orders'!$M:$M, 'Change Orders'!$B:$B, A5, 'Change Orders'!$W:$W, "Approved") -> 0 | O5: =COUNTIFS('Production Tasks'!$B:$B, A5, 'Production Tasks'!$V:$V, "Active") -> 0 | P5: Active | Q5: Gate 03 Advance | R5: Bex Izzy | S5: Immersive art installations, VIP hospitality lounge, and sensory exhibits
A6: NYFW26 | B6: NYFW Runway & Digital Immersion | C6: IMG Fashion | D6: GHXSTSHIP | E6: Spring Studios | F6: New York, NY | G6: 2026-11-15 | H6: 2027-02-20 | I6: 2027-02-11 | J6: Tier 06 Theatrical | K6: 3900000 | L6: =SUMIFS('Budget Expenses'!$X:$X, 'Budget Expenses'!$B:$B, A6) -> 0 | M6: =SUMIFS('Budget Expenses'!$Z:$Z, 'Budget Expenses'!$B:$B, A6) -> 0 | N6: =SUMIFS('Change Orders'!$M:$M, 'Change Orders'!$B:$B, A6, 'Change Orders'!$W:$W, "Approved") -> 0 | O6: =COUNTIFS('Production Tasks'!$B:$B, A6, 'Production Tasks'!$V:$V, "Active") -> 0 | P6: Scheduled | Q6: Gate 02 Engage | R6: Julian Clarkson | S6: High-concept fashion runway, broadcast capture, and digital streaming

Sheet Activity Log
A1: RECORD ID | B1: ORGANIZATION | C1: PROJECT | D1: DEPARTMENT | E1: CATEGORY | F1: SUB CATEGORY | G1: TIMESTAMP | H1: LOCATION / ZONE | I1: SUBJECT / ITEM | J1: DESCRIPTION | K1: PARTY INVOLVED | L1: QTY / VALUE | M1: PRIORITY | N1: LOGGED BY | O1: REFERENCE ID | P1: STATUS | Q1: FLAG | R1: NOTES | S1: CREATED BY | T1: CREATED AT | U1: UPDATED AT

Sheet Production Schedule
A1: ACTIVITY ID | B1: PROJECT ID | C1: PARENT ACTIVITY ID | D1: WBS CODE | E1: PHASE CODE | F1: PHASE | G1: ACT | H1: GATE | I1: ACTIVITY NAME | J1: ACTIVITY TYPE | K1: DELIVERABLE | L1: SOP ID | M1: OWNER ROLE | N1: PERSONNEL ID | O1: START DATE | P1: END DATE | Q1: DURATION (DAYS) | R1: CRITICAL PATH | S1: TOTAL TASKS | T1: COMPLETED TASKS | U1: PROGRESS (%) | V1: STATUS | W1: FLAG | X1: NOTES
A2: 0000-SCP-001 | B2: CSMIA26 | C2: G1-GATE-001 | D2: 1.1 | E2: SCP | F2: Scope | G2: PLAN | H2: 1 | I2: Approve event budget envelope and spend authority | J2: Summary Activity | K2: Event budget envelope memo | L2: SOP-022 | M2: TIGRE/JC | N2: P-021 | O2: 46255 | P2: 46268 | Q2: 14 | R2: Y | S2: =COUNTIF('Production Tasks'!$C$2:$C$25, A2) -> 2 | T2: =COUNTIFS('Production Tasks'!$C$2:$C$25, A2, 'Production Tasks'!$V$2:$V$25, "Complete") -> 2 | U2: =IF(S2>0, T2/S2, IF(V2="Complete", 1, 0)) -> 1 | V2: Complete | W2: FALSE | X2: Spend authority thresholds approved
A3: 1000-SCP-001 | B3: CSMIA26 | C3: G1-GATE-001 | D3: 1.2 | E3: SCP | F3: Scope | G3: PLAN | H3: 1 | I3: Define event creative concept & visual identity | J3: Summary Activity | K3: Creative brief & narrative deck | M3: BEX/IZZY | N3: P-006 | O3: 46255 | P3: 46268 | Q3: 14 | R3: Y | S3: =COUNTIF('Production Tasks'!$C$2:$C$25, A3) -> 1 | T3: =COUNTIFS('Production Tasks'!$C$2:$C$25, A3, 'Production Tasks'!$V$2:$V$25, "Complete") -> 1 | U3: =IF(S3>0, T3/S3, IF(V3="Complete", 1, 0)) -> 1 | V3: Complete | W3: FALSE | X3: Creative lock validated at Gate 1
A4: 2000-SCP-001 | B4: CSMIA26 | C4: G1-GATE-001 | D4: 1.3 | E4: SCP | F4: Scope | G4: PLAN | H4: 1 | I4: Lock talent lineup, set times & performance format | J4: Summary Activity | K4: Lineup curation memo | M4: IZZY | N4: P-005 | O4: 46255 | P4: 46268 | Q4: 14 | R4: Y | S4: =COUNTIF('Production Tasks'!$C$2:$C$25, A4) -> 0 | T4: =COUNTIFS('Production Tasks'!$C$2:$C$25, A4, 'Production Tasks'!$V$2:$V$25, "Complete") -> 0 | U4: =IF(S4>0, T4/S4, IF(V4="Complete", 1, 0)) -> 1 | V4: Complete | W4: FALSE | X4: Headliner and support roster locked
A5: G1-GATE-001 | B5: CSMIA26 | D5: 1 | E5: SCP | F5: Scope | G5: PLAN | H5: 1 | I5: Gate 1 Exit: Scope & Budget Lock Ratified | J5: Milestone Gate | K5: Gate 1 ratification memo | M5: TIGRE/JC | N5: P-021 | O5: 46268 | P5: 46268 | Q5: 0 | R5: Y | S5: =SUMIFS($S$2:$S$22, $C$2:$C$22, A5, $J$2:$J$22, "Summary Activity") -> 3 | T5: =SUMIFS($T$2:$T$22, $C$2:$C$22, A5, $J$2:$J$22, "Summary Activity") -> 3 | U5: =IF(S5>0, T5/S5, IF(V5="Complete", 1, 0)) -> 1 | V5: Complete | W5: FALSE | X5: Go/no-go milestone satisfied
A6: 0000-ENG-002 | B6: CSMIA26 | C6: G2-GATE-002 | D6: 2.1 | E6: ENG | F6: Engage | G6: PLAN | H6: 2 | I6: Execute master co-promoter & host agreements | J6: Summary Activity | K6: Executed co-promoter agreement | L6: SOP-022 | M6: JC/TIGRE | N6: P-021 | O6: 46269 | P6: 46282 | Q6: 14 | R6: Y | S6: =COUNTIF('Production Tasks'!$C$2:$C$25, A6) -> 2 | T6: =COUNTIFS('Production Tasks'!$C$2:$C$25, A6, 'Production Tasks'!$V$2:$V$25, "Complete") -> 2 | U6: =IF(S6>0, T6/S6, IF(V6="Complete", 1, 0)) -> 1 | V6: Complete | W6: FALSE | X6: Spotify and Tigre legal signoff complete
A7: 2000-ENG-002 | B7: CSMIA26 | C7: G2-GATE-002 | D7: 2.2 | E7: ENG | F7: Engage | G7: PLAN | H7: 2 | I7: Issue talent offers & execute performance contracts | J7: Summary Activity | K7: Executed talent contracts | L7: SOP-031 | M7: IZZY/TIGRE | N7: P-005 | O7: 46269 | P7: 46282 | Q7: 14 | R7: Y | S7: =COUNTIF('Production Tasks'!$C$2:$C$25, A7) -> 1 | T7: =COUNTIFS('Production Tasks'!$C$2:$C$25, A7, 'Production Tasks'!$V$2:$V$25, "Complete") -> 1 | U7: =IF(S7>0, T7/S7, IF(V7="Complete", 1, 0)) -> 1 | V7: Complete | W7: FALSE | X7: Deposit releases unblocked on execution
A8: G2-GATE-002 | B8: CSMIA26 | C8: G1-GATE-001 | D8: 2 | E8: ENG | F8: Engage | G8: PLAN | H8: 2 | I8: Gate 2 Exit: Contracting & Accountable Parties | J8: Milestone Gate | K8: Contract execution binder | L8: SOP-022 | M8: TIGRE/JC | N8: P-001 | O8: 46282 | P8: 46282 | Q8: 0 | R8: Y | S8: =SUMIFS($S$2:$S$22, $C$2:$C$22, A8, $J$2:$J$22, "Summary Activity") -> 3 | T8: =SUMIFS($T$2:$T$22, $C$2:$C$22, A8, $J$2:$J$22, "Summary Activity") -> 3 | U8: =IF(S8>0, T8/S8, IF(V8="Complete", 1, 0)) -> 1 | V8: Complete | W8: FALSE | X8: Zero unassigned scope requirements
A9: 0000-ADV-003 | B9: CSMIA26 | C9: G3-GATE-003 | D9: 3.1 | E9: ADV | F9: Advance | G9: PLAN | H9: 3 | I9: Confirm event certificates of insurance & endorsements | J9: Summary Activity | K9: Event COI binder | L9: SOP-022 | M9: TIGRE | N9: P-001 | O9: 46283 | P9: 46289 | Q9: 7 | R9: Y | S9: =COUNTIF('Production Tasks'!$C$2:$C$25, A9) -> 1 | T9: =COUNTIFS('Production Tasks'!$C$2:$C$25, A9, 'Production Tasks'!$V$2:$V$25, "Complete") -> 1 | U9: =IF(S9>0, T9/S9, IF(V9="Complete", 1, 0)) -> 1 | V9: Complete | W9: FALSE | X9: GL & liquor liability additional insureds on file
A10: 3000-ADV-003 | B10: CSMIA26 | C10: G3-GATE-003 | D10: 3.2 | E10: ADV | F10: Advance | G10: PLAN | H10: 3 | I10: Launch RSVP platform, ticketing tiers & invite list | J10: Summary Activity | K10: Live RSVP system | L10: SOP-028 | M10: JC/BEX | N10: P-006 | O10: 46283 | P10: 46289 | Q10: 7 | R10: Y | S10: =COUNTIF('Production Tasks'!$C$2:$C$25, A10) -> 1 | T10: =COUNTIFS('Production Tasks'!$C$2:$C$25, A10, 'Production Tasks'!$V$2:$V$25, "Complete") -> 1 | U10: =IF(S10>0, T10/S10, IF(V10="Complete", 1, 0)) -> 1 | V10: Complete | W10: FALSE | X10: Guest allocations verified
A11: G3-GATE-003 | B11: CSMIA26 | C11: G2-GATE-002 | D11: 3 | E11: ADV | F11: Advance | G11: PLAN | H11: 3 | I11: Gate 3 Exit: Advance & Baseline PO Lock | J11: Milestone Gate | K11: PO baseline register | M11: JC | N11: P-021 | O11: 46289 | P11: 46289 | Q11: 0 | R11: Y | S11: =SUMIFS($S$2:$S$22, $C$2:$C$22, A11, $J$2:$J$22, "Summary Activity") -> 2 | T11: =SUMIFS($T$2:$T$22, $C$2:$C$22, A11, $J$2:$J$22, "Summary Activity") -> 2 | U11: =IF(S11>0, T11/S11, IF(V11="Complete", 1, 0)) -> 1 | V11: Complete | W11: FALSE | X11: Permits filed; rigging verified
A12: 4000-PRC-004 | B12: CSMIA26 | C12: G4-GATE-004 | D12: 4.1 | E12: PRC | F12: Procure | G12: BUILD | H12: 4 | I12: Issue purchase orders for scenic, millwork & FF&E | J12: Summary Activity | K12: Fabrication purchase orders | L12: SOP-009 | M12: SMC/JC | N12: P-021 | O12: 46290 | P12: 46296 | Q12: 7 | R12: Y | S12: =COUNTIF('Production Tasks'!$C$2:$C$25, A12) -> 2 | T12: =COUNTIFS('Production Tasks'!$C$2:$C$25, A12, 'Production Tasks'!$V$2:$V$25, "Complete") -> 2 | U12: =IF(S12>0, T12/S12, IF(V12="Complete", 1, 0)) -> 1 | V12: Complete | W12: FALSE | X12: 3-week fabrication lead time lock
A13: G4-GATE-004 | B13: CSMIA26 | C13: G3-GATE-003 | D13: 4 | E13: PRC | F13: Procure | G13: BUILD | H13: 4 | I13: Gate 4 Exit: All Awards & Deposits Released | J13: Milestone Gate | K13: Deposit disbursements confirmation | M13: TIGRE | N13: P-001 | O13: 46296 | P13: 46296 | Q13: 0 | R13: Y | S13: =SUMIFS($S$2:$S$22, $C$2:$C$22, A13, $J$2:$J$22, "Summary Activity") -> 2 | T13: =SUMIFS($T$2:$T$22, $C$2:$C$22, A13, $J$2:$J$22, "Summary Activity") -> 2 | U13: =IF(S13>0, T13/S13, IF(V13="Complete", 1, 0)) -> 1 | V13: Complete | W13: FALSE | X13: All vendor awards issued
A14: 4000-BLD-005 | B14: CSMIA26 | C14: G5-GATE-005 | D14: 5.1 | E14: BLD | F14: Build | G14: BUILD | H14: 5 | I14: Pre-assemble modular bar wraps, DJ altar & lounge scenic | J14: Summary Activity | K14: Prefabricated components | L14: SOP-009 | M14: VENDOR/SMC | N14: P-021 | O14: 46297 | P14: 46306 | Q14: 10 | R14: Y | S14: =COUNTIF('Production Tasks'!$C$2:$C$25, A14) -> 2 | T14: =COUNTIFS('Production Tasks'!$C$2:$C$25, A14, 'Production Tasks'!$V$2:$V$25, "Complete") -> 0 | U14: =IF(S14>0, T14/S14, IF(V14="Complete", 1, 0)) -> 0 | V14: Active | W14: FALSE | X14: Shop prep and finishing off-site
A15: 5000-BLD-005 | B15: CSMIA26 | C15: G5-GATE-005 | D15: 5.2 | E15: BLD | F15: Build | G15: BUILD | H15: 5 | I15: Build stage decks, erect truss towers & hang line arrays | J15: Summary Activity | K15: Staging & truss structure | L15: SOP-001 | M15: VENDOR/JC | N15: P-021 | O15: 46297 | P15: 46306 | Q15: 10 | R15: Y | S15: =COUNTIF('Production Tasks'!$C$2:$C$25, A15) -> 2 | T15: =COUNTIFS('Production Tasks'!$C$2:$C$25, A15, 'Production Tasks'!$V$2:$V$25, "Complete") -> 1 | U15: =IF(S15>0, T15/S15, IF(V15="Complete", 1, 0)) -> 0.5 | V15: Active | W15: FALSE | X15: Rigging certification stamped
A16: G5-GATE-005 | B16: CSMIA26 | C16: G4-GATE-004 | D16: 5 | E16: BLD | F16: Build | G16: BUILD | H16: 5 | I16: Gate 5 Exit: Fabrication & Shop QC Pass | J16: Milestone Gate | K16: Shop QC signoff memo | L16: SOP-001 | M16: JC | N16: P-021 | O16: 46306 | P16: 46306 | Q16: 0 | R16: Y | S16: =SUMIFS($S$2:$S$22, $C$2:$C$22, A16, $J$2:$J$22, "Summary Activity") -> 4 | T16: =SUMIFS($T$2:$T$22, $C$2:$C$22, A16, $J$2:$J$22, "Summary Activity") -> 1 | U16: =IF(S16>0, T16/S16, IF(V16="Complete", 1, 0)) -> 0.25 | V16: Active | W16: FALSE | X16: Load-in dispatch unblocked
A17: 5000-INS-006 | B17: CSMIA26 | C17: G6-GATE-006 | D17: 6.1 | E17: INS | F17: Install | G17: BUILD | H17: 6 | I17: Connect power distro, commission audio & lighting timecode | J17: Summary Activity | K17: Commissioned AVL production rig | L17: SOP-002 | M17: JC | N17: P-021 | O17: 46307 | P17: 46310 | Q17: 4 | R17: Y | S17: =COUNTIF('Production Tasks'!$C$2:$C$25, A17) -> 2 | T17: =COUNTIFS('Production Tasks'!$C$2:$C$25, A17, 'Production Tasks'!$V$2:$V$25, "Complete") -> 0 | U17: =IF(S17>0, T17/S17, IF(V17="Complete", 1, 0)) -> 0 | V17: Scheduled | W17: FALSE | X17: Soundcheck & decibel compliance validated
A18: 6000-INS-006 | B18: CSMIA26 | C18: G6-GATE-006 | D18: 6.2 | E18: INS | F18: Install | G18: BUILD | H18: 6 | I18: Conduct safety & egress inspection with City of Miami Fire | J18: Summary Activity | K18: Fire Marshal inspection signoff | L18: SOP-005 | M18: JC/TIGRE | N18: P-021 | O18: 46307 | P18: 46310 | Q18: 4 | R18: Y | S18: =COUNTIF('Production Tasks'!$C$2:$C$25, A18) -> 2 | T18: =COUNTIFS('Production Tasks'!$C$2:$C$25, A18, 'Production Tasks'!$V$2:$V$25, "Complete") -> 0 | U18: =IF(S18>0, T18/S18, IF(V18="Complete", 1, 0)) -> 0 | V18: Scheduled | W18: FALSE | X18: Assembly occupancy permit granted
A19: G6-GATE-006 | B19: CSMIA26 | C19: G5-GATE-005 | D19: 6 | E19: INS | F19: Install | G19: BUILD | H19: 6 | I19: Gate 6 Exit: Operational Readiness Signoff | J19: Milestone Gate | K19: Readiness signoff memo | L19: SOP-004 | M19: JC/SPOTIFY | N19: P-021 | O19: 46310 | P19: 46310 | Q19: 0 | R19: Y | S19: =SUMIFS($S$2:$S$22, $C$2:$C$22, A19, $J$2:$J$22, "Summary Activity") -> 4 | T19: =SUMIFS($T$2:$T$22, $C$2:$C$22, A19, $J$2:$J$22, "Summary Activity") -> 0 | U19: =IF(S19>0, T19/S19, IF(V19="Complete", 1, 0)) -> 0 | V19: Scheduled | W19: FALSE | X19: Final go/no-go gate exit satisfied
A20: 7000-OPR-007 | B20: CSMIA26 | C20: G7-GATE-007 | D20: 7.1 | E20: OPR | F20: Operate | G20: SHOW | H20: 7 | I20: Host guest check-in, VIP activations & show live operations | J20: Summary Activity | K20: Incident log & daily ops report | L20: SOP-006 | M20: BEX/JC | N20: P-006 | O20: 46311 | P20: 46311 | Q20: 1 | R20: Y | S20: =COUNTIF('Production Tasks'!$C$2:$C$25, A20) -> 2 | T20: =COUNTIFS('Production Tasks'!$C$2:$C$25, A20, 'Production Tasks'!$V$2:$V$25, "Complete") -> 0 | U20: =IF(S20>0, T20/S20, IF(V20="Complete", 1, 0)) -> 0 | V20: Ready | W20: FALSE | X20: Doors open at 19:00 EDT
A21: 9000-AMP-008 | B21: CSMIA26 | C21: G7-GATE-007 | D21: 8.1 | E21: AMP | F21: Amplify | G21: SHOW | H21: 8 | I21: Broadcast distribution, media recap & footfall analytics | J21: Summary Activity | K21: Event data & analytics recap | L21: SOP-007 | M21: JC/BEX | N21: P-021 | O21: 46312 | P21: 46318 | Q21: 7 | R21: N | S21: =COUNTIF('Production Tasks'!$C$2:$C$25, A21) -> 2 | T21: =COUNTIFS('Production Tasks'!$C$2:$C$25, A21, 'Production Tasks'!$V$2:$V$25, "Complete") -> 0 | U21: =IF(S21>0, T21/S21, IF(V21="Complete", 1, 0)) -> 0 | V21: Ready | W21: FALSE | X21: Audience dwell & stream peak concurrents
A22: 0000-CLS-009 | B22: CSMIA26 | C22: G7-GATE-007 | D22: 9.1 | E22: CLS | F22: Close | G22: SHOW | H22: 9 | I22: Complete production strike, final ledger & closeouts | J22: Summary Activity | K22: Final financial cost report | L22: SOP-008 | M22: JC/TIGRE | N22: P-021 | O22: 46319 | P22: 46325 | Q22: 7 | R22: Y | S22: =COUNTIF('Production Tasks'!$C$2:$C$25, A22) -> 2 | T22: =COUNTIFS('Production Tasks'!$C$2:$C$25, A22, 'Production Tasks'!$V$2:$V$25, "Complete") -> 0 | U22: =IF(S22>0, T22/S22, IF(V22="Complete", 1, 0)) -> 0 | V22: Ready | W22: FALSE | X22: Reconciliation against Gate 3 baseline

Sheet Production Tasks
A1: TASK ID | B1: PROJECT ID | C1: ACTIVITY ID | D1: WBS CODE | E1: TASK NAME | F1: DESCRIPTION | G1: RECORD KIND | H1: RECORD SUBTYPE | I1: TEAM CODE | J1: LOCATION ID | K1: PERSONNEL ID | L1: ASSIGNEE NAME | M1: START DATE | N1: END DATE | O1: DURATION (DAYS) | P1: PREDECESSORS | Q1: PRIORITY | R1: DELIVERABLE | S1: LINKED WORK ORDER ID | T1: SOP ID | U1: PROGRESS (%) | V1: STATUS | W1: FLAG | X1: NOTES
A2: TSK-001 | B2: CSMIA26 | C2: 0000-SCP-001 | D2: 1.1.1 | E2: Draft spend envelope and authority matrix | F2: Define baseline budget limits and executive delegation of authority | G2: Task | H2: Define | I2: 0000-T01 | J2: LOC-03 | K2: P-021 | L2: Julian Clarkson | M2: 46255 | N2: 46261 | O2: 7 | Q2: Critical | R2: Approved spend thresholds memo | T2: SOP-022 | U2: 1 | V2: Complete | W2: FALSE | X2: Governed by SOP-022; Board envelope threshold sign-off
A3: TSK-002 | B3: CSMIA26 | C3: 0000-SCP-001 | D3: 1.1.2 | E3: Establish WBS chart of accounts mapping | F3: Align project expense items to master GL accounts and cost centers | G3: Task | H3: Coordinate | I3: 0000-T02 | J3: LOC-03 | K3: P-021 | L3: Julian Clarkson | M3: 46262 | N3: 46268 | O3: 7 | P3: TSK-001 | Q3: High | R3: Chart of accounts ledger map | U3: 1 | V3: Complete | W3: FALSE | X3: Reconciled with CC-VENUE and CC-CORP
A4: TSK-003 | B4: CSMIA26 | C4: 0000-ENG-002 | D4: 1.2.1 | E4: Negotiate co-promoter master agreement | F4: Finalize legal terms and liability provisions with co-promoter | G4: Task | H4: Coordinate | I4: 0000-T04 | J4: LOC-03 | K4: P-001 | L4: Ashley Sumner | M4: 46269 | N4: 46275 | O4: 7 | P4: TSK-002 | Q4: Critical | R4: Executed co-promoter contract | T4: SOP-031 | U4: 1 | V4: Complete | W4: FALSE | X4: Governed by SOP-031; Spotify and Tigre legal review
A5: TSK-004 | B5: CSMIA26 | C5: 0000-ENG-002 | D5: 1.2.2 | E5: Issue venue license and occupancy agreement | F5: Finalize primary site lease terms and indemnification clauses | G5: Task | H5: Execute | I5: 0000-T04 | J5: LOC-03 | K5: P-001 | L5: Ashley Sumner | M5: 46276 | N5: 46282 | O5: 7 | P5: TSK-003 | Q5: High | R5: Countersigned venue agreement | T5: SOP-034 | U5: 1 | V5: Complete | W5: FALSE | X5: Governed by SOP-034; Premises occupancy rider verified
A6: TSK-005 | B6: CSMIA26 | C6: 0000-ADV-003 | D6: 1.3.1 | E6: Bind general liability and excess umbrella policy | F6: Secure certificate of insurance with additional insured endorsements | G6: Task | H6: Verify | I6: 0000-T03 | J6: LOC-03 | K6: P-001 | L6: Ashley Sumner | M6: 46283 | N6: 46289 | O6: 7 | P6: TSK-004 | Q6: Critical | R6: Certificate of Insurance binder | T6: SOP-022 | U6: 1 | V6: Complete | W6: FALSE | X6: Governed by SOP-022; $5M aggregate limit compliance
A7: TSK-006 | B7: CSMIA26 | C7: 1000-SCP-001 | D7: 2.1.1 | E7: Publish creative identity guidelines and mood boards | F7: Establish color system, typographic hierarchy, and environmental guidelines | G7: Task | H7: Produce | I7: 1000-T01 | J7: LOC-03 | K7: P-006 | L7: Rebecca Bex | M7: 46255 | N7: 46268 | O7: 14 | Q7: High | R7: Visual identity brief deck | U7: 1 | V7: Complete | W7: FALSE | X7: Wynwood aesthetic alignment
A8: TSK-007 | B8: CSMIA26 | C8: 2000-ENG-002 | D8: 2.2.1 | E8: Issue artist offers and confirm headline performance | F8: Finalize talent deal memos, hospitality riders, and deposit schedules | G8: Task | H8: Execute | I8: 2000-T03 | J8: LOC-06 | K8: P-005 | L8: Isabella Acker | M8: 46269 | N8: 46282 | O8: 14 | P8: TSK-006 | Q8: Critical | R8: Executed artist performance contracts | T8: SOP-031 | U8: 1 | V8: Complete | W8: FALSE | X8: Governed by SOP-031; 50% deposit release authorized
A9: TSK-008 | B9: CSMIA26 | C9: 3000-ADV-003 | D9: 2.3.1 | E9: Deploy ticketing tiers and influencer RSVP portal | F9: Set up guest registration portal, VIP allocations, and tier validation | G9: Task | H9: Systems | I9: 3000-T01 | J9: LOC-03 | K9: P-006 | L9: Rebecca Bex | M9: 46283 | N9: 46289 | O9: 7 | P9: TSK-007 | Q9: High | R9: Live RSVP ticketing engine | T9: SOP-028 | U9: 1 | V9: Complete | W9: FALSE | X9: Governed by SOP-028; Capacity caps keyed to venue limits
A10: TSK-009 | B10: CSMIA26 | C10: 4000-PRC-004 | D10: 3.1.1 | E10: Order modular scenic wall panels and graphic skins | F10: Transmit fabrication specifications for stage backdrops and partitions | G10: Build | H10: Scenic | I10: 4000-T03 | J10: LOC-16 | K10: P-021 | L10: Julian Clarkson | M10: 46290 | N10: 46296 | O10: 7 | P10: TSK-008 | Q10: High | R10: Scenic fabrication purchase orders | S10: WO-002 | T10: SOP-009 | U10: 1 | V10: Complete | W10: FALSE | X10: Governed by SOP-009; Material flame-spread certification verified
A11: TSK-010 | B11: CSMIA26 | C11: 4000-PRC-004 | D11: 3.1.2 | E11: Contract FF&E lounge furniture and patio shade fixtures | F11: Procure designer sectionals, cocktail tables, and outdoor canopy hardware | G11: Task | H11: Coordinate | I11: 4000-T06 | J11: LOC-06 | K11: P-021 | L11: Julian Clarkson | M11: 46290 | N11: 46296 | O11: 7 | P11: TSK-009 | Q11: Medium | R11: FF&E vendor dispatch schedule | T11: SOP-009 | U11: 1 | V11: Complete | W11: FALSE | X11: Governed by SOP-009; Coordinated with SMC design specs
A12: TSK-011 | B12: CSMIA26 | C12: 4000-BLD-005 | D12: 3.2.1 | E12: Off-site fabrication of modular bar facades and DJ altar | F12: Millwork assembly, paint finishing, and edge LED channel integration | G12: Build | H12: Scenic | I12: 4000-T03 | J12: LOC-22 | K12: P-021 | L12: Julian Clarkson | M12: 46297 | N12: 46303 | O12: 7 | P12: TSK-010 | Q12: High | R12: Completed modular bar components | S12: WO-002 | T12: SOP-009 | U12: 0.8 | V12: Active | W12: FALSE | X12: Governed by SOP-009; Shop QC passed; awaiting load-in dispatch
A13: TSK-012 | B13: CSMIA26 | C13: 4000-BLD-005 | D13: 3.2.2 | E13: Pre-assemble neon signage frames and backdrop mounts | F13: Wire low-voltage transformers and test illuminated neon phrase fixtures | G13: Build | H13: Systems | I13: 4000-T07 | J13: LOC-16 | K13: P-006 | L13: Rebecca Bex | M13: 46301 | N13: 46306 | O13: 6 | P13: TSK-011 | Q13: Medium | R13: Pre-tested neon display assemblies | T13: SOP-002 | U13: 0.6 | V13: Active | W13: FALSE | X13: Governed by SOP-002; Exhibition room feature installation
A14: TSK-013 | B14: CSMIA26 | C14: 5000-BLD-005 | D14: 3.3.1 | E14: Erect stage decking and ground-support truss towers | F14: Assemble 4x8 decks with guardrails, ballast plates, and vertical motor masts | G14: Build | H14: Structural | I14: 5000-T05 | J14: LOC-01 | K14: P-021 | L14: Julian Clarkson | M14: 46297 | N14: 46301 | O14: 5 | P14: TSK-010 | Q14: Critical | R14: Structural stage and truss signoff | S14: WO-002 | T14: SOP-001 | U14: 1 | V14: Complete | W14: FALSE | X14: Governed by SOP-001; Rigging cert stamped by structural engineer
A15: TSK-014 | B15: CSMIA26 | C15: 5000-BLD-005 | D15: 3.3.2 | E15: Hang line array audio clusters and cardioid subwoofers | F15: Fly primary PA hangs, connect speaker multicores, and align front fills | G15: Build | H15: Systems | I15: 5000-T01 | J15: LOC-01 | K15: P-024 | L15: David Miller | M15: 46302 | N15: 46306 | O15: 5 | P15: TSK-013 | Q15: High | R15: Flown audio rig ready for tuning | S15: WO-001 | T15: SOP-001 | U15: 0.75 | V15: Active | W15: FALSE | X15: Governed by SOP-001; David Miller leading A1 hang
A16: TSK-015 | B16: CSMIA26 | C16: 5000-INS-006 | D16: 3.4.1 | E16: Connect temporary generator power distro and branch circuits | F16: Tie in primary 200A distro panels, test grounding, and balance phase loads | G16: Build | H16: Systems | I16: 5000-T04 | J16: LOC-01 | K16: P-021 | L16: Julian Clarkson | M16: 46307 | N16: 46308 | O16: 2 | P16: TSK-014 | Q16: Critical | R16: Certified power distribution network | S16: WO-001 | T16: SOP-002 | U16: 0 | V16: Scheduled | W16: FALSE | X16: Governed by SOP-002; Master electrician inspection prerequisite
A17: TSK-016 | B17: CSMIA26 | C17: 5000-INS-006 | D17: 3.4.2 | E17: Tune acoustic room curves and program lighting timecode | F17: Execute pink noise room alignment, timecode sync tests, and mover fixture presets | G17: Build | H17: Commissioning | I17: 5000-T01 | J17: LOC-01 | K17: P-024 | L17: David Miller | M17: 46309 | N17: 46310 | O17: 2 | P17: TSK-015 | Q17: High | R17: Commissioned AVL production system | S17: WO-001 | T17: SOP-003 | U17: 0 | V17: Scheduled | W17: FALSE | X17: Governed by SOP-003; Decibel limits validated for City of Miami noise variance
A18: TSK-017 | B18: CSMIA26 | C18: 6000-INS-006 | D18: 3.5.1 | E18: Conduct municipal life safety and fire marshal walkthrough | F18: Inspect egress corridors, fire extinguishers, panic hardware, and crowd barricades | G18: Inspection | H18: Safety | I18: 6000-T03 | J18: LOC-17 | K18: P-021 | L18: Julian Clarkson | M18: 46309 | N18: 46310 | O18: 2 | P18: TSK-016 | Q18: Critical | R18: Fire Marshal assembly occupancy permit | T18: SOP-005 | U18: 0 | V18: Scheduled | W18: FALSE | X18: Governed by SOP-005; AHJ signoff required prior to public doors
A19: TSK-018 | B19: CSMIA26 | C19: 6000-INS-006 | D19: 3.5.2 | E19: Brief security detail, crowd managers, and medical staff | F19: Review radio protocol, emergency evacuation routes, and threat escalation procedures | G19: Task | H19: Coordinate | I19: 6000-T05 | J19: LOC-03 | K19: P-016 | L19: Mary Christianson | M19: 46310 | N19: 46310 | O19: 1 | P19: TSK-017 | Q19: High | R19: Security deployment roster & sign-in | T19: SOP-004 | U19: 0 | V19: Scheduled | W19: FALSE | X19: Governed by SOP-004; City of Miami PD off-duty coordination
A20: TSK-019 | B20: CSMIA26 | C20: 7000-OPR-007 | D20: 4.1.1 | E20: Manage guest check-in, VIP wristbands, and credential scanning | F20: Operate front-of-house arrival portal, ticket scanners, and swag gift distribution | G20: Shift | H20: Show | I20: 7000-T03 | J20: LOC-02 | K20: P-006 | L20: Rebecca Bex | M20: 46311 | N20: 46311 | O20: 1 | P20: TSK-018 | Q20: High | R20: Guest entry log & scan counts | T20: SOP-028 | U20: 0 | V20: Ready | W20: FALSE | X20: Governed by SOP-028; Continuous sync with live attendance dashboard
A21: TSK-020 | B21: CSMIA26 | C21: 7000-OPR-007 | D21: 4.1.2 | E21: Direct main stage live performance and DJ show calling | F21: Coordinate stage management, cue lights, lighting presets, and talent changeovers | G21: Shift | H21: Show | I21: 2000-T01 | J21: LOC-01 | K21: P-021 | L21: Julian Clarkson | M21: 46311 | N21: 46311 | O21: 1 | P21: TSK-016 | Q21: Critical | R21: Flawless live show execution | T21: SOP-006 | U21: 0 | V21: Ready | W21: FALSE | X21: Governed by SOP-006; Run of show cues strictly maintained
A22: TSK-021 | B22: CSMIA26 | C22: 9000-AMP-008 | D22: 4.2.1 | E22: Ingest live multicam footage and encode press social reels | F22: Edit same-day highlights, color grade clips, and push media assets to PR distribution | G22: Task | H22: Produce | I22: 3000-T02 | J22: LOC-03 | K22: P-006 | L22: Rebecca Bex | M22: 46312 | N22: 46315 | O22: 4 | P22: TSK-020 | Q22: High | R22: Post-event media highlight reel | T22: SOP-007 | U22: 0 | V22: Ready | W22: FALSE | X22: Governed by SOP-007; Cleared usage rights on all tracks
A23: TSK-022 | B23: CSMIA26 | C23: 9000-AMP-008 | D23: 4.2.2 | E23: Aggregate attendance footfall and stream viewer analytics | F23: Compile RFID scan metrics, dwell heatmap reports, and social impression tallies | G23: Task | H23: Produce | I23: 9000-T04 | J23: LOC-03 | K23: P-021 | L23: Julian Clarkson | M23: 46312 | N23: 46318 | O23: 7 | P23: TSK-021 | Q23: Medium | R23: Analytics & ROI recap report | T23: SOP-028 | U23: 0 | V23: Ready | W23: FALSE | X23: Governed by SOP-028; Measures against Gate 1 KPI targets
A24: TSK-023 | B24: CSMIA26 | C24: 0000-CLS-009 | D24: 4.3.1 | E24: Strike production rigging and return equipment rentals | F24: De-rig line arrays, pack truss, disassemble staging, and load out carrier trucks | G24: Strike | H24: Show Strike | I24: 5000-T05 | J24: LOC-01 | K24: P-021 | L24: Julian Clarkson | M24: 46312 | N24: 46315 | O24: 4 | P24: TSK-020 | Q24: High | R24: Rental equipment return manifests | S24: WO-002 | T24: SOP-008 | U24: 0 | V24: Ready | W24: FALSE | X24: Governed by SOP-008; Zero damage disposition signoff
A25: TSK-024 | B25: CSMIA26 | C25: 0000-CLS-009 | D25: 4.3.2 | E25: Execute post-event financial settlement and bond releases | F25: Reconcile PO actuals against budget baseline and secure municipal deposit returns | G25: Task | H25: Verify | I25: 0000-T02 | J25: LOC-03 | K25: P-001 | L25: Ashley Sumner | M25: 46319 | N25: 46325 | O25: 7 | P25: TSK-023 | Q25: High | R25: Final financial reconciliation ledger | T25: SOP-034 | U25: 0 | V25: Ready | W25: FALSE | X25: Governed by SOP-034; Closeout signoff by Executive Producer

Sheet Work Orders
A1: RECORD ID | B1: PROJECT ID | C1: DEPARTMENT | D1: CATEGORY | E1: SUB CATEGORY | F1: WORK ORDER TYPE | G1: PRIORITY | H1: LOCATION ID | I1: LOCATION NAME | J1: ITEM ID | K1: TEAM CODE | L1: PERSONNEL ID | M1: LEAD ASSIGNEE NAME | N1: TASK TITLE | O1: DESCRIPTION | P1: SCOPE OF WORK | Q1: SCHEDULED START DATE | R1: SCHEDULED END DATE | S1: ACTUAL START DATE | T1: ACTUAL END DATE | U1: ESTIMATED HOURS | V1: ACTUAL HOURS | W1: LABOR RATE | X1: TOTAL LABOR COST | Y1: SAFETY HAZARD LEVEL | Z1: COMPLETION PERCENTAGE | AA1: STATUS | AB1: FLAG | AC1: RESOLUTION NOTES | AD1: NOTES | AE1: CREATED BY | AF1: CREATED AT | AG1: UPDATED AT
A2: WO-001 | B2: ='Cover Page'!$C$7 -> CSMIA26 | C2: 5000 Production | D2: 5000.01 Audio | E2: Audio Infrastructure | F2: AVL Installation | G2: Critical | H2: LOC-01 | I2: {=IF(ISBLANK(H2), "", _xlfn.XLOOKUP(H2, Locations!$A$2:$A100, Locations!$F$2:$F100, ""))} -> Zone B - Main Stage | J2: 5000.01.02-XPMS-004 | K2: 5000-T01 | L2: P-024 | M2: {=IF(ISBLANK(L2), "", TRIM(_xlfn.XLOOKUP(L2, 'Personnel Roster'!$A$2:$A100, 'Personnel Roster'!$D$2:$D100, "") & " " & _xlfn.XLOOKUP(L2, 'Personnel Roster'!$A$2:$A100, 'Personnel Roster'!$E$2:$E100, "")))} -> David Miller | N2: Main PA Line Array Hang and Calibration | O2: Install and tune main FOH line array system | P2: Acoustic sweep, time alignment, and safety cable inspection | Q2: 46310 | R2: 46311 | S2: 46310 | T2: 46311 | U2: 16 | V2: 14.5 | W2: 75 | X2: =V2*W2 -> 1087.5 | Y2: Medium | Z2: 1 | AA2: Completed | AB2: FALSE | AC2: System calibrated to 102 dBA target | AD2: Signed off by Technical Production Manager | AE2: Julian Clarkson | AF2: 46296 | AG2: 46311
A3: WO-002 | B3: ='Cover Page'!$C$7 -> CSMIA26 | C3: 4000 Environment | D3: 4000.01 Construction & Carpentry | E3: General Tools & Hardware | F3: Facility Setup | G3: High | H3: LOC-01 | I3: {=IF(ISBLANK(H3), "", _xlfn.XLOOKUP(H3, Locations!$A$2:$A100, Locations!$F$2:$F100, ""))} -> Zone B - Main Stage | J3: 4000.08.01-XPMS-001 | K3: 4000-T04 | L3: P-021 | M3: {=IF(ISBLANK(L3), "", TRIM(_xlfn.XLOOKUP(L3, 'Personnel Roster'!$A$2:$A100, 'Personnel Roster'!$D$2:$D100, "") & " " & _xlfn.XLOOKUP(L3, 'Personnel Roster'!$A$2:$A100, 'Personnel Roster'!$E$2:$E100, "")))} -> Julian Clarkson | N3: Stage Decks and Barricade Erection | O3: Assemble 4x8 modular stage decking and Mojo safety barricade | P3: Leveling, clamp torquing, and stage skirt attachment | Q3: 46313 | R3: 46314 | S3: 46313 | T3: 46314 | U3: 24 | V3: 22 | W3: 65 | X3: =V3*W3 -> 1430 | Y3: High | Z3: 1 | AA3: Completed | AB3: FALSE | AC3: Structural stability certified | AD3: Stagehand union crew utilized | AE3: Julian Clarkson | AF3: 46300 | AG3: 46314
A4: WO-003 | B4: ='Cover Page'!$C$7 -> CSMIA26 | C4: 9000 Technology | D4: 9000.52 Venue IT | E4: Network Provision | F4: Network Deployment | G4: High | H4: LOC-03 | I4: {=IF(ISBLANK(H4), "", _xlfn.XLOOKUP(H4, Locations!$A$2:$A100, Locations!$F$2:$F100, ""))} -> Production Office / Quartermaster | J4: 9000.01.01-XPMS-005 | K4: 9000-T06 | L4: P-021 | M4: {=IF(ISBLANK(L4), "", TRIM(_xlfn.XLOOKUP(L4, 'Personnel Roster'!$A$2:$A100, 'Personnel Roster'!$D$2:$D100, "") & " " & _xlfn.XLOOKUP(L4, 'Personnel Roster'!$A$2:$A100, 'Personnel Roster'!$E$2:$E100, "")))} -> Julian Clarkson | N4: Production Network VLAN Configuration | O4: Configure segregated VLANs for guest WiFi and broadcast telemetry | P4: Fiber patch to switches, router config, and bandwidth test | Q4: 46315 | R4: 46316 | S4: 46315 | T4: 46316 | U4: 12 | V4: 11.5 | W4: 85 | X4: =V4*W4 -> 977.5 | Y4: Low | Z4: 1 | AA4: Completed | AB4: FALSE | AC4: Network throughput validated at 1 Gbps | AD4: Tested with Toast POS hardware | AE4: Julian Clarkson | AF4: 46305 | AG4: 46316
A5: WO-004 | B5: ='Cover Page'!$C$7 -> CSMIA26 | C5: 6000 Operations | D5: 6000.04 Security & Access Control | E5: Security & Access Control | F5: Security Commissioning | G5: Medium | H5: LOC-08 | I5: {=IF(ISBLANK(H5), "", _xlfn.XLOOKUP(H5, Locations!$A$2:$A100, Locations!$F$2:$F100, ""))} -> Gate 2 - South Gate | J5: 9000.04.01-XPMS-002 | K5: 6000-T07 | L5: P-016 | M5: {=IF(ISBLANK(L5), "", TRIM(_xlfn.XLOOKUP(L5, 'Personnel Roster'!$A$2:$A100, 'Personnel Roster'!$D$2:$D100, "") & " " & _xlfn.XLOOKUP(L5, 'Personnel Roster'!$A$2:$A100, 'Personnel Roster'!$E$2:$E100, "")))} -> Mary Christianson | N5: Access Control and Magnetometer Deployment | O5: Install walk-through metal detectors and set ingress gates | P5: Power tie-in, sensitivity calibration, and barrier alignment | Q5: 46317 | R5: 46318 | S5: 46317 | U5: 10 | V5: 6 | W5: 55 | X5: =V5*W5 -> 330 | Y5: Medium | Z5: 0.6 | AA5: In Progress | AB5: FALSE | AC5: Hardware operational; awaiting final shift walk | AD5: Coordinated with City Fire Inspector | AE5: Julian Clarkson | AF5: 46307 | AG5: 46317
A6: WO-005 | B6: ='Cover Page'!$C$7 -> CSMIA26 | C6: 5000 Production | D6: 5000.02 Lighting | E6: Lighting Control | F6: Rigging & Focus | G6: High | H6: LOC-01 | I6: {=IF(ISBLANK(H6), "", _xlfn.XLOOKUP(H6, Locations!$A$2:$A100, Locations!$F$2:$F100, ""))} -> Zone B - Main Stage | J6: 5000.02.02-XPMS-004 | K6: 5000-T03 | L6: P-021 | M6: {=IF(ISBLANK(L6), "", TRIM(_xlfn.XLOOKUP(L6, 'Personnel Roster'!$A$2:$A100, 'Personnel Roster'!$D$2:$D100, "") & " " & _xlfn.XLOOKUP(L6, 'Personnel Roster'!$A$2:$A100, 'Personnel Roster'!$E$2:$E100, "")))} -> Julian Clarkson | N6: Overhead Lighting Truss Focus and DMX Addressing | O6: Hang moving heads and test Art-Net lighting universe control | P6: Safety wire secondary attachments, lamp check, and cue recording | Q6: 46320 | R6: 46321 | U6: 18 | V6: 0 | W6: 75 | X6: =V6*W6 -> 0 | Y6: High | Z6: 0 | AA6: Scheduled | AB6: FALSE | AC6: Pending rigger signoff | AD6: Focus scheduled for dark hours | AE6: Julian Clarkson | AF6: 46309 | AG6: 46309

Sheet Run of Show
A1: RECORD ID | B1: ORGANIZATION | C1: PROJECT ID | D1: SCHEDULE RECORD ID | E1: CUE ID | F1: ACT | G1: SCENE | H1: DESCRIPTION | I1: START TIME | J1: END TIME | K1: DURATION (MIN) | L1: LOCATION ID | M1: PERSONNEL ID | N1: AUDIO CUE | O1: LIGHTING CUE | P1: VIDEO CUE | Q1: SFX CUE | R1: STAGE CUE | S1: STATUS | T1: FLAG | U1: NOTES | V1: CREATED BY | W1: CREATED AT | X1: UPDATED AT
A2: ROS-001 | B2: GHXSTSHIP | C2: CSMIA26 | D2: 5000-OPR-007 | E2: CUE-01 | F2: Act I · Ingress & Warm-Up | G2: Doors Open & Guest Check-In | H2: Front of house doors open; guest credentials check and initial lounge activation | I2: 0.75 | J2: 0.77083333 | K2: 30 | L2: LOC-02 | M2: P-016 | N2: Ambient background music at 72 dBA; FOH mix standby | O2: Look 01 - Warm architectural wash & amber accents | P2: Looping Casa Spotify brand reel & sponsor logo matrix | Q2: Baseline atmospheric scent diffusion active; haze standby | R2: Stage dark; DJ gear line check verified; green rooms active | S2: Scheduled | T2: FALSE | U2: Coordinate arrival pace with door security; RFID scanning active | V2: Julian Clarkson | W2: 46297.413 | X2: 46297.413
A3: ROS-002 | B3: GHXSTSHIP | C3: CSMIA26 | D3: 5000-OPR-007 | E3: CUE-02 | F3: Act I · Ingress & Warm-Up | G3: Support DJ Set & Cocktail Reception | H3: Opening support DJ set building energy across the sanctuary floor and patio | I3: 0.77083333 | J3: 0.8125 | K3: 60 | L3: LOC-01 | M3: P-024 | N3: DJ direct input hot; live stereo mains at 85 dBA | O3: Look 02 - Subtle tempo-synced movers & neon perimeter glow | P3: Generative ambient visuals mapped across primary LED wall | Q3: Low haze output (15%) for beam visibility | R3: Support DJ on riser; stage monitors balanced | S3: Scheduled | T3: FALSE | U3: Beverage and canapé service in full circulation across El Patio | V3: Julian Clarkson | W3: 46297.413 | X3: 46297.413
A4: ROS-003 | B4: GHXSTSHIP | C4: CSMIA26 | D4: 5000-OPR-007 | E4: CUE-03 | F4: Act II · Official Opening & Remarks | G4: Executive Welcome & Opening Remarks | H4: Formal welcome remarks by Isabella Acker (Spotify) and Ashley Sumner (Tigre) | I4: 0.8125 | J4: 0.82291667 | K4: 15 | L4: LOC-01 | M4: P-021 | N4: DJ track fade to bed; wireless handheld mics 1 & 2 live at 82 dBA | O4: Look 03 - Crisp keylight wash center-stage; house ambient dimmed 50% | P4: Presentation title slide; live IMAG feed on stage side blades | Q4: Haze paused; clear atmosphere for clear sightlines | R4: Speakers escorted to downstage right; lectern placed center | S4: Scheduled | T4: FALSE | U4: Broadcast feed live recording enabled; timecode sync verified | V4: Julian Clarkson | W4: 46297.413 | X4: 46297.413
A5: ROS-004 | B5: GHXSTSHIP | C5: CSMIA26 | D5: 5000-OPR-007 | E5: CUE-04 | F5: Act II · Official Opening & Remarks | G5: Brand Sizzle & Artist Video Reveal | H5: Dynamic video sizzle reveal showcasing Casa Spotify artist partnerships | I5: 0.82291667 | J5: 0.83333333 | K5: 15 | L5: LOC-01 | M5: P-021 | N5: 5.1 surround sizzle audio playback from media server at 90 dBA | O5: Look 04 - Complete blackout into pulsing emerald/cyan strobes | P5: Full-resolution 4K branded sizzle reel playing on main LED wall | Q5: Cryo CO2 jet single burst on final beat drop | R5: Lectern struck to stage left; headline backline powered hot | S5: Scheduled | T5: FALSE | U5: Headliner escorted from Artist Village Green Room (LOC-06) to stage wing | V5: Julian Clarkson | W5: 46297.413 | X5: 46297.413
A6: ROS-005 | B6: GHXSTSHIP | C6: CSMIA26 | D6: 5000-OPR-007 | E6: CUE-05 | F6: Act III · Headline Performance | G6: Headliner Live Performance (Set 1) | H6: Featured headliner live performance and full concert presentation | I6: 0.83333333 | J6: 0.88541667 | K6: 75 | L6: LOC-01 | M6: P-024 | N6: Full line array concert mix, cardioid sub engagement at 98 dBA | O6: Look 05 - High-energy programmed movers, beam sweeps & pixel tape | P6: Live artist-synced reactive visuals & dynamic multi-cam IMAG | Q6: Cold-spark fountains on track climax; medium atmospheric haze (30%) | R6: Headliner on stage; audio tech standing by stage left | S6: Scheduled | T6: FALSE | U6: Noise monitor logging compliance at Biscayne property perimeter | V6: Julian Clarkson | W6: 46297.413 | X6: 46297.413
A7: ROS-006 | B7: GHXSTSHIP | C7: CSMIA26 | D7: 5000-OPR-007 | E7: CUE-06 | F7: Act III · Headline Performance | G7: Guest Artist Collab & Show Finale | H7: Surprise guest artist collaboration and peak performance finale | I7: 0.88541667 | J7: 0.91666667 | K7: 45 | L7: LOC-01 | M7: P-024 | N7: Guest wireless vocal channels unmuted; peak concert mix at 100 dBA | O7: Look 06 - Audience blinders full, laser aerial fan & 360 strobe sweeps | P7: High-contrast synchronized strobe visual packages across all screens | Q7: Continuous CO2 cryo cannon bursts & biodegradable confetti drop | R7: Guest artist escort onto stage right; stagehands on perimeter | S7: Scheduled | T7: FALSE | U7: Photographers alerted for hero capture moment; security perimeter alert | V7: Julian Clarkson | W7: 46297.413 | X7: 46297.413
A8: ROS-007 | B8: GHXSTSHIP | C8: CSMIA26 | D8: 5000-OPR-007 | E8: CUE-07 | F8: Act IV · Cool-Down & Egress | G8: After-Show DJ & Late-Night Bites | H8: Artist bow, transition to after-hours lounge format, and late-night food cart | I8: 0.91666667 | J8: 0.95833333 | K8: 60 | L8: LOC-01 | M8: P-021 | N8: Live PA transition to downtempo lounge playlist at 80 dBA | O8: Look 07 - Warm golden-hour lounge state; stage movers to static focus | P8: Event recap reel loop & partner appreciation graphic credits | Q8: SFX systems fully safe and isolated; haze exhausted | R8: Headliners escorted to private hospitality lounge; backline isolated | S8: Scheduled | T8: FALSE | U8: Late-night street food carts active on El Patio; rideshare hub dispatch | V8: Julian Clarkson | W8: 46297.413 | X8: 46297.413
A9: ROS-008 | B9: GHXSTSHIP | C9: CSMIA26 | D9: 5000-OPR-007 | E9: CUE-08 | F9: Act IV · Cool-Down & Egress | G9: Final Egress, Load-Out & Space Restoration | H9: Venue doors close; orderly patron egress, initial strike, and custodial turnaround | I9: 0.95833333 | J9: 0.98958333 | K9: 45 | L9: LOC-17 | M9: P-016 | N9: Curfew audio mute; system standby and console shutdown | O9: Look 08 - Full work lights up; exterior security flood illumination | P9: Displays powered down into standby mode | Q9: Systems depressurized and lockbox secured | R9: Overhire stagehands load-in; rolling backline cases to dock A | S9: Scheduled | T9: FALSE | U9: Incident CAD log closed; security sweep verified; venue dark call | V9: Julian Clarkson | W9: 46297.413 | X9: 46297.413

Sheet SOP Library
A1: SOP ID | B1: TITLE | C1: OPERATIONAL DOMAIN | D1: REVISION | E1: ORGANIZATION | F1: PROJECT | G1: DEPARTMENT | H1: CATEGORY | I1: SUB CATEGORY | J1: ACCOUNTABLE ROLE CODE | K1: ACCOUNTABLE ROLE TITLE | L1: REQUIRED PPE / COMPLIANCE TAG | M1: PREREQUISITES & HAZARDS | N1: PROCEDURE STEP 1 | O1: PROCEDURE STEP 2 | P1: PROCEDURE STEP 3 | Q1: PROCEDURE STEP 4 | R1: REFERENCE DOC ID | S1: REFERENCE DOCUMENT NAME | T1: STATUS | U1: FLAG | V1: NOTES | W1: CREATED BY | X1: CREATED AT | Y1: UPDATED AT
A2: SOP-001 | B2: Overhead Rigging & Motor Inspection Protocol | C2: Structural & Rigging Safety | D2: v2.0 | G2: 5000 Production | H2: 5000.05.02 | I2: Overhead Rigging | J2: 5000.51.02 | K2: {=_xlfn.XLOOKUP(J2, 'Roles Library'!$A$2:$A100, 'Roles Library'!$B$2:$B100, "")} -> Head Arena / Festival Rigger | L2: TAG-002 OSHA · TAG-022 ETCP · Hard Hat, ANSI Steel-Toe Boots, High-Vis Vest, Fall Arrest Harness | M2: Verify structural stamped load capacity (DOC-004), verify clear drop zone below trusses, and lock out ground personnel. | N2: Pre-Rig Inspection: Inspect all 1-ton CM lodestar chain hoists, steel cables, shackles, and Spansets for wear, deformation, or certification expiration. | O2: Bridle & Point Hanging: Attach engineered beam clamps to approved building structural nodes per stamped plot; rig motor hoist cables with safety secondary. | P2: Truss Assembly & Dead-Hang Proof: Pin 20.5-inch box truss sections; run cable looms; perform dead-lift test bump to 3 feet; verify shackle mousing and weight distribution. | Q2: Trim Height Lockout: Hoist rig to final trim elevation (22 ft); engage secondary safety safeties/steel chokers; tag out controller box at FOH. | R2: DOC-004 | S2: {=_xlfn.XLOOKUP(R2, 'Document & Asset Library'!$A$2:$A100, 'Document & Asset Library'!$B$2:$B100, "")} -> Overhead Rigging Plot & Stamped Structural Analysis | T2: Active | U2: FALSE | V2: OSHA & ETCP compliant overhead rigging inspection procedure. | W2: Julian Clarkson | X2: 46297.413 | Y2: 46297
A3: SOP-002 | B3: Temporary Event Power Distribution & Generator Energization | C3: High-Voltage Electrical Safety | D3: v1.2 | G3: 5000 Production | H3: 5000.06.01 | I3: Electrical Distribution | J3: 5000.50.02 | K3: {=_xlfn.XLOOKUP(J3, 'Roles Library'!$A$2:$A100, 'Roles Library'!$B$2:$B100, "")} -> Master Electrician / Power Lead | L3: TAG-002 OSHA · TAG-041 NEC · NFPA 70E Arc-Flash Face Shield, Class 0 Insulated Gloves, Safety Glasses | M3: Permit EL-2026-04421 on file (DOC-003); 400A diesel generator grounded to 25 ohms or less; lockout/tagout in effect. | N3: Grounding & Feeder Lay: Drive copper grounding rod; test soil resistance with earth ground meter; lay 4/0 AWG feeder runs in heavy-duty yellow jacket cable ramps. | O3: Cam-Lock Connection Sequence: Connect Ground (Green), Neutral (White), Phase C (Blue), Phase B (Red), Phase A (Black) in strict NEC sequence. | P3: Energization & Phase Rotation: Power generator to 60 Hz idle; verify phase voltage (120V/208V 3-phase) and rotation meter before closing main distribution breaker. | Q3: Sub-Distro Branch Load Balancing: Energize audio, lighting, and video distribution boxes sequentially; monitor balanced amp draw across all 3 legs (max 80% derate). | R3: DOC-003 | S3: {=_xlfn.XLOOKUP(R3, 'Document & Asset Library'!$A$2:$A100, 'Document & Asset Library'!$B$2:$B100, "")} -> Temporary Power & Generator Tie-In Permit & Load Calc | T3: Active | U3: FALSE | V3: NEC & NFPA 70E temporary power tie-in and generator energization protocol. | W3: Julian Clarkson | X3: 46297.413 | Y3: 46297
A4: SOP-003 | B4: Concert Line Array Tuning & Perimeter SPL Curfew Enforcement | C4: Acoustic Systems & Municipal Compliance | D4: v2.0 | G4: 5000 Production | H4: 5000.01.02 | I4: Audio Engineering | J4: 9000.50.02 | K4: {=_xlfn.XLOOKUP(J4, 'Roles Library'!$A$2:$A100, 'Roles Library'!$B$2:$B100, "")} -> Audio Engineer - A1/FOH | L4: TAG-002 OSHA · Hearing Protection (Custom Molded / High-Fidelity Earplugs) | M4: EASE plot alignment confirmed (DOC-005); SMAART acoustic measurement rig calibrated; stage clear of non-audio crew. | N4: Pink Noise Line Check & Phase Verification: Sweep pink noise through individual speaker elements (tops, downfills, subs); confirm polarity and phase coherence in SMAART. | O4: Cardioid Sub Optimization: Align delay and phase cancellation on rear-facing sub elements to create 18dB rear rejection toward Biscayne property boundary. | P4: System EQ & Target Curve Voicing: Apply room curve filtering for vocal clarity and dynamic range; tune FOH mix position to target 98 dBA Leq (15 min). | Q4: Perimeter Curfew Logging: Deploy remote Type 2 sound level meter at property edge; continuously record calibrated SPL to verify <78 dBA compliance through midnight. | R4: DOC-005 | S4: {=_xlfn.XLOOKUP(R4, 'Document & Asset Library'!$A$2:$A100, 'Document & Asset Library'!$B$2:$B100, "")} -> Acoustic Sound Modeling & SPL Compliance Plan | T4: Active | U4: FALSE | V4: Acoustic line array tuning and Biscayne perimeter SPL curfew compliance. | W4: Julian Clarkson | X4: 46297.413 | Y4: 46297
A5: SOP-004 | B5: Severe Weather Monitoring & Temporary Structure Evacuation | C5: Life Safety & Weather Trigger Management | D5: v1.5 | G5: 6000 Operations | H5: 6000.05.01 | I5: Severe Weather & Egress | J5: 6000.50.02 | K5: {=_xlfn.XLOOKUP(J5, 'Roles Library'!$A$2:$A100, 'Roles Library'!$B$2:$B100, "")} -> Site Safety & Security Lead | L5: TAG-002 OSHA · TAG-019 NFPA · Weatherproof Tactical Hi-Vis Outerwear, Flashlight, Two-Way Radio (Channel 1) | M5: On-site calibrated anemometer active; live radar weather monitoring feed connected; Emergency Action Plan active (DOC-008). | N5: Advisory State (25 MPH Gusts / Lightning <15 Miles): Notify Executive Producer and Department Heads via Radio Ch 1; inspect tent ballasts and loose signage. | O5: Restricted State (35 MPH Gusts / Lightning <8 Miles): Pause high-altitude staging/aerial lifts; lower flying LED walls to safety deck; pause patio dining service. | P5: Evacuation Trigger (45 MPH Gusts / Lightning <5 Miles): Trigger mass notification; illuminate emergency work lights; activate orderly egress toward indoor sanctuary (LOC-01). | Q5: Post-Storm All-Clear & Inspection: Conduct structural engineering inspection of outdoor canopies, rigging points, and electrical lines before re-admitting guests. | R5: DOC-008 | S5: {=_xlfn.XLOOKUP(R5, 'Document & Asset Library'!$A$2:$A100, 'Document & Asset Library'!$B$2:$B100, "")} -> Comprehensive Emergency Action & Severe Weather Plan | T5: Active | U5: FALSE | V5: Severe weather action levels and temporary structure evacuation protocol. | W5: Julian Clarkson | X5: 46297.413 | Y5: 46297
A6: SOP-005 | B6: Assembly Occupancy Ingress & Egress Door Control | C6: Crowd Management & Fire Code Compliance | D6: v1.0 | G6: 6000 Operations | H6: 6000.50.01 | I6: House Management | J6: 6000.50.01 | K6: {=_xlfn.XLOOKUP(J6, 'Roles Library'!$A$2:$A100, 'Roles Library'!$B$2:$B100, "")} -> House Manager | L6: TAG-002 OSHA · TAG-006 ADA · Certified Crowd Manager Badge, Hi-Vis Identification Lanyard | M6: Assembly permit BD-2026-08914 approved (DOC-002); master egress widths verified (DOC-001); minimum 8 crowd managers on post. | N6: Pre-Ingress Life Safety Walk: Walk all exit corridors, panic hardware, emergency illuminated exit signs, and fire extinguisher stations; verify zero pathway obstructions. | O6: Queue Line Stanchion Configuration: Establish ADA-compliant arrival switchbacks (36-inch clear path); position RFID scanners; open check-in gates at T-00:30 (18:00). | P6: Capacity Flow Tracking: Monitor real-time headcount dashboard; maintain headcount under 350 occupant maximum; enforce 1-in-1-out policy if capacity reached. | Q6: Egress Call & Doors Clearance: At event conclusion (23:00), prop all double exit doors fully open; guide patron flow toward rideshare dispatch hub on 76th St. | R6: DOC-002 | S6: {=_xlfn.XLOOKUP(R6, 'Document & Asset Library'!$A$2:$A100, 'Document & Asset Library'!$B$2:$B100, "")} -> City of Miami Special Assembly Occupancy Permit | T6: Active | U6: FALSE | V6: Assembly occupancy door control and crowd manager egress coordination. | W6: Julian Clarkson | X6: 46297.413 | Y6: 46297
A7: SOP-006 | B7: Live Performance Show Calling & Cue Execution Sequence | C7: Stage Management & Live Production Control | D7: v3.1 | G7: 9000 Technology | H7: 9000.50.01 | I7: Show Calling | J7: 9000.50.01 | K7: {=_xlfn.XLOOKUP(J7, 'Roles Library'!$A$2:$A100, 'Roles Library'!$B$2:$B100, "")} -> Production Stage Manager | L7: TAG-002 OSHA · Clear-Com Headset, Production Flashlight with Red Filter | M7: Run of Show cue list locked; SMPTE timecode sync verified with playback and lighting consoles; talent green room escorts standby. | N7: Comms Line Check (T-00:15): Establish multi-channel comms check with Audio (Ch A), Lighting (Ch B), Video (Ch C), and Stage Deck (Ch D); verify cue lights green. | O7: Standby Call Cadence: Issue standard verbal standbys precisely 30 seconds prior to cue trigger: \"Standby Audio Cue 05, Standby Lighting Look 05, Standby Video Blade 05\". | P7: Cue Execution Call: Call crisp execution trigger on downbeat or timecode mark: \"Audio, Lights, Video... GO.\" Confirm acknowledge from all discipline operators. | Q7: Hold & Abort Protocol: In the event of deck hazard, performer distress, or safety breach, immediately call \"HOLD, HOLD, HOLD\" on all channels and take stage to safe wash. | R7: DOC-007 | S7: {=_xlfn.XLOOKUP(R7, 'Document & Asset Library'!$A$2:$A100, 'Document & Asset Library'!$B$2:$B100, "")} -> Artist Sizzle Reel & Main LED Key Visual Master 4K | T7: Active | U7: FALSE | V7: Live performance cue execution sequence and emergency hold protocol. | W7: Julian Clarkson | X7: 46297.413 | Y7: 46297
A8: SOP-007 | B8: Real-Time Media Ingest, Checksum Verification & Social Reel Delivery | C8: Digital Asset Management & PR Workflow | D8: v1.0 | G8: 3000 Marketing | H8: 3000.50.02 | I8: Media Production | J8: 3000.50.02 | K8: {=_xlfn.XLOOKUP(J8, 'Roles Library'!$A$2:$A100, 'Roles Library'!$B$2:$B100, "")} -> Lead Cinematographer / Video Shooter | L8: TAG-026 PCI · Anti-Static Handling Wrist Strap, Media Hard Drive Vault Bags | M8: 10GbE NAS network connected; cleared artist music sync rights on file; Casa Spotify Brand Toolkit active (DOC-006). | N8: CFexpress / SD Card Offload: Ingest raw 4K camera cards via ShotPut Pro; compute MD5/xxHash checksum verification to primary NVMe RAID storage. | O8: Secondary Cloud Backup: Trigger automated parallel upload to Google Drive archive directory and off-site cloud bucket with version tagging. | P8: Editorial & Color Grading: Conform footage in Premiere Pro / DaVinci Resolve using Casa Spotify Wynwood LUT; apply official Spotify logo bugs and artist titles. | Q8: PR & Social Master Handoff: Export 9x16 vertical reels (H.264/ProRes) within 90 minutes of set completion; push assets to PR distribution team with cleared usage metadata. | R8: DOC-006 | S8: {=_xlfn.XLOOKUP(R8, 'Document & Asset Library'!$A$2:$A100, 'Document & Asset Library'!$B$2:$B100, "")} -> Casa Spotify Wynwood Brand Toolkit & Style Guide | T8: Active | U8: FALSE | V8: Real-time media card offload, checksum verification, and PR reel delivery. | W8: Julian Clarkson | X8: 46297.413 | Y8: 46297
A9: SOP-008 | B9: Post-Show Strike Sequence & Venue Space Restoration | C9: Load-Out Logistics & Space Handover | D9: v2.0 | G9: 5000 Production | H9: 5000.51.01 | I9: Stage & Rig Strike | J9: 5000.51.01 | K9: {=_xlfn.XLOOKUP(J9, 'Roles Library'!$A$2:$A100, 'Roles Library'!$B$2:$B100, "")} -> Lead Stagehand / Deck Crew Chief | L9: TAG-002 OSHA · Steel-Toe Boots, Heavy Leather Rigging Gloves, High-Vis Vest, Hard Hat | M9: Audience 100% egressed; venue power isolated; truck staging bay active in Marshalling Yard; Work Order WO-002 active. | N9: Backline & Microphones Strike: Disconnect instrument mics, pack artist backline into ATA flight cases; secure high-value wireless gear into locked Pelican cases. | O9: LED Wall & Lighting Truss Drop: Lower overhead trusses to 4 ft service height; de-cable pixel tape and DMX looms; pack LED video tiles into custom road cases. | P9: Motor De-Rig & Cable Pull: Slack chain hoists; derig beam clamps; coil 4/0 feeder cables into rolltainers; strike temporary distro boxes to staging dock. | Q9: Sanitation Sweep & Venue Handover: Conduct sweeping and debris removal across sanctuary floor and El Patio; conduct joint walk with venue manager for damage sign-off. | R9: DOC-001 | S9: {=_xlfn.XLOOKUP(R9, 'Document & Asset Library'!$A$2:$A100, 'Document & Asset Library'!$B$2:$B100, "")} -> Master Architectural Site Plan & Life Safety CAD | T9: Active | U9: FALSE | V9: Post-show stage strike, equipment packing, and venue space restoration. | W9: Julian Clarkson | X9: 46297.413 | Y9: 46297
A10: SOP-009 | B10: Temporary Demountable Structures (TDS) Ballast & Wind Bracing Protocol | C10: Temporary Structures & Wind Engineering | D10: v1.4 | G10: 4000 Environment | H10: 4000.08.02 | I10: Tents & Temporary Structures | J10: 4000.50.01 | K10: {=_xlfn.XLOOKUP(J10, 'Roles Library'!$A$2:$A100, 'Roles Library'!$B$2:$B100, "")} -> Structural Carpenter / Build Lead | L10: TAG-002 OSHA · TAG-008 TENT_PERMIT · TAG-036 STRUCT_ENG · Hard Hat, Steel-Toe Boots, High-Vis Vest | M10: Stamped engineering ballast calculation on file (DOC-009); calibrated water meter/crane scale for weight verification; anemometer active. | N10: Pre-Erection Footing Inspection: Verify subgrade compaction, asphalt integrity, and laser-level baseplate pads; position pre-cast concrete ballast blocks per structural plot. | O10: Frame Truss Pinning & Squaring: Assemble structural aluminum box arches on ground; verify diagonal squareness within 0.25 in; insert all structural pins and safety R-clips. | P10: Ballast Rigging & Guying: Connect high-tensile ratchet straps and 3/8-in wire rope guying to concrete weights; tension each guy wire to engineered load specification. | Q10: Membrane Tensioning & Flame Cert Log: Pull fire-retardant vinyl canopies through keder rails; ratchet tension to prevent wind pocketing; post NFPA 701 flame cert tag at mast. | R10: DOC-009 | S10: {=_xlfn.XLOOKUP(R10, 'Document & Asset Library'!$A$2:$A100, 'Document & Asset Library'!$B$2:$B100, "")} -> Temporary Demountable Structures (TDS) Wind Stability & Ballast Analysis | T10: Active | U10: FALSE | V10: ANSI ES1.7 & Florida Building Code temporary structure ballast and guy wire protocol. | W10: Julian Clarkson | X10: 46297.413 | Y10: 46297
A11: SOP-010 | B11: Stage Pyrotechnics, Flame Effects & Cold Spark Safety Sequence | C11: Pyrotechnics & Atmospheric Effects Safety | D11: v1.0 | G11: 5000 Production | H11: 5000.07.01 | I11: Atmospheric Effects | J11: 5000.52.01 | K11: {=_xlfn.XLOOKUP(J11, 'Roles Library'!$A$2:$A100, 'Roles Library'!$B$2:$B100, "")} -> Special Effects / Pyro Lead | L11: TAG-002 OSHA · TAG-019 NFPA · TAG-038 PYRO_LICENSE · Nomex Flame-Resistant Jacket, Safety Glasses, 2A-10BC Extinguisher | M11: City of Miami Fire-Rescue permit active (DOC-010); designated 15-foot separation safety zone established; Miami Fire watch on duty. | N11: Hardware & Fuel Integrity Inspection: Inspect LP-gas hoses, solenoid valves, and titanium cold-spark granules; verify pressure regulators and emergency deadman switches. | O11: Perimeter Barrier & Line-of-Sight Lock: Establish physical stanchions 15 ft from discharge nozzles; verify clear overhead clearance to trussing (>25 ft) and drapery. | P11: Arming Sequence & Pyro Controller Link: Connect digital firing controller via isolated dry-contact DMX line; verify continuity; arm system only on stage manager verbal standby. | Q11: Post-Fire Safe Depressurization & Canister Lock: Disarm firing console immediately post-cue; vent residual gas lines; vacuum titanium dust; lock canisters in pyro vault. | R11: DOC-010 | S11: {=_xlfn.XLOOKUP(R11, 'Document & Asset Library'!$A$2:$A100, 'Document & Asset Library'!$B$2:$B100, "")} -> Miami Fire-Rescue Special Effects & Flame Effects Permit | T11: Active | U11: FALSE | V11: NFPA 160 & NFPA 1126 stage flame effects and cold spark firing procedure. | W11: Julian Clarkson | X11: 46297.413 | Y11: 46297
A12: SOP-011 | B12: Class 3B/4 Audience-Scanned Laser Alignment & Termination Safety | C12: Optical Radiation & Laser Safety | D12: v1.0 | G12: 5000 Production | H12: 5000.07.01 | I12: Atmospheric Effects | J12: 9000.50.03 | K12: {=_xlfn.XLOOKUP(J12, 'Roles Library'!$A$2:$A100, 'Roles Library'!$B$2:$B100, "")} -> Lighting Designer / LD | L12: TAG-002 OSHA · TAG-018 ANSI · Laser Safety Eyewear (OD 7+ @ 520nm/450nm/638nm) | M12: FDA CDRH variance valid (DOC-011); certified Laser Safety Officer (LSO) on site; hard mechanical beam stops anchored. | N12: Physical Rigging & E-Stop Verification: Mount RGB projector to rigid truss with secondary safety cable; wire hardwired emergency mushroom e-stop at FOH control position. | O12: Scan-Fail Circuit & Masking Calibration: Calibrate hardware scan-fail interlock boards; configure geometric software masking zones to prevent exposure below 10 ft from floor. | P12: Low-Power Beam Alignment & Termination Proof: Power up laser in 1% alignment mode; verify all bounce mirrors and strike non-reflective fire-rated beam dumps. | Q12: Full-Power Exposure Metering & LSO Sign-Off: Measure Maximum Permissible Exposure (MPE) at closest patron boundary using calibrated laser power meter; record LSO log. | R12: DOC-011 | S12: {=_xlfn.XLOOKUP(R12, 'Document & Asset Library'!$A$2:$A100, 'Document & Asset Library'!$B$2:$B100, "")} -> FDA CDRH Class 3B/4 Audience-Scanned Laser Variance | T12: Active | U12: FALSE | V12: ANSI Z136.1 & FDA CDRH 21 CFR 1040.10 outdoor entertainment laser safety protocol. | W12: Julian Clarkson | X12: 46297.413 | Y12: 46297
A13: SOP-012 | B13: Environmental Noise Monitoring & Wynwood Perimeter SPL Curfew Enforcement | C13: Acoustic Systems & Municipal Compliance | D13: v2.0 | G13: 5000 Production | H13: 5000.01.02 | I13: Audio Engineering | J13: 9000.50.02 | K13: {=_xlfn.XLOOKUP(J13, 'Roles Library'!$A$2:$A100, 'Roles Library'!$B$2:$B100, "")} -> Audio Engineer - A1/FOH | L13: TAG-002 OSHA · Type 1/2 Calibrated Sound Level Meter, High-Vis Vest, Two-Way Radio | M13: Municipal sound variance on file (DOC-012); acoustical calibrator (94 dB / 114 dB) checked; remote logging telemetry online. | N13: Field Calibrator Verification: Mount microphone on remote perimeter meter; apply 94.0 dB acoustical calibrator; log reference drift within +/-0.3 dB before event start. | O13: FOH Leq Ceiling Enforcement: Set software limiter threshold at FOH console to cap continuous mix volume at 98 dBA Leq (15-min rolling window). | P13: Boundary Telemetry Real-Time Tracking: Continuously monitor property boundary meters along Biscayne Blvd; alert FOH A1 if 5-min Leq approaches 76 dBA. | Q13: Midnight Curfew Step-Down Execution: At 23:59 EDT, execute programmed console master mute on all outdoor PA elements; file continuous SPL audit log to city compliance portal. | R13: DOC-012 | S13: {=_xlfn.XLOOKUP(R13, 'Document & Asset Library'!$A$2:$A100, 'Document & Asset Library'!$B$2:$B100, "")} -> City of Miami Code Compliance Noise Variance & Perimeter Curfew Permit | T13: Active | U13: FALSE | V13: City of Miami Chapter 36 Noise Ordinance and perimeter SPL monitoring procedure. | W13: Julian Clarkson | X13: 46297.413 | Y13: 46297
A14: SOP-013 | B14: Temporary Commercial Kitchen Sanitation & Food Safety Inspection | C14: Culinary Health & Sanitary Compliance | D14: v1.0 | G14: 8000 Hospitality | H14: 8000.01.01 | I14: Catering & Culinary | J14: 8000.51.01 | K14: {=_xlfn.XLOOKUP(J14, 'Roles Library'!$A$2:$A100, 'Roles Library'!$B$2:$B100, "")} -> Executive Catering Captain | L14: TAG-002 OSHA · TAG-010 HEALTH_DEPT · TAG-011 SERVSAFE · Non-Slip Shoes, Food-Grade Nitrile Gloves, Beard Net / Hair Net | M14: Florida DBPR food service license posted (DOC-013); potable hot water station operational (min 100 deg F); digital stem thermometers calibrated in ice bath. | N14: Cold-Chain Receiving & Temperature Verification: Probe all incoming TCS foods (poultry, beef, seafood, dairy); verify internal temp <41 deg F; reject out-of-spec shipments. | O14: Handwashing & 3-Compartment Sink Setup: Establish dedicated handwash station with warm water, soap, single-use paper towels; set wash/rinse/sanitize (200 ppm Quat) sink bays. | P14: Holding Temperature & Cross-Contamination Control: Monitor hot holding units (>135 deg F) and refrigerated prep tables (<41 deg F) every 2 hours; enforce allergen color-coding. | Q14: Shift Waste Disposal & Sanitizing Break-Down: Discard holding foods at 4-hour mark; sanitize stainless steel prep surfaces with quaternary solution; seal trash cans. | R14: DOC-013 | S14: {=_xlfn.XLOOKUP(R14, 'Document & Asset Library'!$A$2:$A100, 'Document & Asset Library'!$B$2:$B100, "")} -> Florida DBPR Division of Hotels & Restaurants Temporary Food Service License | T14: Active | U14: FALSE | V14: Florida Administrative Code 61C-4 & FDA Food Code temporary food establishment protocol. | W14: Julian Clarkson | X14: 46297.413 | Y14: 46297
A15: SOP-014 | B15: Alcoholic Beverage Dispensing, Age Verification & Intoxication Interception | C15: Alcohol Governance & Hospitality Compliance | D15: v1.1 | G15: 8000 Hospitality | H15: 8000.02.01 | I15: Bar & Beverage | J15: 8000.50.01 | K15: {=_xlfn.XLOOKUP(J15, 'Roles Library'!$A$2:$A100, 'Roles Library'!$B$2:$B100, "")} -> Head Beverage Director / Bar Manager | L15: TAG-012 TIPS · TAG-013 LIQUOR_LICENSE · Certified TIPS/ServSafe Alcohol Badge, Bar Apron | M15: Florida DBPR ABT permit posted (DOC-014); electronic ID barcode scanners active at all bar stations; security liaison assigned to bar perimeter. | N15: 100% ID Scanning & Wristband Verification: Inspect physical photo ID for all patrons requesting alcohol; verify age 21+ via optical scanner; confirm intact 21+ wristband. | O15: Standard Pour Volume & Recipe Control: Utilize measured jiggers for all spirit pours (1.5 oz spirit maximum per drink); enforce strict 2-drink maximum per transaction. | P15: Behavioral Intoxication Assessment: Monitor guests for slurred speech, motor instability, or combative behavior; refuse service tactfully using non-confrontational phrasing. | Q15: Cut-Off Protocol & Security Dispatch: In event of refused service, immediately notify Bar Manager and dispatch roving Security Officer to offer hydration and rideshare escort. | R15: DOC-014 | S15: {=_xlfn.XLOOKUP(R15, 'Document & Asset Library'!$A$2:$A100, 'Document & Asset Library'!$B$2:$B100, "")} -> Florida DBPR Division of ABT Special Event Alcoholic Beverage Permit (ODP) | T15: Active | U15: FALSE | V15: Florida Statute 561 & 562 beverage law compliance and responsible vendor procedure. | W15: Julian Clarkson | X15: 46297.413 | Y15: 46297
A16: SOP-015 | B16: Mass-Gathering Emergency Medical Dispatch, Triage & Heat Illness Protocol | C16: Emergency Medical Services & Life Safety | D16: v2.1 | G16: 6000 Operations | H16: 6000.05.02 | I16: Medical & EMS | J16: 7000.51.01 | K16: {=_xlfn.XLOOKUP(J16, 'Roles Library'!$A$2:$A100, 'Roles Library'!$B$2:$B100, "")} -> Lead Event Paramedic / EMT | L16: TAG-002 OSHA · TAG-028 HIPAA · Nitrile Exam Gloves, N95 Mask, High-Vis Medical Vest, Two-Way Radio (Channel 2) | M16: Miami-Dade Fire Rescue medical plan active (DOC-015); on-site air-conditioned medical tent established; dedicated ALS ambulance parked in dock bay. | N16: Triage Bay Readiness & Equipment Check: Perform daily operational bump check on Zoll AED, oxygen cylinders, suction units, and trauma jump kits; confirm cold IV saline stores. | O16: Roving Medic Rapid-Response Cadence: Deploy pairs of EMTs across Main Stage and El Patio; maintain 3-minute maximum response radius to any distress call on Radio Ch 2. | P16: Heat Illness & Substance Harm Reduction: Triage symptomatic patrons; initiate rapid evaporative cooling, electrolyte fluid replacement, and vital signs monitoring every 10 min. | Q16: 911 Escalation & Secure Transport Handoff: For red-tier critical patients, coordinate seamless patient transfer to Miami-Dade Fire Rescue ALS transport unit via Gate 3 access lane. | R16: DOC-015 | S16: {=_xlfn.XLOOKUP(R16, 'Document & Asset Library'!$A$2:$A100, 'Document & Asset Library'!$B$2:$B100, "")} -> Event Mass-Gathering Medical Action Plan & Miami-Dade EMS Detail | T16: Active | U16: FALSE | V16: Florida EMS Chapter 401 & NFPA 3000 mass gathering emergency medical protocol. | W16: Julian Clarkson | X16: 46297.413 | Y16: 46297
A17: SOP-016 | B17: Physical Security Perimeter Access, Metal Detection & Bag Inspection | C17: Security Operations & Threat Mitigation | D17: v2.0 | G17: 6000 Operations | H17: 6000.04.01 | I17: Security & Access Control | J17: 6000.52.01 | K17: {=_xlfn.XLOOKUP(J17, 'Roles Library'!$A$2:$A100, 'Roles Library'!$B$2:$B100, "")} -> Security Supervisor | L17: TAG-002 OSHA · TAG-021 BG_CHECK · Uniformed Security Officer Attire, Flashlight, Two-Way Radio (Channel 1) | M17: City of Miami approved security overlay on file (DOC-016); walk-through magnetometers calibrated; prohibited items amnesty bins staged outside entry switchbacks. | N17: Entry Lane Divestment Screening: Instruct arriving patrons to divest metallic items into inspection trays; visually inspect clear bags (12x6x12 in max) with wooden inspection dowel. | O17: Walk-Through Magnetometer Processing: Guide patrons through magnetometer at standard cadence; conduct secondary screening with handheld wand if zone alert triggers. | P17: Prohibited Item Confiscation & Chain of Custody: Safely confiscate contraband, weapons, or unauthorized recording rigs; deposit into locked evidence locker; log owner info. | Q17: Threat Interception & Law Enforcement Handover: If illegal firearms or hostile behavior detected, immediately detain subject, initiate ICS emergency call, and hand over to on-site MPD. | R17: DOC-016 | S17: {=_xlfn.XLOOKUP(R17, 'Document & Asset Library'!$A$2:$A100, 'Document & Asset Library'!$B$2:$B100, "")} -> Event Physical Security, Crowd Management & Evacuation Routing Plan | T17: Active | U17: FALSE | V17: DHS Active Shooter & Florida Class D security guard screening standards. | W17: Julian Clarkson | X17: 46297.413 | Y17: 46297
A18: SOP-017 | B18: Public Right-of-Way Traffic Control & Marshalling Yard Truck Staging | C18: Traffic Engineering & Logistics Coordination | D18: v1.3 | G18: 6000 Operations | H18: 6000.02.07 | I18: Trucks & Transport | J18: 6000.51.02 | K18: {=_xlfn.XLOOKUP(J18, 'Roles Library'!$A$2:$A100, 'Roles Library'!$B$2:$B100, "")} -> Marshalling Yard & Dock Master | L18: TAG-002 OSHA · TAG-016 DOT · ANSI Class 3 High-Vis Vest, Steel-Toe Boots, Hard Hat, Traffic Wand, Radio (Channel 3) | M18: City of Miami / FDOT MOT permit active (DOC-017); certified traffic flaggers positioned; Type II traffic cones and electronic arrow board deployed along 76th St. | N18: Street Closure Signage & Arrow Board Activation: Deploy advance warning signs ('ROAD WORK AHEAD', 'LANE CLOSED') per FDOT index; power electronic directional arrow board. | O18: Carrier Dispatch & Marshalling Check-In: Intercept arriving 53-ft tractor-trailers at holding yard; verify carrier Bill of Lading (BOL), driver phone, and assigned dock appointment. | P18: Dock Call & Reversing Spotter Escort: Guide truck from holding bay into loading dock; assign 2 ground spotters with safety whistles to clear pedestrian sidewalk traffic. | Q18: Wheels Chocking & Loading Ramp Deployment: Place heavy-duty rubber wheel chocks under rear trailer tandem; engage dock leveler lip before authorizing forklift load-in. | R18: DOC-017 | S18: {=_xlfn.XLOOKUP(R18, 'Document & Asset Library'!$A$2:$A100, 'Document & Asset Library'!$B$2:$B100, "")} -> Public Right-of-Way Closure & Maintenance of Traffic (MOT) Plan | T18: Active | U18: FALSE | V18: FDOT Standard Plans Index 102 & MUTCD Part 6 traffic control and freight staging procedure. | W18: Julian Clarkson | X18: 46297.413 | Y18: 46297
A19: SOP-018 | B19: Commercial Drone Aerial Video Capture & Airspace Safety Protocol | C19: Aviation Safety & UAS Operations | D19: v1.0 | G19: 5000 Production | H19: 5000.08.01 | I19: Cameras & Capture | J19: 3000.50.02 | K19: {=_xlfn.XLOOKUP(J19, 'Roles Library'!$A$2:$A100, 'Roles Library'!$B$2:$B100, "")} -> Lead Cinematographer / Video Shooter | L19: TAG-003 FAA · TAG-023 FAA_PART107 · High-Vis Flight Crew Vest, Safety Glasses, Two-Way Radio | M19: FAA Part 107 waiver on file (DOC-018); LAANC airspace authorization verified; dedicated Visual Observer (VO) positioned on sanctuary roof deck. | N19: Pre-Flight Airspace & Telemetry Inspection: Conduct pre-flight drone inspection (rotors, gimbal, obstacle sensors); confirm GPS lock (>16 satellites); set Return-to-Home altitude to 150 ft. | O19: Visual Observer Comms & Geo-Fence Setup: Establish continuous voice comms between Pilot in Command (PIC) and VO; lock geofence boundaries to prevent flight over unshielded crowds. | P19: In-Flight Mission Execution & Battery Thresholds: Execute programmed sweeping cinematic passes; initiate mandatory return and landing sequence when battery telemetry reaches 25%. | Q19: Post-Flight Media Offload & Flight Logging: Power down aircraft; offload flight logs and micro-SD footage cards; log total flight hours and airspace compliance into ops portal. | R19: DOC-018 | S19: {=_xlfn.XLOOKUP(R19, 'Document & Asset Library'!$A$2:$A100, 'Document & Asset Library'!$B$2:$B100, "")} -> FAA Part 107 Airspace Authorization & UAS Night Flight Waiver | T19: Active | U19: FALSE | V19: FAA Part 107 federal regulations and commercial UAS safe flight operation protocol. | W19: Julian Clarkson | X19: 46297.413 | Y19: 46297
A20: SOP-019 | B20: ADA Accessibility, Companion Seating & Barrier-Free Path Management | C20: Universal Accessibility & Guest Services | D20: v2.0 | G20: 7000 Experience | H20: 7000.01.01 | I20: Guest Experience & Journey | J20: 7000.50.01 | K20: {=_xlfn.XLOOKUP(J20, 'Roles Library'!$A$2:$A100, 'Roles Library'!$B$2:$B100, "")} -> Front of House Lead / Box Office Manager | L20: TAG-006 ADA · Front-of-House Credential Badge, Digital Ingress Scanner | M20: Master ADA survey on file (DOC-019); wheelchair viewing platforms inspected; clear accessible path (min 36 inches) marked throughout all activation zones. | N20: Pre-Event Route & Ramp Verification: Walk all accessible routes from public sidewalk to stage viewing areas; verify ramp slopes do not exceed 1:12; verify zero lip thresholds >0.25 in. | O20: Elevated Viewing Platform Setup: Configure ADA viewing riser with code-compliant handrails, edge protection kick plates, and paired companion chairs with unobstructed sightlines. | P20: Assisted Listening & Sensory Kit Distribution: Inspect RF assisted listening receivers and neck loops; stage sensory kits (noise-canceling headphones, sunglasses) at FOH guest desk. | Q20: Accessible Egress Escort & Dedicated Exit Clearance: During show egress, position dedicated guest ambassadors along primary ramp routes to ensure unimpeded wheelchair flow to rideshare hub. | R20: DOC-019 | S20: {=_xlfn.XLOOKUP(R20, 'Document & Asset Library'!$A$2:$A100, 'Document & Asset Library'!$B$2:$B100, "")} -> ADA Accessibility, Companion Seating & Accessible Route Survey | T20: Active | U20: FALSE | V20: 2010 ADA Standards for Accessible Design & Florida Accessibility Code protocol. | W20: Julian Clarkson | X20: 46297.413 | Y20: 46297
A21: SOP-020 | B21: Radio Frequency (RF) Spectrum Coordination & Wireless Intercom Intermodulation | C21: Communications Infrastructure & Spectrum Control | D21: v1.5 | G21: 9000 Technology | H21: 9000.03.01 | I21: Two-Way Radios | J21: 9000.52.01 | K21: {=_xlfn.XLOOKUP(J21, 'Roles Library'!$A$2:$A100, 'Roles Library'!$B$2:$B100, "")} -> Lead Network & Comms Engineer | L21: TAG-033 FCC · TAG-034 FCC_PART74 · RF Analyzer Wand, High-Fidelity Test Headphones | M21: FCC Part 74 license active (DOC-020); RF spectrum analyzer calibrated; Shure Wireless Workbench environment loaded with Miami broadcast exclusions. | N21: Wideband Spectrum Sweep (470-608 MHz): Perform RF spectrum sweep across Wynwood venue airspace; identify active DTV broadcast channels and unauthorized rogue transmitters. | O21: Intermodulation Calculation & Frequency Deployment: Compute intermodulation distortion profiles; coordinate compatible frequencies for 16x wireless mics and 8x IEM transmitters. | P21: Axient Digital ShowLink & FreeSpeak Pairing: Deploy networked antenna distro (distro4); pair digital transmitters via IR sync; verify ShowLink automated interference avoidance. | Q21: Walk-Test RF Coverage & Shadow Mapping: Walk venue boundaries with test transmitter; verify zero dropouts across sanctuary, stage, and BOH green rooms; log RF stability report. | R21: DOC-020 | S21: {=_xlfn.XLOOKUP(R21, 'Document & Asset Library'!$A$2:$A100, 'Document & Asset Library'!$B$2:$B100, "")} -> FCC Part 74 Wireless Microphone & Comms Frequency Coordination | T21: Active | U21: FALSE | V21: FCC Part 74 Subpart H & AES recommended wireless audio frequency coordination protocol. | W21: Julian Clarkson | X21: 46297.413 | Y21: 46297
A22: SOP-021 | B22: Generator Diesel Fueling, Spill Containment & Secondary HazMat Handling | C22: Hazardous Materials & Fuel Safety | D22: v1.0 | G22: 6000 Operations | H22: 6000.09.01 | I22: Waste Management | J22: 5000.50.02 | K22: {=_xlfn.XLOOKUP(J22, 'Roles Library'!$A$2:$A100, 'Roles Library'!$B$2:$B100, "")} -> Master Electrician / Power Lead | L22: TAG-002 OSHA · TAG-040 EPA · Chemical Nitrile Gloves, Safety Splash Goggles, Fuel-Resistant Apron | M22: Environmental containment plan active (DOC-021); 55-gallon universal spill kit staged within 15 ft of fuel port; fire extinguisher (20BC) charged on post. | N22: Pre-Fueling Ground Berm & Pad Inspection: Inspect secondary containment berm under 400A diesel generator; verify rubber liner intact with zero tears, water, or oil residue. | O22: Bonding & Static Ground Wire Attachment: Attach heavy-duty copper static bonding cable from fuel supply truck chassis to generator ground lug prior to opening fuel cap. | P22: Monitored Delivery & Cam-Lock Tightness: Execute controlled fuel pumping at low velocity (<25 GPM); monitor mechanical sight gauge; stop transfer at 90% tank capacity. | Q22: Nozzle Capping & Containment Log Clearance: Wipe fuel nozzle; disconnect bonding clamp; inspect spill berm for drips; record delivered gallons and date into HazMat binder. | R22: DOC-021 | S22: {=_xlfn.XLOOKUP(R22, 'Document & Asset Library'!$A$2:$A100, 'Document & Asset Library'!$B$2:$B100, "")} -> Hazardous Materials & Diesel Fuel Storage Environmental Plan | T22: Active | U22: FALSE | V22: EPA SPCC Rule 40 CFR 112 & Miami-Dade DERM temporary fuel transfer protocol. | W22: Julian Clarkson | X22: 46297.413 | Y22: 46297
A23: SOP-022 | B23: Commercial Insurance Endorsement Verification & Subcontractor COI Audit | C23: Risk Governance & Insurance Compliance | D23: v1.0 | G23: 0000 Executive | H23: 0000.06.01 | I23: Insurance | J23: 0000.51.01 | K23: {=_xlfn.XLOOKUP(J23, 'Roles Library'!$A$2:$A100, 'Roles Library'!$B$2:$B100, "")} -> Production Finance Director | L23: None Required (Administrative Governance) | M23: Master insurance binder bound (DOC-022); contract vendor roster active; digital COI tracking ledger online. | N23: ACORD 25 Certificate Intake: Ingest all incoming vendor Certificates of Insurance; verify policy effective dates encompass entire load-in, event, and load-out window. | O23: Coverage Limit & Endorsement Audit: Confirm minimum $1M Occurrence / $2M Aggregate GL limits; verify $5M Umbrella, Statutory Workers' Comp, and $1M Commercial Auto. | P23: Additional Insured Endorsement Scrutiny: Verify mandatory endorsement CG 20 26 or equivalent naming GHXSTSHIP, Spotify, and Venue Owner as Additional Insureds with Waiver of Subrogation. | Q23: Gate 2 Clearance & Vendor Access Lockout: Mark vendor insurance status 'Approved' in Procurement Catalog; issue digital pass to dock master; lock out unapproved subcontractors. | R23: DOC-022 | S23: {=_xlfn.XLOOKUP(R23, 'Document & Asset Library'!$A$2:$A100, 'Document & Asset Library'!$B$2:$B100, "")} -> Commercial General Liability & $10M Excess Umbrella Insurance Binder | T23: Active | U23: FALSE | V23: Commercial insurance risk underwriting standards & ACORD document verification protocol. | W23: Julian Clarkson | X23: 46297.413 | Y23: 46297
A24: SOP-023 | B24: Aerial Work Platform (AWP) Operation, MEWP Inspection & Fall Arrest Protocols | C24: Fall Protection & High-Altitude Safety | D24: v2.1 | G24: 5000 Production | H24: 5000.05.02 | I24: Rigging Hardware | J24: 5000.51.02 | K24: {=_xlfn.XLOOKUP(J24, 'Roles Library'!$A$2:$A100, 'Roles Library'!$B$2:$B100, "")} -> Head Arena / Festival Rigger | L24: TAG-002 OSHA · ANSI A92.20 Full-Body Fall Arrest Harness, Shock-Absorbing Lanyard, Hard Hat with Chinstrap | M24: Fall protection plan active (DOC-023); certified MEWP operators rostered; ground drop-zone barricades staged. | N24: Pre-Operation MEWP Walkaround: Perform daily pre-start inspection on scissor lift and articulating boom lift; test ground/basket emergency stop controls and hydraulic lines. | O24: Fall Restraint Lanyard Anchorage: Prior to raising platform, attach harness lanyard to designated engineered anchor point inside basket; confirm 100% tie-off compliance. | P24: Ground Perimeter Drop-Zone Lockout: Establish physical stanchions and red warning tape directly below elevated work basket; position ground spotter with whistle. | Q24: Elevated Maneuver & Overhead Clearance: Operate platform smoothly at crawl speed; maintain minimum 10-ft clearance from overhead building utilities, beams, and HVAC ducts. | R24: DOC-023 | S24: {=_xlfn.XLOOKUP(R24, 'Document & Asset Library'!$A$2:$A100, 'Document & Asset Library'!$B$2:$B100, "")} -> OSHA Fall Protection & Aerial Work Platform (AWP) Safety Protocol | T24: Active | U24: FALSE | V24: OSHA 1926.453 & ANSI/SAIA A92.22 safe use of mobile elevating work platforms (MEWPs). | W24: Julian Clarkson | X24: 46297.413 | Y24: 46297
A25: SOP-024 | B25: Structural Rigging Hardware Proof-Testing & Beam Clamp Installation | C25: Structural & Rigging Safety | D25: v1.0 | G25: 5000 Production | H25: 5000.05.02 | I25: Rigging Hardware | J25: 5000.51.03 | K25: {=_xlfn.XLOOKUP(J25, 'Roles Library'!$A$2:$A100, 'Roles Library'!$B$2:$B100, "")} -> Lead System Rigger | L25: TAG-002 OSHA · TAG-022 ETCP · Hard Hat, Steel-Toe Boots, Heavy Leather Rigging Gloves, Fall Harness | M25: Structural proof pull-test cert on file (DOC-024); stamped rigging plot DOC-004 approved; torque wrench calibrated. | N25: Visual Hardware Grade Inspection: Inspect all 5/8-in Crosby shackles, G-100 master links, wire rope slings, and polyester Spansets; verify zero elongation, cuts, or heat damage. | O25: Engineered Beam Clamp Placement: Mount forged steel beam clamps to approved structural I-beams per stamped plot; torque clamp locking nuts to manufacturer specified foot-pounds. | P25: Secondary Safety Choker Rigging: Rig independent wire rope safety secondary choker around building structural beam node; mouse all shackle pins with stainless safety wire. | Q25: Test Pull & Load Cell Zeroing: Hang calibrated digital wireless load cell from hook; perform test pull; zero load cell before pinning truss bridles; log static tare weights. | R25: DOC-024 | S25: {=_xlfn.XLOOKUP(R25, 'Document & Asset Library'!$A$2:$A100, 'Document & Asset Library'!$B$2:$B100, "")} -> ANSI ES1.9 Rigging Point Inspection & Proof Test Certification | T25: Active | U25: FALSE | V25: ANSI ES1.6 & OSHA 1910.184 entertainment rigging hardware inspection and proof-testing. | W25: Julian Clarkson | X25: 46297.413 | Y25: 46297
A26: SOP-025 | B26: Live Show Stage Management, SMPTE Timecode Sync & Performer Handover | C26: Stage Management & Live Production Control | D26: v4.0 | G26: 9000 Technology | H26: 9000.50.01 | I26: Show Control & Playback | J26: 9000.50.01 | K26: {=_xlfn.XLOOKUP(J26, 'Roles Library'!$A$2:$A100, 'Roles Library'!$B$2:$B100, "")} -> Production Stage Manager | L26: Clear-Com Headset, Production Flashlight with Red Filter, Run of Show Binder | M26: Master cue schedule active (DOC-025); SMPTE timecode sync generator locked (29.97 fps); artist green room escort in place. | N26: Master Timecode Clock Lock: Verify SMPTE linear timecode lock across playback DAWs, grandMA3 lighting desks, and disguise d3 media servers; confirm zero frame drift. | O26: Talent Escort & Mic Sanitization (T-00:20): Escort headline artist from dressing room to stage left; fit sanitized wireless handheld mic and test custom IEM mix with A2. | P26: Standby Call Sequence (T-00:02): Issue verbal countdown on Comms Ch A & B: 'Standby Top of Show, Standby Lighting Look 01, Standby Video Blade 01, Standby Audio Playback'. | Q26: Show Trigger GO & Live Changeover: Call crisp 'GO' trigger precisely at 20:00:00; monitor live performance telemetry; oversee seamless 8-minute DJ to live band changeover. | R26: DOC-025 | S26: {=_xlfn.XLOOKUP(R26, 'Document & Asset Library'!$A$2:$A100, 'Document & Asset Library'!$B$2:$B100, "")} -> Master Run of Show & SMPTE Timecode Production Cue Sheet | T26: Active | U26: FALSE | V26: Production stage management and SMPTE timecode synchronization live execution protocol. | W26: Julian Clarkson | X26: 46297.413 | Y26: 46297
A27: SOP-026 | B27: Solid Waste Diversion, Compost Sorting & Post-Event Site Sanitation | C27: Environmental Sustainability & Waste Operations | D27: v1.0 | G27: 6000 Operations | H27: 6000.09.01 | I27: Waste Management | J27: 6000.51.01 | K27: {=_xlfn.XLOOKUP(J27, 'Roles Library'!$A$2:$A100, 'Roles Library'!$B$2:$B100, "")} -> Janitorial & Waste Operations Lead | L27: TAG-002 OSHA · Heavy-Duty Nitrile Cleaning Gloves, Steel-Toe Boots, High-Vis Vest, Safety Glasses | M27: Waste diversion plan active (DOC-026); dual-stream recycling/trash pairs staged; compost dumpster spotted in yard. | N27: Pre-Event Waste Station Deployment: Position co-located 3-stream waste stations (Compost, Clean Recycling, Landfill) every 25 ft across sanctuary and patio with visual signage. | O27: Live Shift Monitoring & Bin Turnaround: Rove public areas; empty bins before reaching 75% capacity; replace with color-coded biodegradable liners; haul bags to rear compactor. | P27: Post-Event Floor Magnetic & Mechanical Sweep: Following patron egress, execute rolling magnet sweep across lawn/patio for metal fasteners; complete wet mop of polished concrete floors. | Q27: Waste Stream Weighing & Diversion Reporting: Record weights of compost, single-stream recyclables, and landfill haul; compute event diversion percentage for sustainability report. | R27: DOC-026 | S27: {=_xlfn.XLOOKUP(R27, 'Document & Asset Library'!$A$2:$A100, 'Document & Asset Library'!$B$2:$B100, "")} -> Solid Waste Diversion, Composting & Site Sanitation Log | T27: Active | U27: FALSE | V27: Zero-waste event certification & LEED temporary event waste diversion protocol. | W27: Julian Clarkson | X27: 46297.413 | Y27: 46297
A28: SOP-027 | B28: Temporary Potable Water Plumbing, Backflow Prevention & Disinfection | C28: Water Distribution & Plumbing Hygiene | D28: v1.0 | G28: 6000 Operations | H28: 6000.06.04 | I28: Water & Plumbing | J28: 4000.51.01 | K28: {=_xlfn.XLOOKUP(J28, 'Roles Library'!$A$2:$A100, 'Roles Library'!$B$2:$B100, "")} -> HVAC & Site Climate Tech | L28: TAG-002 OSHA · NSF Food-Grade Rubber Gloves, Safety Glasses, Pipe Wrenches | M28: Backflow inspection cert active (DOC-027); certified reduced pressure backflow preventer (RPBP) mounted; potable NSF-61 hoses sanitized. | N28: Source Tie-In & Backflow Assembly Installation: Connect primary water supply to municipal spigot; install tested RPBP backflow preventer; verify zero cross-contamination. | O28: Distribution Line Chlorination & Flush: Flush temporary potable distribution lines with 50 ppm chlorine solution for 24 hours; flush with fresh water until residual chlorine <0.5 ppm. | P28: Potable Water Distribution & Pressure Regulation: Connect NSF-61 certified food-grade hoses to catering prep trailers, beverage carts, and handwash sinks; regulate pressure to 45 PSI. | Q28: Daily Water Quality Sampling & Drain Inspection: Conduct daily chlorine and bacterial dip test; inspect gray water collection tanks; schedule pump-out truck before tanks reach 80%. | R28: DOC-027 | S28: {=_xlfn.XLOOKUP(R28, 'Document & Asset Library'!$A$2:$A100, 'Document & Asset Library'!$B$2:$B100, "")} -> Temporary Potable Water System Disinfection & Backflow Certification | T28: Active | U28: FALSE | V28: IPC Section 608 & Miami-Dade WASD temporary potable water distribution protocol. | W28: Julian Clarkson | X28: 46297.413 | Y28: 46297
A29: SOP-028 | B29: RFID / NFC Credential Issuance, Zone Access Encoding & Anti-Passback Validation | C29: Credentialing Systems & Access Security | D29: v2.0 | G29: 7000 Experience | H29: 7000.50.02 | I29: Credentials | J29: 7000.50.02 | K29: {=_xlfn.XLOOKUP(J29, 'Roles Library'!$A$2:$A100, 'Roles Library'!$B$2:$B100, "")} -> Credential Operations Coordinator | L29: None Required (Administrative / Tech) | M29: Credential security matrix approved (DOC-028); encrypted RFID wristbands in vault; Zebra RFID badge printers online. | N29: Master Credential Database Sync: Ingest approved personnel roster and VIP guest list into access management server; assign unique encrypted UID per record. | O29: RFID Wristband Encoding & Physical Verification: Encode 13.56 MHz NFC wristband chips with tier permissions (All-Access, VIP, Production, GA); visually inspect tamper-evident clasp. | P29: Turnstile Validation & Anti-Passback Enforcement: Configure optical turnstiles and handheld scanners with 15-minute anti-passback rule; verify sub-second scan validation latency. | Q29: Real-Time Attendance Headcount Monitoring: Track live scan feeds to maintain real-time occupant counts per zone; alert security if sanctuary approaches 350 occupant cap. | R29: DOC-028 | S29: {=_xlfn.XLOOKUP(R29, 'Document & Asset Library'!$A$2:$A100, 'Document & Asset Library'!$B$2:$B100, "")} -> RFID Credentialing Architecture & Zone Security Matrix | T29: Active | U29: FALSE | V29: ISO/IEC 14443 & PCI compliance event access credentialing protocol. | W29: Julian Clarkson | X29: 46297.413 | Y29: 46297
A30: SOP-029 | B30: Marshalling Yard Loading Dock Traffic Management, Forklift & Rig Staging | C30: Logistics Operations & Loading Dock Safety | D30: v2.2 | G30: 6000 Operations | H30: 6000.02.01 | I30: Forklifts & Loaders | J30: 6000.51.02 | K30: {=_xlfn.XLOOKUP(J30, 'Roles Library'!$A$2:$A100, 'Roles Library'!$B$2:$B100, "")} -> Marshalling Yard & Dock Master | L30: TAG-002 OSHA · TAG-018 ANSI · Steel-Toe Boots, High-Vis Vest, Hard Hat, Work Gloves, Radio (Channel 3) | M30: Dock booking schedule locked (DOC-029); certified forklift operators on call; yellow jacket cable ramps installed across traffic lane. | N30: Carrier Arrival Check-In & Yard Spotting: Check in carrier trucks at marshalling gate; verify seal numbers against manifest; assign designated trailer staging bay. | O30: Loading Dock Safety Sequence: Position trailer at Dock 1; engage tractor spring brakes; set dual rubber wheel chocks; lower trailer support stabilizing jacks. | P30: Forklift Unloading & Floor Load Distribution: Unload heavy rigging road cases using 5,000-lb forklift; distribute weight evenly across dock floor; maintain clear 8-ft aisleways. | Q30: Dock Clearance & Carrier Release Sign-Off: Clear empty pallets and dunnage; inspect trailer floor for damage; sign carrier Bill of Lading with time stamp; dispatch carrier. | R30: DOC-029 | S30: {=_xlfn.XLOOKUP(R30, 'Document & Asset Library'!$A$2:$A100, 'Document & Asset Library'!$B$2:$B100, "")} -> Marshalling Yard Freight Schedule & Dock Booking Master | T30: Active | U30: FALSE | V30: OSHA 1910.178 powered industrial trucks and loading dock freight safety procedures. | W30: Julian Clarkson | X30: 46297.413 | Y30: 46297
A31: SOP-030 | B31: Temporary HVAC Spot Cooler Deployment, Ducting & Condensate Management | C31: Climate Control & Environmental Engineering | D31: v1.2 | G31: 4000 Environment | H31: 4000.51.02 | I31: Climate Control | J31: 4000.51.01 | K31: {=_xlfn.XLOOKUP(J31, 'Roles Library'!$A$2:$A100, 'Roles Library'!$B$2:$B100, "")} -> HVAC & Site Climate Tech | L31: TAG-002 OSHA · Safety Glasses, Work Gloves, ANSI Steel-Toe Boots | M31: HVAC load calculation on file (DOC-030); 208V 3-phase power drop verified; spot coolers staged in BOH corridor. | N31: Spot Cooler Placement & Power Verification: Position 5-ton spot coolers in designated cooling nodes; connect 50A twist-lock power cables; verify proper phase rotation. | O31: Flexible Ducting Run & Supply Air Balancing: Route 12-inch insulated flexible supply ducts to audience hot zones and stage wings; secure duct runs with zip ties and aircraft cable. | P31: Condensate Pump & Drainage Routing: Connect automatic condensate sump pumps to drainage tubing; route discharge lines to sanitary sewer drain; test float switch cutoff. | Q31: Thermostat Calibration & Thermal Load Monitoring: Set digital thermostats to maintain 72 deg F ambient / 50% relative humidity; monitor server rack and LED wall exhaust zones. | R31: DOC-030 | S31: {=_xlfn.XLOOKUP(R31, 'Document & Asset Library'!$A$2:$A100, 'Document & Asset Library'!$B$2:$B100, "")} -> Temporary HVAC Load Calculation & Psychrometric Cooling Plan | T31: Active | U31: FALSE | V31: ASHRAE Standard 55 & Florida Mechanical Code temporary event cooling protocol. | W31: Julian Clarkson | X31: 46297.413 | Y31: 46297
A32: SOP-031 | B32: Talent Hospitality Advancing, Green Room Security & Rider Execution | C32: Artist Production & Hospitality Management | D32: v1.0 | G32: 2000 Talent | H32: 2000.03.01 | I32: Advancing | J32: 2000.50.02 | K32: {=_xlfn.XLOOKUP(J32, 'Roles Library'!$A$2:$A100, 'Roles Library'!$B$2:$B100, "")} -> Artist Relations Coordinator | L32: Artist Relations Access Lanyard, Production Radio (Channel 4) | M32: Countersigned talent contract on file (DOC-031); rider fulfillment items procured; green room lockbox combination set. | N32: Green Room Space Preparation & Inspection: Deep clean artist green room; stage requested FF&E (couches, mirrors, garment steamer); verify private restroom stocked and locked. | O32: Rider Food & Beverage Fulfillment: Stock rider-specified beverages, organic snacks, and local specialty provisions; verify strict adherence to dietary restrictions and allergies. | P32: Green Room Access Security Lockout: Post security officer outside artist dressing room suite; enforce strict closed-door policy; permit access only to badge-verified roster. | Q32: Artist Settlement & Sign-Off Documentation: Review hospitality receipts with artist road manager; confirm cash per-diems disbursed; obtain countersigned settlement voucher. | R32: DOC-031 | S32: {=_xlfn.XLOOKUP(R32, 'Document & Asset Library'!$A$2:$A100, 'Document & Asset Library'!$B$2:$B100, "")} -> Artist Performance Contract, Music Publishing & Sync Clearances | T32: Active | U32: FALSE | V32: GHXSTSHIP talent advancing standards and artist hospitality execution procedure. | W32: Julian Clarkson | X32: 46297.413 | Y32: 46297
A33: SOP-032 | B33: Incident Command CAD Logging, Mass Notification & AHJ Escalation | C33: Crisis Communications & Incident Command | D33: v2.0 | G33: 6000 Operations | H33: 6000.05.01 | I33: Incident Management | J33: 6000.50.02 | K33: {=_xlfn.XLOOKUP(J33, 'Roles Library'!$A$2:$A100, 'Roles Library'!$B$2:$B100, "")} -> Site Safety & Security Lead | L33: Clear-Com Headset, Mobile CAD Dispatch Tablet, Radio (Channel 1) | M33: Emergency Action Plan active (DOC-032); multi-channel radio matrix active; direct dispatch link to Miami 911 PSAP. | N33: CAD Incident Ingest & Verification: Receive incident report on Radio Ch 1; record exact timestamp, location code (LOC-xx), reporting party, and severity level in CAD log. | O33: Tactical Resource Dispatch: Dispatch nearest security officer, EMT team, or technical lead based on incident class; maintain active timer on response milestone. | P33: Mass Notification Alert Triggering: In event of major life safety emergency, activate pre-recorded audio/visual evacuation message across all PA clusters and LED displays. | Q33: AHJ Briefing & Incident Debrief Closure: Coordinate on-site briefing with responding Miami Fire/Police commanders; document resolution notes and witness statements; close ticket. | R33: DOC-032 | S33: {=_xlfn.XLOOKUP(R33, 'Document & Asset Library'!$A$2:$A100, 'Document & Asset Library'!$B$2:$B100, "")} -> Incident Command Structure (ICS) & Emergency CAD Dispatch Guide | T33: Active | U33: FALSE | V33: FEMA NIMS Incident Command System & NFPA 3000 emergency operations procedure. | W33: Julian Clarkson | X33: 46297.413 | Y33: 46297
A34: SOP-033 | B34: Environmental Scent Diffusion Nebulization & Fragrance Safety Control | C34: Sensory Design & Atmosphere Management | D34: v1.1 | G34: 7000 Experience | H34: 7000.04.01 | I34: Scent Diffusion | J34: 7000.50.01 | K34: {=_xlfn.XLOOKUP(J34, 'Roles Library'!$A$2:$A100, 'Roles Library'!$B$2:$B100, "")} -> Front of House Lead / Box Office Manager | L34: Nitrile Handling Gloves, Safety Glasses | M34: IFRA compliance safety data sheet active (DOC-033); cold-air nebulizers installed; botanical aroma cartridges stocked. | N34: Cartridge Ingest & IFRA Batch Verification: Inspect aroma oil cartridges; verify IFRA safety certificates and batch numbers; ensure 100% hypoallergenic, phthalate-free oil. | O34: Nebulizer Installation & HVAC Ducted Interface: Install cold-air diffusion units in primary air handler supply plenums; calibrate sub-micron droplet atomization. | P34: Daypart Intensity Programming: Program digital diffusion duty cycles: 20% intensity for daytime arrival, 45% for evening reception, 10% during high-energy performance. | Q34: Sensory Air Quality Monitoring: Inspect venue air quality; ensure zero visible haze or oil residue on surfaces; log guest feedback and adjust fragrance concentration. | R34: DOC-033 | S34: {=_xlfn.XLOOKUP(R34, 'Document & Asset Library'!$A$2:$A100, 'Document & Asset Library'!$B$2:$B100, "")} -> Scent Diffusion Formulation & Hypoallergenic Safety Data Sheet (SDS) | T34: Active | U34: FALSE | V34: IFRA Standards & OSHA indoor air quality environmental fragrancing protocol. | W34: Julian Clarkson | X34: 46297.413 | Y34: 46297
A35: SOP-034 | B35: Post-Event Venue Space Handover, Damage Inspection & Landlord Sign-Off | C35: Facility Restoration & Space Handover | D35: v1.0 | G35: 0000 Executive | H35: 0000.50.04 | I35: Close Activities | J35: 0000.50.01 | K35: {=_xlfn.XLOOKUP(J35, 'Roles Library'!$A$2:$A100, 'Roles Library'!$B$2:$B100, "")} -> Chief Executive Officer | L35: High-Vis Vest, Flashlight, Digital Camera / Tablet | M35: Architectural site CAD on file (DOC-034); pre-lease baseline photographic survey on file; strike completed (SOP-008). | N35: Joint Architectural Walkthrough: Conduct comprehensive physical walk of sanctuary, patio, mezzanine, and parking facilities with building owner / landlord representative. | O35: Photographic Punch List Generation: Photograph all surfaces, doors, glazing, and electrical tie-in panels; document any pre-existing vs event-related wear or marks. | P35: Immediate Restoration Remediation: Deploy facilities maintenance technician to patch minor drywall blemishes, paint scuffs, or replace blown utility light bulbs. | Q35: Formal Handover Sign-Off & Security Deposit Release: Execute countersigned space release and condition certificate; submit documentation to finance for security bond return. | R35: DOC-034 | S35: {=_xlfn.XLOOKUP(R35, 'Document & Asset Library'!$A$2:$A100, 'Document & Asset Library'!$B$2:$B100, "")} -> Post-Event Site Restoration & Landlord Handover Inspection Log | T35: Active | U35: FALSE | V35: Commercial lease surrender and post-production venue restoration sign-off procedure. | W35: Julian Clarkson | X35: 46297.413 | Y35: 46297

Sheet Locations
A1: RECORD ID | B1: PROJECT ID | C1: DEPARTMENT | D1: CATEGORY | E1: SUB CATEGORY | F1: LOCATION | G1: DESCRIPTION | H1: STATUS | I1: FLAG | J1: NOTES | K1: CREATED BY | L1: CREATED AT | M1: UPDATED AT
A2: LOC-01 | B2: ='Cover Page'!$C$7 -> CSMIA26 | C2: Site Operations | D2: Stage | E2: Main Stage | F2: Zone B - Main Stage | G2: Primary festival performance stage and FOH corridor | H2: Active | I2: FALSE | J2: Safety ramp inspection cleared | K2: Julian Clarkson | L2: 46295.545 | M2: 46295.545
A3: LOC-02 | B3: ='Cover Page'!$C$7 -> CSMIA26 | C3: Guest Experience | D3: Gates | E3: Box Office | F3: Gate 1 - North Box Office | G3: Primary attendee entrance and wristband exchange | H3: Active | I3: FALSE | J3: Guest services lockbox compartment on site | K3: Sarah Jenkins | L3: 46295.545 | M3: 46295.545
A4: LOC-03 | B4: ='Cover Page'!$C$7 -> CSMIA26 | C4: Technical Production | D4: Production Office | E4: Quartermaster | F4: Production Office / Quartermaster | G4: Central technical asset check-out and production admin | H4: Active | I4: FALSE | J4: Radio depot and surveillance kit hub | K4: Alex Rivera | L4: 46295.545 | M4: 46295.545
A5: LOC-04 | B5: ='Cover Page'!$C$7 -> CSMIA26 | C5: Stage Operations | D5: Back of House | E5: Stage Left | F5: Back of House - Stage Left | G5: Stage deck build, crew check-in, and truss staging | H5: Active | I5: FALSE | J5: Overhire stagehand crew muster point | K5: Julian Clarkson | L5: 46295.545 | M5: 46295.545
A6: LOC-05 | B6: ='Cover Page'!$C$7 -> CSMIA26 | C6: Logistics / Site Ops | D6: Loading Dock | E6: Freight | F6: Loading Dock B | G6: Heavy freight delivery intake and staging dock | H6: Active | I6: FALSE | J6: BOL filing and crate intake hub | K6: Elena Rostova | L6: 46295.545 | M6: 46295.545
A7: LOC-06 | B7: ='Cover Page'!$C$7 -> CSMIA26 | C7: Catering & Hospitality | D7: Hospitality | E7: Artist Village | F7: Artist Village Green Room | G7: Artist hospitality green room suites and compound | H7: Active | I7: FALSE | J7: Hospitality logistics and catering runs | K7: Sarah Jenkins | L7: 46295.545 | M7: 46295.545
A8: LOC-07 | B8: ='Cover Page'!$C$7 -> CSMIA26 | C8: Site Operations | D8: Power Compound | E8: Generators | F8: Zone D - Generator Compound 2 | G8: Primary 250kVA generator compound and fuel bank | H8: Active | I8: FALSE | J8: Fuel technician dispatch monitoring | K8: Julian Clarkson | L8: 46295.545 | M8: 46295.545
A9: LOC-08 | B9: ='Cover Page'!$C$7 -> CSMIA26 | C9: Security | D9: Perimeter | E9: Gates | F9: Gate 2 - South Gate | G9: Secondary patron ingress and emergency egress | H9: Active | I9: FALSE | J9: Perimeter access point | K9: Julian Clarkson | L9: 46295.545 | M9: 46295.545
A10: LOC-09 | B10: ='Cover Page'!$C$7 -> CSMIA26 | C10: Medical | D10: Health & Safety | E10: First Aid | F10: Medical Tent A - Zone A | G10: Primary triage station and emergency EMT center | H10: Active | I10: FALSE | J10: Paramedic team base | K10: Julian Clarkson | L10: 46295.545 | M10: 46295.545
A11: LOC-10 | B11: ='Cover Page'!$C$7 -> CSMIA26 | C11: Site Operations | D11: Sanitation | E11: Facilities | F11: Sanitation Compound East | G11: Waste management and greywater pumping depot | H11: Active | I11: FALSE | J11: Scheduled servicing route | K11: Julian Clarkson | L11: 46295.545 | M11: 46295.545
A12: LOC-11 | B12: ='Cover Page'!$C$7 -> CSMIA26 | C12: Food & Beverage | D12: Concessions | E12: Bar 1 | F12: Zone A Concessions Row | G12: Main public beverage dispensing stations | H12: Active | I12: FALSE | J12: POS terminals and beverage stock | K12: Julian Clarkson | L12: 46295.545 | M12: 46295.545
A13: LOC-12 | B13: ='Cover Page'!$C$7 -> CSMIA26 | C13: Site Operations | D13: Power Compound | E13: Distribution | F13: Zone A - Power Compound 1 | G13: Audio/visual power distro transformers | H13: Active | I13: FALSE | J13: Load balancing regular checks | K13: Julian Clarkson | L13: 46295.545 | M13: 46295.545
... A33: LOC-32 | B33: ='Cover Page'!$C$7 -> CSMIA26 | C33: Site Operations | D33: Venue | E33: Main Property | F33: The Sanctuary MiMo | G33: Historic sanctuary venue in MiMo district | H33: Active | I33: FALSE | J33: Primary venue property | K33: Julian Clarkson | L33: 46295.545 | M33: 46295.545

Sheet Shipping Manifest
A1: RECORD ID | B1: PROJECT ID | C1: DEPARTMENT | D1: CATEGORY | E1: SUB CATEGORY | F1: VENDOR ID | G1: ITEM | H1: DESCRIPTION | I1: CONTAINER | J1: PALLET COUNT | K1: PIECE COUNT | L1: LENGTH (FT) | M1: WIDTH (FT) | N1: HEIGHT (FT) | O1: VOLUME (CU FT) | P1: DIMENSIONS | Q1: WEIGHT | R1: SHIPMENT DATE | S1: SENDER | T1: ORIGIN | U1: PERSONNEL ID | V1: LOCATION ID | W1: CARRIER | X1: CARRIER PHONE | Y1: TRAILER LICENSE | Z1: SEAL NUMBER | AA1: FREIGHT TYPE | AB1: TRACKING NUMBER | AC1: BILL OF LADING (BOL) | AD1: STATUS | AE1: FLAG | AF1: NOTES | AG1: CREATED BY | AH1: CREATED AT | AI1: UPDATED AT
A2: SHP-001 | B2: ='Cover Page'!$C$7 -> CSMIA26 | C2: 5000 Production | D2: 5000.52.01 | E2: Freight Inbound | F2: VEN-001 | G2: Main Stage Line Array & Truss Rig | H2: Heavy staging & line array dispatch | I2: 53ft Semi | J2: 26 | K2: 84 | L2: 53 | M2: 8.5 | N2: 13.5 | O2: =ROUND(L2*M2*N2, 2) -> 6081.75 | P2: =L2 & " ft x " & M2 & " ft x " & N2 & " ft" -> 53 ft x 8.5 ft x 13.5 ft | Q2: 45,000 lbs | R2: 46297 | S2: PRG Logistics | T2: Orlando, FL | U2: P-021 | V2: LOC-31 | W2: PRG Freight | X2: (800) 555-0191 | Y2: FL-TL-8821 | Z2: SL-990142 | AA2: Ground Freight | AB2: TRK-88219 | AC2: BOL-IIIP-01 | AD2: Scheduled | AE2: FALSE | AF2: Priority load-in delivery; calltime 08:00 EDT | AG2: Julian Clarkson | AH2: 46296 | AI2: 46296
A3: SHP-002 | B3: ='Cover Page'!$C$7 -> CSMIA26 | C3: 5000 Production | D3: 5000.03.01 | E3: Video Inbound | F3: VEN-014 | G3: LED Video Tiles & Processors | H3: High-res outdoor wall panels | I3: 26ft Box Truck | J3: 12 | K3: 48 | L3: 26 | M3: 8 | N3: 12.5 | O3: =ROUND(L3*M3*N3, 2) -> 2600 | P3: =L3 & " ft x " & M3 & " ft x " & N3 & " ft" -> 26 ft x 8 ft x 12.5 ft | Q3: 10,000 lbs | R3: 46301 | S3: NEP Screenworks | T3: Miami, FL | U3: P-021 | V3: LOC-05 | W3: NEP Logistics | X3: (305) 555-0182 | Y3: FL-BX-4410 | Z3: SL-990143 | AA3: Ground Freight | AB3: TRK-99301 | AC3: BOL-IIIP-02 | AD3: Scheduled | AE3: FALSE | AF3: Indoor & outdoor LED walls; calltime 10:00 EDT | AG3: Julian Clarkson | AH3: 46296 | AI3: 46296
A4: SHP-003 | B4: ='Cover Page'!$C$7 -> CSMIA26 | C4: 5000 Production | D4: 5000.52.01 | E4: Freight Outbound | F4: VEN-001 | G4: Full Production Strike & Return | H4: Post-event outbound return freight | I4: 53ft Semi | J4: 26 | K4: 84 | L4: 53 | M4: 8.5 | N4: 13.5 | O4: =ROUND(L4*M4*N4, 2) -> 6081.75 | P4: =L4 & " ft x " & M4 & " ft x " & N4 & " ft" -> 53 ft x 8.5 ft x 13.5 ft | Q4: 45,000 lbs | R4: 46314 | S4: Mana Wynwood | T4: Miami, FL | U4: P-021 | V4: LOC-31 | W4: PRG Freight | X4: (800) 555-0191 | Y4: FL-TL-8822 | Z4: SL-990144 | AA4: Ground Freight | AB4: TRK-88220 | AC4: BOL-IIIP-03 | AD4: Scheduled | AE4: FALSE | AF4: Strike and venue return; calltime 06:00 EDT | AG4: Julian Clarkson | AH4: 46296 | AI4: 46296

Sheet Marshalling Yard Log
A1: RECORD ID | B1: PROJECT ID | C1: DEPARTMENT | D1: CATEGORY | E1: SUB CATEGORY | F1: VEHICLE CALLSIGN | G1: CARRIER / VENDOR ID | H1: SHIPMENT ID | I1: VEHICLE TYPE | J1: DRIVER NAME | K1: CARRIER PHONE | L1: TRAILER LICENSE | M1: SEAL NUMBER | N1: DIMENSIONS | O1: WEIGHT | P1: STAGING BAY | Q1: TARGET DOCK ID | R1: CHECK-IN TIME | S1: DOCK CALL TIME | T1: DOCK RELEASE TIME | U1: STATUS | V1: FLAG | W1: NOTES | X1: CREATED BY | Y1: CREATED AT | Z1: UPDATED AT
A2: MYL-001 | B2: ='Cover Page'!$C$7 -> CSMIA26 | C2: 6000 Operations | D2: 6000.02.07 | E2: Freight Staging | F2: TRUCK-01 | G2: VEN-001 | H2: SHP-001 | I2: 53ft Tractor-Trailer | J2: Carlos Gomez | K2: (407) 555-0142 | L2: FL-TL-8821 | M2: SL-990142 | N2: 53ft x 8.5ft x 13.5ft | O2: 45,000 lbs | P2: BAY-01 | Q2: LOC-31 | R2: 46297.312 | S2: 46297.333 | T2: 46297.479 | U2: Staged | V2: FALSE | W2: Arrived on schedule; holding for dock A clearance | X2: Julian Clarkson | Y2: 46296 | Z2: 46296
A3: MYL-002 | B3: ='Cover Page'!$C$7 -> CSMIA26 | C3: 6000 Operations | D3: 6000.02.07 | E3: Video Staging | F3: TRUCK-02 | G3: VEN-014 | H3: SHP-002 | I3: 26ft Box Truck | J3: Marcus Vance | K3: (305) 555-0178 | L3: FL-BX-4410 | M3: SL-990143 | N3: 26ft x 8.0ft x 12.5ft | O3: 10,000 lbs | P3: BAY-02 | Q3: LOC-05 | R3: 46301.396 | S3: 46301.417 | T3: 46301.542 | U3: Staged | V3: FALSE | W3: LED wall freight queued for unload | X3: Julian Clarkson | Y3: 46296 | Z3: 46296

Sheet Advance Requests
A1: RECORD ID | B1: ORGANIZATION | C1: PROJECT ID | D1: DEPARTMENT | E1: CATEGORY | F1: SUB CATEGORY | G1: VENDOR ID | H1: ITEM | I1: DESCRIPTION | J1: URID | K1: QUANTITY | L1: UNIT BASIS | M1: ESTIMATE RATE | N1: TOTAL ESTIMATE | O1: LOCATION ID | P1: NEEDED BY DATE | Q1: REQUESTED BY | R1: APPROVER ROLE | S1: APPROVAL DATE | T1: PO NUMBER | U1: STATUS | V1: FLAG | W1: NOTES | X1: CREATED BY | Y1: CREATED AT | Z1: UPDATED AT

Sheet Hospitality Fulfillment
A1: RECORD ID | B1: ORGANIZATION | C1: PROJECT ID | D1: DEPARTMENT | E1: CATEGORY | F1: SUB CATEGORY | G1: ARTIST NAME | H1: LOCATION ID | I1: LIAISON ID | J1: RIDER CONTRACT REF | K1: CATERING PACKAGE | L1: DIETARY REQUIREMENTS | M1: HEADCOUNT | N1: DELIVERY DEADLINE | O1: DELIVERY POINT | P1: SERVICE STYLE | Q1: STATUS | R1: FLAG | S1: NOTES | T1: CREATED BY | U1: CREATED AT | V1: UPDATED AT

Sheet Asset Inventory
A1: RECORD ID | B1: PROJECT ID | C1: ITEM ID | D1: ITEM | E1: DESCRIPTION | F1: SPECIFICATIONS | G1: COLOR | H1: MAKE & MODEL | I1: SERIAL NUMBER | J1: LABEL | K1: QUANTITY | L1: CONDITION | M1: LOCATION ID | N1: VENDOR ID | O1: UNIT COST | P1: STATUS | Q1: FLAG | R1: NOTES | S1: CREATED BY | T1: CREATED AT | U1: UPDATED AT
A2: AST-0001 | B2: ='Cover Page'!$C$7 -> CSMIA26 | C2: 9000.03.01-XPMS-004 | D2: {=IF(ISBLANK(C2), "", _xlfn.XLOOKUP(C2, 'Procurement Catalog'!$A$2:$A1038, 'Procurement Catalog'!$C$2:$C1038, ""))} -> Radio - Two-Way - Standard | E2: {=IF(ISBLANK(C2), "", _xlfn.XLOOKUP(C2, 'Procurement Catalog'!$A$2:$A1038, 'Procurement Catalog'!$M$2:$M1038, ""))} -> UHF or VHF handheld two-way radio for event operations. | F2: {=IF(ISBLANK(C2), "", _xlfn.XLOOKUP(C2, 'Procurement Catalog'!$A$2:$A1038, 'Procurement Catalog'!$N$2:$N1038, ""))} | G2: Black | I2: SN-CP200-001 | J2: Radio 01 | K2: 1 | L2: Good | M2: LOC-03 | N2: VEN-021 | O2: {=IF(ISBLANK(C2), "", _xlfn.XLOOKUP(C2, 'Procurement Catalog'!$A$2:$A1038, 'Procurement Catalog'!$K$2:$K1038, ""))} -> 15 | P2: Active | Q2: FALSE | R2: Standard comms allocation | S2: Julian Clarkson | T2: 46280 | U2: 46280
A3: AST-0002 | B3: ='Cover Page'!$C$7 -> CSMIA26 | C3: 5000.05.01-XPMS-001 | D3: {=IF(ISBLANK(C3), "", _xlfn.XLOOKUP(C3, 'Procurement Catalog'!$A$2:$A1038, 'Procurement Catalog'!$C$2:$C1038, ""))} -> Chain Motor - Half Ton | E3: {=IF(ISBLANK(C3), "", _xlfn.XLOOKUP(C3, 'Procurement Catalog'!$A$2:$A1038, 'Procurement Catalog'!$M$2:$M1038, ""))} -> Half-ton (1,000 lb) electric chain hoist for lighting and scenic rigging. | F3: {=IF(ISBLANK(C3), "", _xlfn.XLOOKUP(C3, 'Procurement Catalog'!$A$2:$A1038, 'Procurement Catalog'!$N$2:$N1038, ""))} -> 1/2 ton capacity | 60ft chain | Variable speed. | G3: Black | I3: SN-MOTR-0881 | J3: Motor 01 | K3: 1 | L3: Excellent | M3: LOC-01 | N3: VEN-012 | O3: {=IF(ISBLANK(C3), "", _xlfn.XLOOKUP(C3, 'Procurement Catalog'!$A$2:$A1038, 'Procurement Catalog'!$K$2:$K1038, ""))} -> 48.5 | P3: Active | Q3: FALSE | R3: Overhead hoist point | S3: Julian Clarkson | T3: 46280 | U3: 46280
A4: AST-0003 | B4: ='Cover Page'!$C$7 -> CSMIA26 | C4: 9000.03.02-XPMS-002 | D4: {=IF(ISBLANK(C4), "", _xlfn.XLOOKUP(C4, 'Procurement Catalog'!$A$2:$A1038, 'Procurement Catalog'!$C$2:$C1038, ""))} -> Intercom - Wireless | E4: {=IF(ISBLANK(C4), "", _xlfn.XLOOKUP(C4, 'Procurement Catalog'!$A$2:$A1038, 'Procurement Catalog'!$M$2:$M1038, ""))} -> Digital wireless intercom for mobile production staff. | F4: {=IF(ISBLANK(C4), "", _xlfn.XLOOKUP(C4, 'Procurement Catalog'!$A$2:$A1038, 'Procurement Catalog'!$N$2:$N1038, ""))} | G4: Black | I4: SN-BOLERO-014 | J4: Beltpack 01 | K4: 1 | L4: Good | M4: LOC-04 | N4: VEN-015 | O4: {=IF(ISBLANK(C4), "", _xlfn.XLOOKUP(C4, 'Procurement Catalog'!$A$2:$A1038, 'Procurement Catalog'!$K$2:$K1038, ""))} -> 100 | P4: Active | Q4: FALSE | R4: Roaming stage intercom | S4: Julian Clarkson | T4: 46280 | U4: 46280
Q5: FALSE

Sheet Asset Assignments
A1: RECORD ID | B1: ORGANIZATION | C1: PROJECT ID | D1: DEPARTMENT | E1: CATEGORY | F1: SUB CATEGORY | G1: ASSET ID | H1: PERSONNEL ID | I1: ALL CALL | J1: STATUS | K1: FLAG | L1: NOTES | M1: CREATED BY | N1: CREATED AT | O1: UPDATED AT

Sheet Personnel Roster
A1: PERSONNEL ID | B1: ORGANIZATION | C1: PROJECT ID | D1: FIRST NAME | E1: LAST NAME | F1: PREFERRED NAME | G1: EMAIL | H1: PHONE | I1: COMPANY | J1: ROLE CODE | K1: POSITION | L1: DEPARTMENT | M1: CATEGORY | N1: SUB CATEGORY | O1: CLEARANCE TIER | P1: ZONE ACCESS | Q1: CREDENTIAL | R1: CREDENTIAL RECORD ID | S1: ON SITE START | T1: ON SITE END | U1: DIETARY RESTRICTIONS | V1: SHIRT SIZE | W1: SPECIAL ACCOMMODATIONS | X1: EMERGENCY CONTACT NAME | Y1: EMERGENCY CONTACT PHONE | Z1: STATUS | AA1: FLAG | AB1: NOTES | AC1: CREATED BY | AD1: CREATED AT | AE1: UPDATED AT
A2: P-001 | B2: GHXSTSHIP | C2: CSMIA26 | D2: Ashley | E2: Sumner | F2: Ashley | G2: ashley@tigresoundsystem.com | H2: (305) 555-0101 | I2: Tigre Studio | J2: 0000.50.01 | K2: =VLOOKUP(J2, 'Roles Library'!$A$2:$B$36, 2, FALSE) -> Chief Executive Officer | L2: 0000 Executive | M2: 0.5 | N2: Governance and Client Relations | O2: Tier 1 - Executive Master | P2: All Zones | Q2: All Access | R2: CRD-001 | S2: 46266 | T2: 46387 | U2: None | V2: M | W2: None | X2: Tigre Emergency | Y2: (305) 555-0199 | Z2: Active | AA2: FALSE | AB2: Commercial owner | AC2: Julian Clarkson | AD2: 46280 | AE2: 46280
A3: P-005 | B3: GHXSTSHIP | C3: CSMIA26 | D3: Isabella | E3: Acker | F3: Izzy | G3: isabella@spotify.com | H3: (305) 555-0105 | I3: Spotify | J3: 1000.50.01 | K3: =VLOOKUP(J3, 'Roles Library'!$A$2:$B$36, 2, FALSE) -> Creative Director | L3: 1000 Creative | M3: 1000.5 | N3: Programming and Creative Direction | O3: Tier 1 - Executive Master | P3: All Zones | Q3: All Access | R3: CRD-002 | S3: 46266 | T3: 46387 | U3: Vegetarian | V3: S | W3: None | X3: Spotify Emergency | Y3: (305) 555-0195 | Z3: Active | AA3: FALSE | AB3: Creative and talent lead | AC3: Julian Clarkson | AD3: 46280 | AE3: 46280
A4: P-016 | B4: GHXSTSHIP | C4: CSMIA26 | D4: Mary | E4: Christianson | F4: Mary | G4: mary@tigresoundsystem.com | H4: (305) 555-0116 | I4: Tigre Studio | J4: 6000.50.01 | K4: =VLOOKUP(J4, 'Roles Library'!$A$2:$B$36, 2, FALSE) -> House Manager | L4: 6000 Operations | M4: 6000.5 | N4: House Management | O4: Tier 1 - Executive Master | P4: All Zones | Q4: All Access | R4: CRD-003 | S4: 46321 | T4: 46387 | U4: None | V4: M | W4: None | X4: Emergency Contact | Y4: (305) 555-0188 | Z4: Active | AA4: FALSE | AB4: House operations lead | AC4: Julian Clarkson | AD4: 46280 | AE4: 46280
A5: P-021 | B5: GHXSTSHIP | C5: CSMIA26 | D5: Julian | E5: Clarkson | F5: Julian | G5: julian.clarkson@ghxstship.pro | H5: (305) 555-0121 | I5: Tigre Studio | J5: 5000.50.01 | K5: =VLOOKUP(J5, 'Roles Library'!$A$2:$B$36, 2, FALSE) -> Production & Operations Director | L5: 5000 Production | M5: 5000.5 | N5: Production Leadership | O5: Tier 1 - Executive Master | P5: All Zones | Q5: All Access | R5: CRD-004 | S5: 46266 | T5: 46387 | U5: None | V5: L | W5: None | X5: GHXSTSHIP HQ | Y5: (305) 555-0100 | Z5: Active | AA5: FALSE | AB5: Senior production lead | AC5: Julian Clarkson | AD5: 46280 | AE5: 46280
A6: P-024 | B6: GHXSTSHIP | C6: CSMIA26 | D6: David | E6: Miller | F6: Dave | G6: dave@unreal-systems.com | H6: (305) 555-0124 | I6: Unreal-Systems | J6: 9000.50.02 | K6: =VLOOKUP(J6, 'Roles Library'!$A$2:$B$36, 2, FALSE) -> Audio Engineer - A1/FOH | L6: 5000 Production | M6: 9000.5 | N6: Audio Systems | O6: Tier 2 - Technical Lead | P6: Stage & FOH | Q6: Production | R6: CRD-005 | S6: 46342 | T6: 46387 | U6: None | V6: XL | W6: None | X6: Unreal HQ | Y6: (305) 555-0155 | Z6: Active | AA6: FALSE | AB6: FOH audio engineer | AC6: Julian Clarkson | AD6: 46280 | AE6: 46280
A7: P-006 | B7: GHXSTSHIP | C7: CSMIA26 | D7: Rebecca | E7: Bex | F7: Bex | G7: bex@tigresoundsystem.com | H7: (305) 555-0106 | I7: Tigre Studio | J7: 1000.50.02 | K7: =VLOOKUP(J7, 'Roles Library'!$A$2:$B$36, 2, FALSE) -> Event & Programming Director | L7: 1000 Creative | M7: 1000.5 | N7: Programming and Creative Direction | O7: Tier 1 - Executive Master | P7: All Zones | Q7: All Access | R7: CRD-006 | S7: 46235 | T7: 46387 | U7: None | V7: M | W7: None | X7: Tigre Emergency | Y7: (305) 555-0199 | Z7: Active | AA7: FALSE | AB7: Creative and programming lead | AC7: Julian Clarkson | AD7: 46280 | AE7: 46280

Sheet Staffing Requisition
A1: REQ ID | B1: EVENT PHASE | C1: ROLE CODE | D1: RATE CARD ID | E1: JOB TITLE | F1: HEADCOUNT | G1: DURATION (DAYS) | H1: STANDARD RATE | I1: TOTAL ESTIMATED COST | J1: STATUS | K1: FLAG | L1: NOTES | M1: CREATED BY | N1: CREATED AT | O1: UPDATED AT
A2: REQ-001 | B2: Pre-Production | C2: 0000.50.01 | D2: {=_xlfn.XLOOKUP(C2, 'Labor Rate Cards'!$B$2:$B$36, 'Labor Rate Cards'!$A$2:$A$36)} -> LRC-001 | E2: {=_xlfn.XLOOKUP(C2, 'Roles Library'!$A$2:$A$36, 'Roles Library'!$B$2:$B$36)} -> Chief Executive Officer | F2: 1 | G2: 30 | H2: {=_xlfn.XLOOKUP(D2, 'Labor Rate Cards'!$A$2:$A$36, 'Labor Rate Cards'!$F$2:$F$36)} -> 1800 | I2: =F2*G2*H2 -> 54000 | J2: Approved | K2: FALSE | M2: Julian Clarkson | N2: 46296 | O2: 46296
A3: REQ-002 | B3: Creative Conception | C3: 1000.50.01 | D3: {=_xlfn.XLOOKUP(C3, 'Labor Rate Cards'!$B$2:$B$36, 'Labor Rate Cards'!$A$2:$A$36)} -> LRC-002 | E3: {=_xlfn.XLOOKUP(C3, 'Roles Library'!$A$2:$A$36, 'Roles Library'!$B$2:$B$36)} -> Creative Director | F3: 1 | G3: 25 | H3: {=_xlfn.XLOOKUP(D3, 'Labor Rate Cards'!$A$2:$A$36, 'Labor Rate Cards'!$F$2:$F$36)} -> 1250 | I3: =F3*G3*H3 -> 31250 | J3: Approved | K3: FALSE | M3: Julian Clarkson | N3: 46296 | O3: 46296
A4: REQ-003 | B4: Site Build & Load-In | C4: 5000.50.01 | D4: {=_xlfn.XLOOKUP(C4, 'Labor Rate Cards'!$B$2:$B$36, 'Labor Rate Cards'!$A$2:$A$36)} -> LRC-004 | E4: {=_xlfn.XLOOKUP(C4, 'Roles Library'!$A$2:$A$36, 'Roles Library'!$B$2:$B$36)} -> Production & Operations Director | F4: 1 | G4: 20 | H4: {=_xlfn.XLOOKUP(D4, 'Labor Rate Cards'!$A$2:$A$36, 'Labor Rate Cards'!$F$2:$F$36)} -> 1350 | I4: =F4*G4*H4 -> 27000 | J4: Approved | K4: FALSE | M4: Julian Clarkson | N4: 46296 | O4: 46296
A5: REQ-004 | B5: Site Power Install | C5: 5000.50.02 | D5: {=_xlfn.XLOOKUP(C5, 'Labor Rate Cards'!$B$2:$B$36, 'Labor Rate Cards'!$A$2:$A$36)} -> LRC-005 | E5: {=_xlfn.XLOOKUP(C5, 'Roles Library'!$A$2:$A$36, 'Roles Library'!$B$2:$B$36)} -> Master Electrician / Power Lead | F5: 2 | G5: 12 | H5: {=_xlfn.XLOOKUP(D5, 'Labor Rate Cards'!$A$2:$A$36, 'Labor Rate Cards'!$F$2:$F$36)} -> 850 | I5: =F5*G5*H5 -> 20400 | J5: Approved | K5: FALSE | M5: Julian Clarkson | N5: 46296 | O5: 46296
A6: REQ-005 | B6: Venue Operations | C6: 6000.50.01 | D6: {=_xlfn.XLOOKUP(C6, 'Labor Rate Cards'!$B$2:$B$36, 'Labor Rate Cards'!$A$2:$A$36)} -> LRC-006 | E6: {=_xlfn.XLOOKUP(C6, 'Roles Library'!$A$2:$A$36, 'Roles Library'!$B$2:$B$36)} -> House Manager | F6: 1 | G6: 10 | H6: {=_xlfn.XLOOKUP(D6, 'Labor Rate Cards'!$A$2:$A$36, 'Labor Rate Cards'!$F$2:$F$36)} -> 750 | I6: =F6*G6*H6 -> 7500 | J6: Approved | K6: FALSE | M6: Julian Clarkson | N6: 46296 | O6: 46296
A7: REQ-006 | B7: Security Grid Deployment | C7: 6000.50.02 | D7: {=_xlfn.XLOOKUP(C7, 'Labor Rate Cards'!$B$2:$B$36, 'Labor Rate Cards'!$A$2:$A$36)} -> LRC-007 | E7: {=_xlfn.XLOOKUP(C7, 'Roles Library'!$A$2:$A$36, 'Roles Library'!$B$2:$B$36)} -> Site Safety & Security Lead | F7: 2 | G7: 8 | H7: {=_xlfn.XLOOKUP(D7, 'Labor Rate Cards'!$A$2:$A$36, 'Labor Rate Cards'!$F$2:$F$36)} -> 700 | I7: =F7*G7*H7 -> 11200 | J7: Approved | K7: FALSE | M7: Julian Clarkson | N7: 46296 | O7: 46296
A8: REQ-007 | B8: Stage Deck Execution | C8: 9000.50.01 | D8: {=_xlfn.XLOOKUP(C8, 'Labor Rate Cards'!$B$2:$B$36, 'Labor Rate Cards'!$A$2:$A$36)} -> LRC-008 | E8: {=_xlfn.XLOOKUP(C8, 'Roles Library'!$A$2:$A$36, 'Roles Library'!$B$2:$B$36)} -> Production Stage Manager | F8: 1 | G8: 6 | H8: {=_xlfn.XLOOKUP(D8, 'Labor Rate Cards'!$A$2:$A$36, 'Labor Rate Cards'!$F$2:$F$36)} -> 950 | I8: =F8*G8*H8 -> 5700 | J8: Approved | K8: FALSE | M8: Julian Clarkson | N8: 46296 | O8: 46296
A9: REQ-008 | B9: FOH Sound Tuning & Show | C9: 9000.50.02 | D9: {=_xlfn.XLOOKUP(C9, 'Labor Rate Cards'!$B$2:$B$36, 'Labor Rate Cards'!$A$2:$A$36)} -> LRC-009 | E9: {=_xlfn.XLOOKUP(C9, 'Roles Library'!$A$2:$A$36, 'Roles Library'!$B$2:$B$36)} -> Audio Engineer - A1/FOH | F9: 2 | G9: 6 | H9: {=_xlfn.XLOOKUP(D9, 'Labor Rate Cards'!$A$2:$A$36, 'Labor Rate Cards'!$F$2:$F$36)} -> 850 | I9: =F9*G9*H9 -> 10200 | J9: Approved | K9: FALSE | M9: Julian Clarkson | N9: 46296 | O9: 46296
A10: REQ-009 | B10: Lighting Rig & Show Cues | C10: 9000.50.03 | D10: {=_xlfn.XLOOKUP(C10, 'Labor Rate Cards'!$B$2:$B$36, 'Labor Rate Cards'!$A$2:$A$36)} -> LRC-010 | E10: {=_xlfn.XLOOKUP(C10, 'Roles Library'!$A$2:$A$36, 'Roles Library'!$B$2:$B$36)} -> Lighting Designer / LD | F10: 2 | G10: 6 | H10: {=_xlfn.XLOOKUP(D10, 'Labor Rate Cards'!$A$2:$A$36, 'Labor Rate Cards'!$F$2:$F$36)} -> 800 | I10: =F10*G10*H10 -> 9600 | J10: Approved | K10: FALSE | M10: Julian Clarkson | N10: 46296 | O10: 46296

Sheet Crew Shifts
A1: SHIFT ID | B1: PROJECT ID | C1: SHIFT DATE | D1: DEPARTMENT | E1: LOCATION NAME | F1: PERSONNEL ID | G1: CREW NAME | H1: ROLE CODE | I1: RATE CARD ID | J1: JOB TITLE | K1: SCHEDULED CALL TIME | L1: SCHEDULED WRAP TIME | M1: SCHEDULED MEAL BREAK (HRS) | N1: NET SCHEDULED HOURS | O1: PAY BASIS | P1: STANDARD RATE | Q1: HOURLY BASE RATE | R1: SCHEDULED PAY | S1: STATUS | T1: FLAG | U1: NOTES | V1: CREATED BY | W1: CREATED AT | X1: UPDATED AT
A2: SHF-001 | B2: CSMIA26 | C2: 46346 | D2: 5000 Production | E2: Main Stage & Bar | F2: P-021 | G2: {=TRIM(_xlfn.XLOOKUP(F2, 'Personnel Roster'!$A$2:$A100, 'Personnel Roster'!$D$2:$D100, "") & " " & _xlfn.XLOOKUP(F2, 'Personnel Roster'!$A$2:$A100, 'Personnel Roster'!$E$2:$E100, ""))} -> Julian Clarkson | H2: 5000.50.01 | I2: LRC-004 | J2: {=IFERROR(_xlfn.XLOOKUP(I2, 'Labor Rate Cards'!$A$2:$A$36, 'Labor Rate Cards'!$C$2:$C$36), "")} -> Production & Operations Director | K2: 0.33333333 | L2: 0.79166667 | M2: 1 | N2: =ROUND((L2-K2)*24 - M2, 2) -> 10 | O2: {=IFERROR(_xlfn.XLOOKUP(I2, 'Labor Rate Cards'!$A$2:$A$36, 'Labor Rate Cards'!$E$2:$E$36), "Day Rate")} -> Day Rate | P2: {=IFERROR(_xlfn.XLOOKUP(I2, 'Labor Rate Cards'!$A$2:$A$36, 'Labor Rate Cards'!$F$2:$F$36), 0)} -> 1350 | Q2: =ROUND(P2/10, 2) -> 135 | R2: =IF(O2="Day Rate", P2, ROUND(Q2*N2, 2)) -> 1350 | S2: Confirmed | T2: FALSE | V2: Julian Clarkson | W2: 46296 | X2: 46296
A3: SHF-002 | B3: CSMIA26 | C3: 46346 | D3: 5000 Production | E3: Main Stage & Bar | F3: P-024 | G3: {=TRIM(_xlfn.XLOOKUP(F3, 'Personnel Roster'!$A$2:$A100, 'Personnel Roster'!$D$2:$D100, "") & " " & _xlfn.XLOOKUP(F3, 'Personnel Roster'!$A$2:$A100, 'Personnel Roster'!$E$2:$E100, ""))} -> David Miller | H3: 9000.50.02 | I3: LRC-009 | J3: {=IFERROR(_xlfn.XLOOKUP(I3, 'Labor Rate Cards'!$A$2:$A$36, 'Labor Rate Cards'!$C$2:$C$36), "")} -> Audio Engineer - A1/FOH | K3: 0.33333333 | L3: 0.79166667 | M3: 1 | N3: =ROUND((L3-K3)*24 - M3, 2) -> 10 | O3: {=IFERROR(_xlfn.XLOOKUP(I3, 'Labor Rate Cards'!$A$2:$A$36, 'Labor Rate Cards'!$E$2:$E$36), "Day Rate")} -> Day Rate | P3: {=IFERROR(_xlfn.XLOOKUP(I3, 'Labor Rate Cards'!$A$2:$A$36, 'Labor Rate Cards'!$F$2:$F$36), 0)} -> 850 | Q3: =ROUND(P3/10, 2) -> 85 | R3: =IF(O3="Day Rate", P3, ROUND(Q3*N3, 2)) -> 850 | S3: Confirmed | T3: FALSE | V3: Julian Clarkson | W3: 46296 | X3: 46296
A4: SHF-003 | B4: CSMIA26 | C4: 46346 | D4: 6000 Operations | E4: All Zones | F4: P-016 | G4: {=TRIM(_xlfn.XLOOKUP(F4, 'Personnel Roster'!$A$2:$A100, 'Personnel Roster'!$D$2:$D100, "") & " " & _xlfn.XLOOKUP(F4, 'Personnel Roster'!$A$2:$A100, 'Personnel Roster'!$E$2:$E100, ""))} -> Mary Christianson | H4: 6000.50.01 | I4: LRC-006 | J4: {=IFERROR(_xlfn.XLOOKUP(I4, 'Labor Rate Cards'!$A$2:$A$36, 'Labor Rate Cards'!$C$2:$C$36), "")} -> House Manager | K4: 0.375 | L4: 0.79166667 | M4: 1 | N4: =ROUND((L4-K4)*24 - M4, 2) -> 9 | O4: {=IFERROR(_xlfn.XLOOKUP(I4, 'Labor Rate Cards'!$A$2:$A$36, 'Labor Rate Cards'!$E$2:$E$36), "Day Rate")} -> Day Rate | P4: {=IFERROR(_xlfn.XLOOKUP(I4, 'Labor Rate Cards'!$A$2:$A$36, 'Labor Rate Cards'!$F$2:$F$36), 0)} -> 750 | Q4: =ROUND(P4/10, 2) -> 75 | R4: =IF(O4="Day Rate", P4, ROUND(Q4*N4, 2)) -> 750 | S4: Confirmed | T4: FALSE | V4: Julian Clarkson | W4: 46296 | X4: 46296
A5: SHF-004 | B5: CSMIA26 | C5: 46346 | D5: 1000 Creative | E5: All Zones | F5: P-005 | G5: {=TRIM(_xlfn.XLOOKUP(F5, 'Personnel Roster'!$A$2:$A100, 'Personnel Roster'!$D$2:$D100, "") & " " & _xlfn.XLOOKUP(F5, 'Personnel Roster'!$A$2:$A100, 'Personnel Roster'!$E$2:$E100, ""))} -> Isabella Acker | H5: 1000.50.01 | I5: LRC-002 | J5: {=IFERROR(_xlfn.XLOOKUP(I5, 'Labor Rate Cards'!$A$2:$A$36, 'Labor Rate Cards'!$C$2:$C$36), "")} -> Creative Director | K5: 0.375 | L5: 0.79166667 | M5: 1 | N5: =ROUND((L5-K5)*24 - M5, 2) -> 9 | O5: {=IFERROR(_xlfn.XLOOKUP(I5, 'Labor Rate Cards'!$A$2:$A$36, 'Labor Rate Cards'!$E$2:$E$36), "Day Rate")} -> Day Rate | P5: {=IFERROR(_xlfn.XLOOKUP(I5, 'Labor Rate Cards'!$A$2:$A$36, 'Labor Rate Cards'!$F$2:$F$36), 0)} -> 1250 | Q5: =ROUND(P5/10, 2) -> 125 | R5: =IF(O5="Day Rate", P5, ROUND(Q5*N5, 2)) -> 1250 | S5: Confirmed | T5: FALSE | V5: Julian Clarkson | W5: 46296 | X5: 46296
A6: SHF-005 | B6: CSMIA26 | C6: 46346 | D6: 1000 Creative | E6: All Zones | F6: P-006 | G6: {=TRIM(_xlfn.XLOOKUP(F6, 'Personnel Roster'!$A$2:$A100, 'Personnel Roster'!$D$2:$D100, "") & " " & _xlfn.XLOOKUP(F6, 'Personnel Roster'!$A$2:$A100, 'Personnel Roster'!$E$2:$E100, ""))} -> Rebecca Bex | H6: 1000.50.02 | I6: LRC-003 | J6: {=IFERROR(_xlfn.XLOOKUP(I6, 'Labor Rate Cards'!$A$2:$A$36, 'Labor Rate Cards'!$C$2:$C$36), "")} -> Event & Programming Director | K6: 0.375 | L6: 0.79166667 | M6: 1 | N6: =ROUND((L6-K6)*24 - M6, 2) -> 9 | O6: {=IFERROR(_xlfn.XLOOKUP(I6, 'Labor Rate Cards'!$A$2:$A$36, 'Labor Rate Cards'!$E$2:$E$36), "Day Rate")} -> Day Rate | P6: {=IFERROR(_xlfn.XLOOKUP(I6, 'Labor Rate Cards'!$A$2:$A$36, 'Labor Rate Cards'!$F$2:$F$36), 0)} -> 1100 | Q6: =ROUND(P6/10, 2) -> 110 | R6: =IF(O6="Day Rate", P6, ROUND(Q6*N6, 2)) -> 1100 | S6: Confirmed | T6: FALSE | V6: Julian Clarkson | W6: 46296 | X6: 46296
A7: SHF-006 | B7: CSMIA26 | C7: 46346 | D7: 0000 Executive | E7: All Zones | F7: P-001 | G7: {=TRIM(_xlfn.XLOOKUP(F7, 'Personnel Roster'!$A$2:$A100, 'Personnel Roster'!$D$2:$D100, "") & " " & _xlfn.XLOOKUP(F7, 'Personnel Roster'!$A$2:$A100, 'Personnel Roster'!$E$2:$E100, ""))} -> Ashley Sumner | H7: 0000.50.01 | I7: LRC-001 | J7: {=IFERROR(_xlfn.XLOOKUP(I7, 'Labor Rate Cards'!$A$2:$A$36, 'Labor Rate Cards'!$C$2:$C$36), "")} -> Chief Executive Officer | K7: 0.41666667 | L7: 0.75 | M7: 1 | N7: =ROUND((L7-K7)*24 - M7, 2) -> 7 | O7: {=IFERROR(_xlfn.XLOOKUP(I7, 'Labor Rate Cards'!$A$2:$A$36, 'Labor Rate Cards'!$E$2:$E$36), "Day Rate")} -> Day Rate | P7: {=IFERROR(_xlfn.XLOOKUP(I7, 'Labor Rate Cards'!$A$2:$A$36, 'Labor Rate Cards'!$F$2:$F$36), 0)} -> 1800 | Q7: =ROUND(P7/10, 2) -> 180 | R7: =IF(O7="Day Rate", P7, ROUND(Q7*N7, 2)) -> 1800 | S7: Confirmed | T7: FALSE | V7: Julian Clarkson | W7: 46296 | X7: 46296
A8: SHF-007 | B8: CSMIA26 | C8: 46347 | D8: 5000 Production | E8: Main Stage & Bar | F8: P-021 | G8: {=TRIM(_xlfn.XLOOKUP(F8, 'Personnel Roster'!$A$2:$A100, 'Personnel Roster'!$D$2:$D100, "") & " " & _xlfn.XLOOKUP(F8, 'Personnel Roster'!$A$2:$A100, 'Personnel Roster'!$E$2:$E100, ""))} -> Julian Clarkson | H8: 5000.50.01 | I8: LRC-004 | J8: {=IFERROR(_xlfn.XLOOKUP(I8, 'Labor Rate Cards'!$A$2:$A$36, 'Labor Rate Cards'!$C$2:$C$36), "")} -> Production & Operations Director | K8: 0.33333333 | L8: 0.83333333 | M8: 1 | N8: =ROUND((L8-K8)*24 - M8, 2) -> 11 | O8: {=IFERROR(_xlfn.XLOOKUP(I8, 'Labor Rate Cards'!$A$2:$A$36, 'Labor Rate Cards'!$E$2:$E$36), "Day Rate")} -> Day Rate | P8: {=IFERROR(_xlfn.XLOOKUP(I8, 'Labor Rate Cards'!$A$2:$A$36, 'Labor Rate Cards'!$F$2:$F$36), 0)} -> 1350 | Q8: =ROUND(P8/10, 2) -> 135 | R8: =IF(O8="Day Rate", P8, ROUND(Q8*N8, 2)) -> 1350 | S8: Confirmed | T8: FALSE | V8: Julian Clarkson | W8: 46296 | X8: 46296
A9: SHF-008 | B9: CSMIA26 | C9: 46347 | D9: 5000 Production | E9: Main Stage & Bar | F9: P-024 | G9: {=TRIM(_xlfn.XLOOKUP(F9, 'Personnel Roster'!$A$2:$A100, 'Personnel Roster'!$D$2:$D100, "") & " " & _xlfn.XLOOKUP(F9, 'Personnel Roster'!$A$2:$A100, 'Personnel Roster'!$E$2:$E100, ""))} -> David Miller | H9: 9000.50.02 | I9: LRC-009 | J9: {=IFERROR(_xlfn.XLOOKUP(I9, 'Labor Rate Cards'!$A$2:$A$36, 'Labor Rate Cards'!$C$2:$C$36), "")} -> Audio Engineer - A1/FOH | K9: 0.33333333 | L9: 0.83333333 | M9: 1 | N9: =ROUND((L9-K9)*24 - M9, 2) -> 11 | O9: {=IFERROR(_xlfn.XLOOKUP(I9, 'Labor Rate Cards'!$A$2:$A$36, 'Labor Rate Cards'!$E$2:$E$36), "Day Rate")} -> Day Rate | P9: {=IFERROR(_xlfn.XLOOKUP(I9, 'Labor Rate Cards'!$A$2:$A$36, 'Labor Rate Cards'!$F$2:$F$36), 0)} -> 850 | Q9: =ROUND(P9/10, 2) -> 85 | R9: =IF(O9="Day Rate", P9, ROUND(Q9*N9, 2)) -> 850 | S9: Confirmed | T9: FALSE | V9: Julian Clarkson | W9: 46296 | X9: 46296

Sheet Crew Timesheets
A1: TIMESHEET ID | B1: PROJECT ID | C1: SHIFT ID | D1: WORK DATE | E1: PERSONNEL ID | F1: CREW NAME | G1: ROLE CODE | H1: RATE CARD ID | I1: JOB TITLE | J1: ACTUAL IN TIME | K1: MEAL OUT TIME | L1: MEAL IN TIME | M1: ACTUAL OUT TIME | N1: MEAL DURATION (HRS) | O1: TOTAL ELAPSED HOURS | P1: NET WORKED HOURS | Q1: REGULAR HOURS (1.0x) | R1: OVERTIME HOURS (1.5x) | S1: DOUBLE TIME HOURS (2.0x) | T1: HOURLY BASE RATE | U1: REGULAR PAY | V1: OVERTIME PAY | W1: DOUBLE TIME PAY | X1: MEAL PENALTY PAY | Y1: PER DIEM PAY | Z1: GROSS EARNINGS | AA1: EXPENSE GL ACCOUNT | AB1: EXPENSE GL NAME | AC1: STATUS | AD1: FLAG | AE1: NOTES | AF1: CREATED BY | AG1: CREATED AT | AH1: UPDATED AT
A2: TS-001 | B2: CSMIA26 | C2: SHF-001 | D2: ='Crew Shifts'!C2 -> 46346 | E2: ='Crew Shifts'!F2 -> P-021 | F2: {=TRIM(_xlfn.XLOOKUP(E2, 'Personnel Roster'!$A$2:$A100, 'Personnel Roster'!$D$2:$D100, "") & " " & _xlfn.XLOOKUP(E2, 'Personnel Roster'!$A$2:$A100, 'Personnel Roster'!$E$2:$E100, ""))} -> Julian Clarkson | G2: ='Crew Shifts'!H2 -> 5000.50.01 | H2: ='Crew Shifts'!I2 -> LRC-004 | I2: ='Crew Shifts'!J2 -> Production & Operations Director | J2: 0.32291667 | K2: 0.54166667 | L2: 0.58333333 | M2: 0.80208333 | N2: =ROUND((L2-K2)*24, 2) -> 1 | O2: =ROUND((M2-J2)*24, 2) -> 11.5 | P2: =ROUND(O2-N2, 2) -> 10.5 | Q2: =ROUND(MIN(8, P2), 2) -> 8 | R2: =ROUND(MAX(0, MIN(4, P2-8)), 2) -> 2.5 | S2: =ROUND(MAX(0, P2-12), 2) -> 0 | T2: ='Crew Shifts'!Q2 -> 135 | U2: =ROUND(Q2*T2, 2) -> 1080 | V2: =ROUND(R2*T2*1.5, 2) -> 506.25 | W2: =ROUND(S2*T2*2, 2) -> 0 | X2: =IF((K2-J2)*24 > 6, 50, 0) -> 0 | Y2: =IFERROR(VLOOKUP(H2, 'Labor Rate Cards'!$A$2:$K$36, 11, FALSE), 0) -> 75 | Z2: =ROUND(U2+V2+W2+X2+Y2, 2) -> 1661.25 | AA2: =IFERROR(VLOOKUP(H2, 'Labor Rate Cards'!$A$2:$L$36, 12, FALSE), "") -> 5500 | AB2: =IFERROR(VLOOKUP(H2, 'Labor Rate Cards'!$A$2:$M$36, 13, FALSE), "") -> Expense · Production | AC2: Approved | AD2: FALSE | AF2: Julian Clarkson | AG2: 46346 | AH2: 46346
A3: TS-002 | B3: CSMIA26 | C3: SHF-002 | D3: ='Crew Shifts'!C3 -> 46346 | E3: ='Crew Shifts'!F3 -> P-024 | F3: {=TRIM(_xlfn.XLOOKUP(E3, 'Personnel Roster'!$A$2:$A100, 'Personnel Roster'!$D$2:$D100, "") & " " & _xlfn.XLOOKUP(E3, 'Personnel Roster'!$A$2:$A100, 'Personnel Roster'!$E$2:$E100, ""))} -> David Miller | G3: ='Crew Shifts'!H3 -> 9000.50.02 | H3: ='Crew Shifts'!I3 -> LRC-009 | I3: ='Crew Shifts'!J3 -> Audio Engineer - A1/FOH | J3: 0.33333333 | K3: 0.60416667 | L3: 0.64583333 | M3: 0.875 | N3: =ROUND((L3-K3)*24, 2) -> 1 | O3: =ROUND((M3-J3)*24, 2) -> 13 | P3: =ROUND(O3-N3, 2) -> 12 | Q3: =ROUND(MIN(8, P3), 2) -> 8 | R3: =ROUND(MAX(0, MIN(4, P3-8)), 2) -> 4 | S3: =ROUND(MAX(0, P3-12), 2) -> 0 | T3: ='Crew Shifts'!Q3 -> 85 | U3: =ROUND(Q3*T3, 2) -> 680 | V3: =ROUND(R3*T3*1.5, 2) -> 510 | W3: =ROUND(S3*T3*2, 2) -> 0 | X3: =IF((K3-J3)*24 > 6, 50, 0) -> 50 | Y3: =IFERROR(VLOOKUP(H3, 'Labor Rate Cards'!$A$2:$K$36, 11, FALSE), 0) -> 75 | Z3: =ROUND(U3+V3+W3+X3+Y3, 2) -> 1315 | AA3: =IFERROR(VLOOKUP(H3, 'Labor Rate Cards'!$A$2:$L$36, 12, FALSE), "") -> 5500 | AB3: =IFERROR(VLOOKUP(H3, 'Labor Rate Cards'!$A$2:$M$36, 13, FALSE), "") -> Expense · Production | AC3: Approved | AD3: FALSE | AF3: Julian Clarkson | AG3: 46346 | AH3: 46346
A4: TS-003 | B4: CSMIA26 | C4: SHF-003 | D4: ='Crew Shifts'!C4 -> 46346 | E4: ='Crew Shifts'!F4 -> P-016 | F4: {=TRIM(_xlfn.XLOOKUP(E4, 'Personnel Roster'!$A$2:$A100, 'Personnel Roster'!$D$2:$D100, "") & " " & _xlfn.XLOOKUP(E4, 'Personnel Roster'!$A$2:$A100, 'Personnel Roster'!$E$2:$E100, ""))} -> Mary Christianson | G4: ='Crew Shifts'!H4 -> 6000.50.01 | H4: ='Crew Shifts'!I4 -> LRC-006 | I4: ='Crew Shifts'!J4 -> House Manager | J4: 0.36458333 | K4: 0.5625 | L4: 0.60416667 | M4: 0.78125 | N4: =ROUND((L4-K4)*24, 2) -> 1 | O4: =ROUND((M4-J4)*24, 2) -> 10 | P4: =ROUND(O4-N4, 2) -> 9 | Q4: =ROUND(MIN(8, P4), 2) -> 8 | R4: =ROUND(MAX(0, MIN(4, P4-8)), 2) -> 1 | S4: =ROUND(MAX(0, P4-12), 2) -> 0 | T4: ='Crew Shifts'!Q4 -> 75 | U4: =ROUND(Q4*T4, 2) -> 600 | V4: =ROUND(R4*T4*1.5, 2) -> 112.5 | W4: =ROUND(S4*T4*2, 2) -> 0 | X4: =IF((K4-J4)*24 > 6, 50, 0) -> 0 | Y4: =IFERROR(VLOOKUP(H4, 'Labor Rate Cards'!$A$2:$K$36, 11, FALSE), 0) -> 75 | Z4: =ROUND(U4+V4+W4+X4+Y4, 2) -> 787.5 | AA4: =IFERROR(VLOOKUP(H4, 'Labor Rate Cards'!$A$2:$L$36, 12, FALSE), "") -> 5600 | AB4: =IFERROR(VLOOKUP(H4, 'Labor Rate Cards'!$A$2:$M$36, 13, FALSE), "") -> Expense · Operations | AC4: Approved | AD4: FALSE | AF4: Julian Clarkson | AG4: 46346 | AH4: 46346
A5: TS-004 | B5: CSMIA26 | C5: SHF-004 | D5: ='Crew Shifts'!C5 -> 46346 | E5: ='Crew Shifts'!F5 -> P-005 | F5: {=TRIM(_xlfn.XLOOKUP(E5, 'Personnel Roster'!$A$2:$A100, 'Personnel Roster'!$D$2:$D100, "") & " " & _xlfn.XLOOKUP(E5, 'Personnel Roster'!$A$2:$A100, 'Personnel Roster'!$E$2:$E100, ""))} -> Isabella Acker | G5: ='Crew Shifts'!H5 -> 1000.50.01 | H5: ='Crew Shifts'!I5 -> LRC-002 | I5: ='Crew Shifts'!J5 -> Creative Director | J5: 0.375 | K5: 0.58333333 | L5: 0.625 | M5: 0.79166667 | N5: =ROUND((L5-K5)*24, 2) -> 1 | O5: =ROUND((M5-J5)*24, 2) -> 10 | P5: =ROUND(O5-N5, 2) -> 9 | Q5: =ROUND(MIN(8, P5), 2) -> 8 | R5: =ROUND(MAX(0, MIN(4, P5-8)), 2) -> 1 | S5: =ROUND(MAX(0, P5-12), 2) -> 0 | T5: ='Crew Shifts'!Q5 -> 125 | U5: =ROUND(Q5*T5, 2) -> 1000 | V5: =ROUND(R5*T5*1.5, 2) -> 187.5 | W5: =ROUND(S5*T5*2, 2) -> 0 | X5: =IF((K5-J5)*24 > 6, 50, 0) -> 0 | Y5: =IFERROR(VLOOKUP(H5, 'Labor Rate Cards'!$A$2:$K$36, 11, FALSE), 0) -> 75 | Z5: =ROUND(U5+V5+W5+X5+Y5, 2) -> 1262.5 | AA5: =IFERROR(VLOOKUP(H5, 'Labor Rate Cards'!$A$2:$L$36, 12, FALSE), "") -> 5100 | AB5: =IFERROR(VLOOKUP(H5, 'Labor Rate Cards'!$A$2:$M$36, 13, FALSE), "") -> Expense · Creative | AC5: Approved | AD5: FALSE | AF5: Julian Clarkson | AG5: 46346 | AH5: 46346
A6: TS-005 | B6: CSMIA26 | C6: SHF-005 | D6: ='Crew Shifts'!C6 -> 46346 | E6: ='Crew Shifts'!F6 -> P-006 | F6: {=TRIM(_xlfn.XLOOKUP(E6, 'Personnel Roster'!$A$2:$A100, 'Personnel Roster'!$D$2:$D100, "") & " " & _xlfn.XLOOKUP(E6, 'Personnel Roster'!$A$2:$A100, 'Personnel Roster'!$E$2:$E100, ""))} -> Rebecca Bex | G6: ='Crew Shifts'!H6 -> 1000.50.02 | H6: ='Crew Shifts'!I6 -> LRC-003 | I6: ='Crew Shifts'!J6 -> Event & Programming Director | J6: 0.375 | K6: 0.57291667 | L6: 0.61458333 | M6: 0.8125 | N6: =ROUND((L6-K6)*24, 2) -> 1 | O6: =ROUND((M6-J6)*24, 2) -> 10.5 | P6: =ROUND(O6-N6, 2) -> 9.5 | Q6: =ROUND(MIN(8, P6), 2) -> 8 | R6: =ROUND(MAX(0, MIN(4, P6-8)), 2) -> 1.5 | S6: =ROUND(MAX(0, P6-12), 2) -> 0 | T6: ='Crew Shifts'!Q6 -> 110 | U6: =ROUND(Q6*T6, 2) -> 880 | V6: =ROUND(R6*T6*1.5, 2) -> 247.5 | W6: =ROUND(S6*T6*2, 2) -> 0 | X6: =IF((K6-J6)*24 > 6, 50, 0) -> 0 | Y6: =IFERROR(VLOOKUP(H6, 'Labor Rate Cards'!$A$2:$K$36, 11, FALSE), 0) -> 75 | Z6: =ROUND(U6+V6+W6+X6+Y6, 2) -> 1202.5 | AA6: =IFERROR(VLOOKUP(H6, 'Labor Rate Cards'!$A$2:$L$36, 12, FALSE), "") -> 5100 | AB6: =IFERROR(VLOOKUP(H6, 'Labor Rate Cards'!$A$2:$M$36, 13, FALSE), "") -> Expense · Creative | AC6: Approved | AD6: FALSE | AF6: Julian Clarkson | AG6: 46346 | AH6: 46346
A7: TS-006 | B7: CSMIA26 | C7: SHF-006 | D7: ='Crew Shifts'!C7 -> 46346 | E7: ='Crew Shifts'!F7 -> P-001 | F7: {=TRIM(_xlfn.XLOOKUP(E7, 'Personnel Roster'!$A$2:$A100, 'Personnel Roster'!$D$2:$D100, "") & " " & _xlfn.XLOOKUP(E7, 'Personnel Roster'!$A$2:$A100, 'Personnel Roster'!$E$2:$E100, ""))} -> Ashley Sumner | G7: ='Crew Shifts'!H7 -> 0000.50.01 | H7: ='Crew Shifts'!I7 -> LRC-001 | I7: ='Crew Shifts'!J7 -> Chief Executive Officer | J7: 0.41666667 | K7: 0.58333333 | L7: 0.625 | M7: 0.75 | N7: =ROUND((L7-K7)*24, 2) -> 1 | O7: =ROUND((M7-J7)*24, 2) -> 8 | P7: =ROUND(O7-N7, 2) -> 7 | Q7: =ROUND(MIN(8, P7), 2) -> 7 | R7: =ROUND(MAX(0, MIN(4, P7-8)), 2) -> 0 | S7: =ROUND(MAX(0, P7-12), 2) -> 0 | T7: ='Crew Shifts'!Q7 -> 180 | U7: =ROUND(Q7*T7, 2) -> 1260 | V7: =ROUND(R7*T7*1.5, 2) -> 0 | W7: =ROUND(S7*T7*2, 2) -> 0 | X7: =IF((K7-J7)*24 > 6, 50, 0) -> 0 | Y7: =IFERROR(VLOOKUP(H7, 'Labor Rate Cards'!$A$2:$K$36, 11, FALSE), 0) -> 75 | Z7: =ROUND(U7+V7+W7+X7+Y7, 2) -> 1335 | AA7: =IFERROR(VLOOKUP(H7, 'Labor Rate Cards'!$A$2:$L$36, 12, FALSE), "") -> 5000 | AB7: =IFERROR(VLOOKUP(H7, 'Labor Rate Cards'!$A$2:$M$36, 13, FALSE), "") -> Expense · Executive | AC7: Approved | AD7: FALSE | AF7: Julian Clarkson | AG7: 46346 | AH7: 46346
A8: TS-007 | B8: CSMIA26 | C8: SHF-007 | D8: ='Crew Shifts'!C8 -> 46347 | E8: ='Crew Shifts'!F8 -> P-021 | F8: {=TRIM(_xlfn.XLOOKUP(E8, 'Personnel Roster'!$A$2:$A100, 'Personnel Roster'!$D$2:$D100, "") & " " & _xlfn.XLOOKUP(E8, 'Personnel Roster'!$A$2:$A100, 'Personnel Roster'!$E$2:$E100, ""))} -> Julian Clarkson | G8: ='Crew Shifts'!H8 -> 5000.50.01 | H8: ='Crew Shifts'!I8 -> LRC-004 | I8: ='Crew Shifts'!J8 -> Production & Operations Director | J8: 0.3125 | K8: 0.58333333 | L8: 0.625 | M8: 0.9375 | N8: =ROUND((L8-K8)*24, 2) -> 1 | O8: =ROUND((M8-J8)*24, 2) -> 15 | P8: =ROUND(O8-N8, 2) -> 14 | Q8: =ROUND(MIN(8, P8), 2) -> 8 | R8: =ROUND(MAX(0, MIN(4, P8-8)), 2) -> 4 | S8: =ROUND(MAX(0, P8-12), 2) -> 2 | T8: ='Crew Shifts'!Q8 -> 135 | U8: =ROUND(Q8*T8, 2) -> 1080 | V8: =ROUND(R8*T8*1.5, 2) -> 810 | W8: =ROUND(S8*T8*2, 2) -> 540 | X8: =IF((K8-J8)*24 > 6, 50, 0) -> 50 | Y8: =IFERROR(VLOOKUP(H8, 'Labor Rate Cards'!$A$2:$K$36, 11, FALSE), 0) -> 75 | Z8: =ROUND(U8+V8+W8+X8+Y8, 2) -> 2555 | AA8: =IFERROR(VLOOKUP(H8, 'Labor Rate Cards'!$A$2:$L$36, 12, FALSE), "") -> 5500 | AB8: =IFERROR(VLOOKUP(H8, 'Labor Rate Cards'!$A$2:$M$36, 13, FALSE), "") -> Expense · Production | AC8: Approved | AD8: FALSE | AF8: Julian Clarkson | AG8: 46347 | AH8: 46347
A9: TS-008 | B9: CSMIA26 | C9: SHF-008 | D9: ='Crew Shifts'!C9 -> 46347 | E9: ='Crew Shifts'!F9 -> P-024 | F9: {=TRIM(_xlfn.XLOOKUP(E9, 'Personnel Roster'!$A$2:$A100, 'Personnel Roster'!$D$2:$D100, "") & " " & _xlfn.XLOOKUP(E9, 'Personnel Roster'!$A$2:$A100, 'Personnel Roster'!$E$2:$E100, ""))} -> David Miller | G9: ='Crew Shifts'!H9 -> 9000.50.02 | H9: ='Crew Shifts'!I9 -> LRC-009 | I9: ='Crew Shifts'!J9 -> Audio Engineer - A1/FOH | J9: 0.3125 | K9: 0.54166667 | L9: 0.58333333 | M9: 0.91666667 | N9: =ROUND((L9-K9)*24, 2) -> 1 | O9: =ROUND((M9-J9)*24, 2) -> 14.5 | P9: =ROUND(O9-N9, 2) -> 13.5 | Q9: =ROUND(MIN(8, P9), 2) -> 8 | R9: =ROUND(MAX(0, MIN(4, P9-8)), 2) -> 4 | S9: =ROUND(MAX(0, P9-12), 2) -> 1.5 | T9: ='Crew Shifts'!Q9 -> 85 | U9: =ROUND(Q9*T9, 2) -> 680 | V9: =ROUND(R9*T9*1.5, 2) -> 510 | W9: =ROUND(S9*T9*2, 2) -> 255 | X9: =IF((K9-J9)*24 > 6, 50, 0) -> 0 | Y9: =IFERROR(VLOOKUP(H9, 'Labor Rate Cards'!$A$2:$K$36, 11, FALSE), 0) -> 75 | Z9: =ROUND(U9+V9+W9+X9+Y9, 2) -> 1520 | AA9: =IFERROR(VLOOKUP(H9, 'Labor Rate Cards'!$A$2:$L$36, 12, FALSE), "") -> 5500 | AB9: =IFERROR(VLOOKUP(H9, 'Labor Rate Cards'!$A$2:$M$36, 13, FALSE), "") -> Expense · Production | AC9: Approved | AD9: FALSE | AF9: Julian Clarkson | AG9: 46347 | AH9: 46347

Sheet Labor Rate Cards
A1: RATE CARD ID | B1: ROLE CODE | C1: JOB TITLE | D1: ENGAGEMENT TYPE | E1: PAY BASIS | F1: STANDARD RATE | G1: MIN GRADE RATE | H1: MAX GRADE RATE | I1: OT MULTIPLIER | J1: DT MULTIPLIER | K1: PER DIEM RATE | L1: DEFAULT GL ACCOUNT | M1: DEFAULT GL NAME | N1: STATUS | O1: FLAG | P1: NOTES | Q1: CREATED BY | R1: CREATED AT | S1: UPDATED AT
A2: LRC-001 | B2: 0000.50.01 | C2: {=_xlfn.XLOOKUP(B2, 'Roles Library'!$A$2:$A$12, 'Roles Library'!$B$2:$B$12)} -> Chief Executive Officer | D2: Retainer | E2: Day Rate | F2: 1800 | G2: 1500 | H2: 2200 | I2: 1 | J2: 1 | K2: 75 | L2: 5000 | M2: =IFERROR(__xludf.DUMMYFUNCTION("XLOOKUP(TO_TEXT(L2), 'GL Accounts'!$A$2:$A$24, 'GL Accounts'!$B$2:$B$24)"),"Expense · Executive") -> Expense · Executive | N2: Active | O2: FALSE | P2: Canonical Executive Lead | Q2: Julian Clarkson | R2: 46280 | S2: 46280
A3: LRC-002 | B3: 1000.50.01 | C3: {=_xlfn.XLOOKUP(B3, 'Roles Library'!$A$2:$A$12, 'Roles Library'!$B$2:$B$12)} -> Creative Director | D3: Contractor 1099 | E3: Day Rate | F3: 1250 | G3: 1000 | H3: 1500 | I3: 1.5 | J3: 2 | K3: 75 | L3: 5100 | M3: =IFERROR(__xludf.DUMMYFUNCTION("XLOOKUP(TO_TEXT(L3), 'GL Accounts'!$A$2:$A$24, 'GL Accounts'!$B$2:$B$24)"),"Expense · Creative") -> Expense · Creative | N3: Active | O3: FALSE | P3: Canonical Creative Lead | Q3: Julian Clarkson | R3: 46280 | S3: 46280
A4: LRC-003 | B4: 1000.50.02 | C4: {=_xlfn.XLOOKUP(B4, 'Roles Library'!$A$2:$A$12, 'Roles Library'!$B$2:$B$12)} -> Event & Programming Director | D4: Contractor 1099 | E4: Day Rate | F4: 1100 | G4: 900 | H4: 1350 | I4: 1.5 | J4: 2 | K4: 75 | L4: 5100 | M4: =IFERROR(__xludf.DUMMYFUNCTION("XLOOKUP(TO_TEXT(L4), 'GL Accounts'!$A$2:$A$24, 'GL Accounts'!$B$2:$B$24)"),"Expense · Creative") -> Expense · Creative | N4: Active | O4: FALSE | P4: Canonical Programming Lead | Q4: Julian Clarkson | R4: 46280 | S4: 46280
A5: LRC-004 | B5: 5000.50.01 | C5: {=_xlfn.XLOOKUP(B5, 'Roles Library'!$A$2:$A$12, 'Roles Library'!$B$2:$B$12)} -> Production & Operations Director | D5: Retainer | E5: Day Rate | F5: 1350 | G5: 1100 | H5: 1600 | I5: 1.5 | J5: 2 | K5: 75 | L5: 5500 | M5: =IFERROR(__xludf.DUMMYFUNCTION("XLOOKUP(TO_TEXT(L5), 'GL Accounts'!$A$2:$A$24, 'GL Accounts'!$B$2:$B$24)"),"Expense · Production") -> Expense · Production | N5: Active | O5: FALSE | P5: Canonical Senior Production Lead | Q5: Julian Clarkson | R5: 46280 | S5: 46280
A6: LRC-005 | B6: 5000.50.02 | C6: {=_xlfn.XLOOKUP(B6, 'Roles Library'!$A$2:$A$12, 'Roles Library'!$B$2:$B$12)} -> Master Electrician / Power Lead | D6: W2 Daily | E6: Day Rate | F6: 850 | G6: 700 | H6: 1000 | I6: 1.5 | J6: 2 | K6: 75 | L6: 5500 | M6: =IFERROR(__xludf.DUMMYFUNCTION("XLOOKUP(TO_TEXT(L6), 'GL Accounts'!$A$2:$A$24, 'GL Accounts'!$B$2:$B$24)"),"Expense · Production") -> Expense · Production | N6: Active | O6: FALSE | P6: Master Power Systems Lead | Q6: Julian Clarkson | R6: 46280 | S6: 46280
A7: LRC-006 | B7: 6000.50.01 | C7: {=_xlfn.XLOOKUP(B7, 'Roles Library'!$A$2:$A$12, 'Roles Library'!$B$2:$B$12)} -> House Manager | D7: Contractor 1099 | E7: Day Rate | F7: 750 | G7: 600 | H7: 900 | I7: 1.5 | J7: 2 | K7: 75 | L7: 5600 | M7: =IFERROR(__xludf.DUMMYFUNCTION("XLOOKUP(TO_TEXT(L7), 'GL Accounts'!$A$2:$A$24, 'GL Accounts'!$B$2:$B$24)"),"Expense · Operations") -> Expense · Operations | N7: Active | O7: FALSE | P7: Canonical House Ops Lead | Q7: Julian Clarkson | R7: 46280 | S7: 46280
A8: LRC-007 | B8: 6000.50.02 | C8: {=_xlfn.XLOOKUP(B8, 'Roles Library'!$A$2:$A$12, 'Roles Library'!$B$2:$B$12)} -> Site Safety & Security Lead | D8: Contractor 1099 | E8: Day Rate | F8: 700 | G8: 550 | H8: 850 | I8: 1.5 | J8: 2 | K8: 75 | L8: 5600 | M8: =IFERROR(__xludf.DUMMYFUNCTION("XLOOKUP(TO_TEXT(L8), 'GL Accounts'!$A$2:$A$24, 'GL Accounts'!$B$2:$B$24)"),"Expense · Operations") -> Expense · Operations | N8: Active | O8: FALSE | P8: Perimeter & Incident Security | Q8: Julian Clarkson | R8: 46280 | S8: 46280
A9: LRC-008 | B9: 9000.50.01 | C9: {=_xlfn.XLOOKUP(B9, 'Roles Library'!$A$2:$A$12, 'Roles Library'!$B$2:$B$12)} -> Production Stage Manager | D9: W2 Daily | E9: Day Rate | F9: 950 | G9: 800 | H9: 1150 | I9: 1.5 | J9: 2 | K9: 75 | L9: 5500 | M9: =IFERROR(__xludf.DUMMYFUNCTION("XLOOKUP(TO_TEXT(L9), 'GL Accounts'!$A$2:$A$24, 'GL Accounts'!$B$2:$B$24)"),"Expense · Production") -> Expense · Production | N9: Active | O9: FALSE | P9: Lead Deck Stage Manager | Q9: Julian Clarkson | R9: 46280 | S9: 46280
A10: LRC-009 | B10: 9000.50.02 | C10: {=_xlfn.XLOOKUP(B10, 'Roles Library'!$A$2:$A$12, 'Roles Library'!$B$2:$B$12)} -> Audio Engineer - A1/FOH | D10: Vendor Master | E10: Day Rate | F10: 850 | G10: 700 | H10: 1000 | I10: 1.5 | J10: 2 | K10: 75 | L10: 5500 | M10: =IFERROR(__xludf.DUMMYFUNCTION("XLOOKUP(TO_TEXT(L10), 'GL Accounts'!$A$2:$A$24, 'GL Accounts'!$B$2:$B$24)"),"Expense · Production") -> Expense · Production | N10: Active | O10: FALSE | P10: Lead Audio Engineer FOH | Q10: Julian Clarkson | R10: 46280 | S10: 46280
A11: LRC-010 | B11: 9000.50.03 | C11: {=_xlfn.XLOOKUP(B11, 'Roles Library'!$A$2:$A$12, 'Roles Library'!$B$2:$B$12)} -> Lighting Designer / LD | D11: Contractor 1099 | E11: Day Rate | F11: 800 | G11: 650 | H11: 950 | I11: 1.5 | J11: 2 | K11: 75 | L11: 5500 | M11: =IFERROR(__xludf.DUMMYFUNCTION("XLOOKUP(TO_TEXT(L11), 'GL Accounts'!$A$2:$A$24, 'GL Accounts'!$B$2:$B$24)"),"Expense · Production") -> Expense · Production | N11: Active | O11: FALSE | P11: Lead Lighting Programmer | Q11: Julian Clarkson | R11: 46280 | S11: 46280
A12: LRC-011 | B12: 9000.50.04 | C12: {=_xlfn.XLOOKUP(B12, 'Roles Library'!$A$2:$A$12, 'Roles Library'!$B$2:$B$12)} -> Video Director / V1 | D12: Contractor 1099 | E12: Day Rate | F12: 800 | G12: 650 | H12: 950 | I12: 1.5 | J12: 2 | K12: 75 | L12: 5500 | M12: =IFERROR(__xludf.DUMMYFUNCTION("XLOOKUP(TO_TEXT(L12), 'GL Accounts'!$A$2:$A$24, 'GL Accounts'!$B$2:$B$24)"),"Expense · Production") -> Expense · Production | N12: Active | O12: FALSE | P12: Lead Video & Media Engineer | Q12: Julian Clarkson | R12: 46280 | S12: 46280
A13: LRC-012 | B13: 0000.51.01 | C13: Production Finance Director | D13: Contractor 1099 | E13: Day Rate | F13: 1200 | G13: 1000 | H13: 1450 | I13: 1.0x | J13: 1.0x | K13: 75 | L13: 5000 | M13: Expense · Executive | N13: Active | O13: FALSE | P13: Fiscal Governance Lead | Q13: Julian Clarkson | R13: 46280 | S13: 46280
A14: LRC-013 | B14: 1000.51.01 | C14: Scenic Art Director | D14: Contractor 1099 | E14: Day Rate | F14: 900 | G14: 750 | H14: 1100 | I14: 1.5x | J14: 2.0x | K14: 75 | L14: 5100 | M14: Expense · Creative | N14: Active | O14: FALSE | P14: Scenic & Environment Lead | Q14: Julian Clarkson | R14: 46280 | S14: 46280
A15: LRC-014 | B15: 2000.50.01 | C15: Backline Tech / Instrument Specialist | D15: W2 Daily | E15: Day Rate | F15: 650 | G15: 550 | H15: 800 | I15: 1.5x | J15: 2.0x | K15: 75 | L15: 5200 | M15: Expense · Talent | N15: Active | O15: FALSE | P15: Stage Backline Lead | Q15: Julian Clarkson | R15: 46280 | S15: 46280
A16: LRC-015 | B16: 2000.50.02 | C16: Artist Relations Coordinator | D16: Contractor 1099 | E16: Day Rate | F16: 550 | G16: 450 | H16: 700 | I16: 1.5x | J16: 2.0x | K16: 75 | L16: 5200 | M16: Expense · Talent | N16: Active | O16: FALSE | P16: Backstage Artist Care Lead | Q16: Julian Clarkson | R16: 46280 | S16: 46280
A17: LRC-016 | B17: 3000.50.01 | C17: Principal Event Photographer | D17: Contractor 1099 | E17: Day Rate | F17: 800 | G17: 650 | H17: 1000 | I17: 1.5x | J17: 2.0x | K17: 75 | L17: 5300 | M17: Expense · Marketing | N17: Active | O17: FALSE | P17: Lead Stills Photographer | Q17: Julian Clarkson | R17: 46280 | S17: 46280
A18: LRC-017 | B18: 3000.50.02 | C18: Lead Cinematographer / Video Shooter | D18: Contractor 1099 | E18: Day Rate | F18: 900 | G18: 750 | H18: 1150 | I18: 1.5x | J18: 2.0x | K18: 75 | L18: 5300 | M18: Expense · Marketing | N18: Active | O18: FALSE | P18: Lead Live Video Capture | Q18: Julian Clarkson | R18: 46280 | S18: 46280
A19: LRC-018 | B19: 3000.50.03 | C19: Real-Time Social Content Producer | D19: Contractor 1099 | E19: Day Rate | F19: 600 | G19: 500 | H19: 750 | I19: 1.5x | J19: 2.0x | K19: 75 | L19: 5300 | M19: Expense · Marketing | N19: Active | O19: FALSE | P19: Live Social Channel Producer | Q19: Julian Clarkson | R19: 46280 | S19: 46280
A20: LRC-019 | B20: 4000.50.01 | C20: Structural Carpenter / Build Lead | D20: W2 Daily | E20: Day Rate | F20: 700 | G20: 600 | H20: 850 | I20: 1.5x | J20: 2.0x | K20: 75 | L20: 5400 | M20: Expense · Environment | N20: Active | O20: FALSE | P20: Master Scenic Build Lead | Q20: Julian Clarkson | R20: 46280 | S20: 46280
A21: LRC-020 | B21: 4000.51.01 | C21: HVAC & Site Climate Tech | D21: Vendor Master | E21: Day Rate | F21: 650 | G21: 550 | H21: 800 | I21: 1.5x | J21: 2.0x | K21: 75 | L21: 5400 | M21: Expense · Environment | N21: Active | O21: FALSE | P21: Site Environmental Climate Tech | Q21: Julian Clarkson | R21: 46280 | S21: 46280
A22: LRC-021 | B22: 5000.50.03 | C22: Production Coordinator | D22: Contractor 1099 | E22: Day Rate | F22: 600 | G22: 500 | H22: 750 | I22: 1.5x | J22: 2.0x | K22: 75 | L22: 5500 | M22: Expense · Production | N22: Active | O22: FALSE | P22: Central Production Office Coordinator | Q22: Julian Clarkson | R22: 46280 | S22: 46280
A23: LRC-022 | B23: 5000.51.01 | C23: Lead Stagehand / Deck Crew Chief | D23: W2 Daily | E23: Day Rate | F23: 550 | G23: 450 | H23: 700 | I23: 1.5x | J23: 2.0x | K23: 75 | L23: 5500 | M23: Expense · Production | N23: Active | O23: FALSE | P23: Lead Stage Deck Crew Chief | Q23: Julian Clarkson | R23: 46280 | S23: 46280
A24: LRC-023 | B24: 5000.51.02 | C24: Head Arena / Festival Rigger | D24: Contractor 1099 | E24: Day Rate | F24: 950 | G24: 800 | H24: 1150 | I24: 1.5x | J24: 2.0x | K24: 75 | L24: 5500 | M24: Expense · Production | N24: Active | O24: FALSE | P24: Head Overhead Rigging Specialist | Q24: Julian Clarkson | R24: 46280 | S24: 46280
... A36: LRC-035 | B36: 9000.52.01 | C36: Lead Network & Comms Engineer | D36: Vendor Master | E36: Day Rate | F36: 850 | G36: 700 | H36: 1050 | I36: 1.5x | J36: 2.0x | K36: 75 | L36: 5900 | M36: Expense · Technology | N36: Active | O36: FALSE | P36: Core IT Network & RF Systems Lead | Q36: Julian Clarkson | R36: 46280 | S36: 46280

Sheet Roles Library
A1: ROLE CODE | B1: JOB TITLE | C1: DEPARTMENT | D1: DISCIPLINE | E1: RANK | F1: JOB SUMMARY | G1: KEY RESPONSIBILITIES | H1: QUALIFICATIONS | I1: PHYSICAL REQUIREMENTS | J1: REQUIRED CERTIFICATIONS | K1: DEFAULT CLEARANCE TIER | L1: DEFAULT RADIO CHANNEL | M1: STATUS | N1: FLAG | O1: NOTES | P1: CREATED BY | Q1: CREATED AT | R1: UPDATED AT
A2: 0000.50.01 | B2: Chief Executive Officer | C2: 0000 Executive | D2: Governance & Client Relations | E2: Executive | F2: Overall executive leadership, commercial governance, and client stakeholder management. | G2: Direct executive strategy; authorize major expenditures; represent production to partners. | H2: 10+ years executive leadership in large-scale live productions. | I2: Standard office & site walkthroughs. | J2: Executive Leadership Certification | K2: Tier 1 - Executive Master | L2: Channel 1 (Emergency) | M2: Active | N2: FALSE | O2: Canonical Executive Lead | P2: Julian Clarkson | Q2: 46280 | R2: 46280
A3: 1000.50.01 | B3: Creative Director | C3: 1000 Creative | D3: Programming & Creative Direction | E3: Director | F3: Visionary oversight for artistic programming, scenic design, and guest creative experience. | G3: Lead creative concepts, guide scenic aesthetics, curate artist programming cadence. | H3: 8+ years creative direction in experiential entertainment. | I3: Standard site walks across creative zones. | J3: Creative Arts Degree or equivalent experience | K3: Tier 1 - Executive Master | L3: Channel 3 (Site Ops) | M3: Active | N3: FALSE | O3: Canonical Creative Lead | P3: Julian Clarkson | Q3: 46280 | R3: 46280
A4: 1000.50.02 | B4: Event & Programming Director | C4: 1000 Creative | D4: Programming & Creative Direction | E4: Director | F4: Curates talent lineup, schedules performance blocks, and coordinates talent logistics. | G4: Manage talent booking, run-of-show synchronization, artist relations alignment. | H4: 7+ years music industry and festival talent management. | I4: Prolonged site presence during show run. | J4: Talent Logistics & Artist Relations Certification | K4: Tier 1 - Executive Master | L4: Channel 3 (Site Ops) | M4: Active | N4: FALSE | O4: Canonical Programming Lead | P4: Julian Clarkson | Q4: 46280 | R4: 46280
A5: 5000.50.01 | B5: Production & Operations Director | C5: 5000 Production | D5: Production Leadership | E5: Director | F5: Senior technical director overseeing stage, site ops, logistics, and vendor integration. | G5: Oversee multi-stage build, enforce master production schedule, direct site leads. | H5: 10+ years festival technical direction and venue buildout. | I5: Able to walk active construction grounds 10+ hrs/day. | J5: OSHA 30, Rigging Inspection Certified | K5: Tier 1 - Executive Master | L5: Channel 3 (Site Ops) | M5: Active | N5: FALSE | O5: Canonical Senior Production Lead | P5: Julian Clarkson | Q5: 46280 | R5: 46280
A6: 5000.50.02 | B6: Master Electrician / Power Lead | C6: 5000 Production | D6: Power & Utilities | E6: Lead Technician | F6: Directs site power distribution, generator synchronization, and technical power safety. | G6: Calculate load schedules, manage temporary generator banks, balance distribution panels. | H6: 6+ years temporary power distribution for live events. | I6: Able to lift 50 lbs, climb ladders, and work outdoors. | J6: Licensed Master Electrician, NFPA 70E | K6: Tier 2 - Technical Lead | L6: Channel 5 (Power & IT) | M6: Active | N6: FALSE | O6: Master Power Systems Lead | P6: Julian Clarkson | Q6: 46280 | R6: 46280
A7: 6000.50.01 | B7: House Manager | C7: 6000 Operations | D7: House Management | E7: Manager | F7: Manages front of house operations, guest circulation, hospitality, and crowd services. | G7: Supervise ushering, coordinate box office and access control, oversee ingress/egress. | H7: 5+ years venue operations and public assembly management. | I7: Continuous walking and standing during operating hours. | J7: Crowd Management Certification, First Aid / CPR | K7: Tier 1 - Executive Master | L7: Channel 4 (Exterior Ops) | M7: Active | N7: FALSE | O7: Canonical House Ops Lead | P7: Julian Clarkson | Q7: 46280 | R7: 46280
A8: 6000.50.02 | B8: Site Safety & Security Lead | C8: 6000 Operations | D8: Safety & Security | E8: Lead | F8: Leads perimeter integrity, crowd safety protocols, emergency egress, and liaison with AHJ. | G8: Direct private security deployment, coordinate with local fire/police, enforce security grid. | H8: 7+ years event security management and law enforcement coordination. | I8: High mobility across perimeter and venue grounds. | J8: OSHA 30, Crowd Control Specialist, CPR/AED | K8: Tier 2 - Technical Lead | L8: Channel 2 (Security) | M8: Active | N8: FALSE | O8: Perimeter & Incident Security | P8: Julian Clarkson | Q8: 46280 | R8: 46280
A9: 9000.50.01 | B9: Production Stage Manager | C9: 5000 Production | D9: Stage Operations | E9: Manager | F9: Executes live run-of-show cues, stage deck turnover, and backline technical transitions. | G9: Call stage cues, coordinate artist deck arrivals, enforce show schedule timing. | H9: 6+ years calling major festival stages or theatrical productions. | I9: Standing and moving backstage during full event duration. | J9: Stage Management Association / OSHA 10 | K9: Tier 2 - Technical Lead | L9: Channel 7 (Stage Ops) | M9: Active | N9: FALSE | O9: Lead Deck Stage Manager | P9: Julian Clarkson | Q9: 46280 | R9: 46280
A10: 9000.50.02 | B10: Audio Engineer - A1/FOH | C10: 5000 Production | D10: Audio Systems | E10: Lead Technician | F10: Front-of-house engineer in charge of acoustic tuning, console mixing, and PA safety. | G10: Mix FOH sound, optimize line array dispersion, oversee Dante audio networking. | H10: 7+ years live concert audio engineering and system design. | I10: Prolonged standing at mixing console, lifting 40 lbs. | J10: Dante Level 3, SMAART Certification | K10: Tier 2 - Technical Lead | L10: Channel 8 (Audio) | M10: Active | N10: FALSE | O10: Lead Audio Engineer FOH | P10: Julian Clarkson | Q10: 46280 | R10: 46280
A11: 9000.50.03 | B11: Lighting Designer / LD | C11: 5000 Production | D11: Lighting Systems | E11: Lead Technician | F11: Programs dynamic visual show cues, operates GrandMA console, and supervises lighting rig. | G11: Program show files, oversee fixture focus and truss hanging, execute show lighting. | H11: 5+ years moving light programming and concert lighting design. | I11: Prolonged console operation, comfortable with heights. | J11: GrandMA3 Programmer Certified, ETCP Preferred | K11: Tier 2 - Technical Lead | L11: Channel 9 (Lighting) | M11: Active | N11: FALSE | O11: Lead Lighting Programmer | P11: Julian Clarkson | Q11: 46280 | R11: 46280
A12: 9000.50.04 | B12: Video Director / V1 | C12: 5000 Production | D12: Video Systems | E12: Lead Technician | F12: Supervises LED wall processors, live video switching, media server playback, and camera feeds. | G12: Manage video switching, synchronize media servers, calibrate LED panels. | H12: 5+ years live video playback and LED video wall engineering. | I12: Sedentary video control position with rapid deck response. | J12: Barco Certified, Disguise D3 Workflow Certified | K12: Tier 2 - Technical Lead | L12: Channel 7 (Stage Ops) | M12: Active | N12: FALSE | O12: Lead Video & Media Engineer | P12: Julian Clarkson | Q12: 46280 | R12: 46280
A13: 0000.51.01 | B13: Production Finance Director | C13: 0000 Executive | D13: Commercial and Finance | E13: Director | F13: Directs overall event fiscal governance, purchase commitments, payroll, and financial closeout. | G13: Manage event pro forma, authorize vendor purchase orders, reconcile master production budget. | H13: 8+ years live event production finance and commercial management. | I13: Standard office & production trailer environment. | J13: CPA or Master in Finance Preferred | K13: Tier 1 - Executive Master | L13: Channel 1 (Emergency) | M13: Active | N13: FALSE | O13: Fiscal Governance Lead | P13: Julian Clarkson | Q13: 46280 | R13: 46280
... A36: 9000.52.01 | B36: Lead Network & Comms Engineer | C36: 9000 Technology | D36: Venue IT | E36: Lead Technician | F36: Deploys event core routers, managed switches, fiber optic trunks, high-density guest WiFi, and RF radios. | G36: Configure VLAN segmentation, manage wireless access points, coordinate radio frequencies. | H36: 6+ years temporary live event IT network infrastructure and RF coordination. | I36: Able to lift 50 lbs, climb ladders, pull fiber runs through cable ramps. | J36: Cisco CCNA / Network+, Shure RF Coordinator Certified | K36: Tier 2 - Technical Lead | L36: Channel 5 (Power & IT) | M36: Active | N36: FALSE | O36: Core IT Network & RF Systems Lead | P36: Julian Clarkson | Q36: 46280 | R36: 46280

Sheet Credential Issuance
A1: RECORD ID | B1: ORGANIZATION | C1: PROJECT ID | D1: DEPARTMENT | E1: CATEGORY | F1: SUB CATEGORY | G1: CREDENTIAL SERIAL | H1: PERSONNEL ID | I1: VENDOR ID | J1: CLEARANCE TIER | K1: CREDENTIAL TYPE | L1: ZONE ACCESS | M1: ISSUED DATE | N1: RETURN STATUS | O1: STATUS | P1: FLAG | Q1: NOTES | R1: CREATED BY | S1: CREATED AT | T1: UPDATED AT
A2: CRD-001 | B2: ='Cover Page'!$I$8 -> GHXSTSHIP | C2: ='Cover Page'!$C$7 -> CSMIA26 | D2: 0000 Executive | E2: 0.5 | F2: Credentials | G2: SER-001 | H2: P-001 | I2: VEN-016 | J2: Tier 1 - Executive Master | K2: All Access | L2: All Zones | M2: 46266 | N2: Issued | O2: Active | P2: FALSE | Q2: Master executive badge | R2: Julian Clarkson | S2: 46280 | T2: 46280
A3: CRD-002 | B3: ='Cover Page'!$I$8 -> GHXSTSHIP | C3: ='Cover Page'!$C$7 -> CSMIA26 | D3: 1000 Creative | E3: 1000.5 | F3: Credentials | G3: SER-002 | H3: P-005 | I3: VEN-017 | J3: Tier 1 - Executive Master | K3: All Access | L3: All Zones | M3: 46266 | N3: Issued | O3: Active | P3: FALSE | Q3: Creative director badge | R3: Julian Clarkson | S3: 46280 | T3: 46280
A4: CRD-003 | B4: ='Cover Page'!$I$8 -> GHXSTSHIP | C4: ='Cover Page'!$C$7 -> CSMIA26 | D4: 6000 Operations | E4: 6000.5 | F4: Credentials | G4: SER-003 | H4: P-016 | I4: VEN-016 | J4: Tier 1 - Executive Master | K4: All Access | L4: All Zones | M4: 46266 | N4: Issued | O4: Active | P4: FALSE | Q4: House manager badge | R4: Julian Clarkson | S4: 46280 | T4: 46280
A5: CRD-004 | B5: ='Cover Page'!$I$8 -> GHXSTSHIP | C5: ='Cover Page'!$C$7 -> CSMIA26 | D5: 5000 Production | E5: 5000.5 | F5: Credentials | G5: SER-004 | H5: P-021 | I5: VEN-016 | J5: Tier 1 - Executive Master | K5: All Access | L5: All Zones | M5: 46266 | N5: Issued | O5: Active | P5: FALSE | Q5: Production director badge | R5: Julian Clarkson | S5: 46280 | T5: 46280
A6: CRD-005 | B6: ='Cover Page'!$I$8 -> GHXSTSHIP | C6: ='Cover Page'!$C$7 -> CSMIA26 | D6: 5000 Production | E6: 5000.5 | F6: Credentials | G6: SER-005 | H6: P-024 | I6: VEN-015 | J6: Tier 2 - Technical Lead | K6: Production | L6: Stage & FOH | M6: 46296 | N6: Issued | O6: Active | P6: FALSE | Q6: FOH audio engineer badge | R6: Julian Clarkson | S6: 46280 | T6: 46280
A7: CRD-006 | B7: ='Cover Page'!$I$8 -> GHXSTSHIP | C7: ='Cover Page'!$C$7 -> CSMIA26 | D7: 1000 Creative | E7: 1000.5 | F7: Credentials | G7: SER-006 | H7: P-006 | I7: VEN-016 | J7: Tier 1 - Executive Master | K7: All Access | L7: All Zones | M7: 46235 | N7: Issued | O7: Active | P7: FALSE | Q7: Event & programming director badge | R7: Julian Clarkson | S7: 46280 | T7: 46280

Sheet Access Grid
A1: RECORD ID | B1: ORGANIZATION | C1: PROJECT ID | D1: DEPARTMENT | E1: CATEGORY | F1: SUB CATEGORY | G1: CREDENTIAL | H1: ACCESS POINT | I1: ACCESS LEVEL | J1: CAPACITY | K1: STATUS | L1: FLAG | M1: NOTES | N1: CREATED BY | O1: CREATED AT | P1: UPDATED AT

Sheet Budget Expenses
A1: RECORD ID | B1: PROJECT ID | C1: EVENT | D1: LOCATION | E1: ZONE | F1: SPACE | G1: ACTIVATION | H1: DEPARTMENT | I1: DISCIPLINE | J1: CATEGORY | K1: SUB CATEGORY | L1: ITEM | M1: DESCRIPTION | N1: URID | O1: PHASE | P1: TIER | Q1: XYZ | R1: LINE TYPE | S1: QUANTITY | T1: RATE | U1: UNIT BASIS | V1: ESTIMATE | W1: BUDGET | X1: COMMITTED | Y1: FORECAST | Z1: ACTUAL | AA1: VARIANCE | AB1: VENDOR | AC1: STATUS | AD1: FLAG | AE1: EXTERNAL NOTES | AF1: INTERNAL NOTES | AG1: ACCOUNT CODE | AH1: ACCOUNT NAME | AI1: COST CENTER | AJ1: URID DIMENSION | AK1: TAX TYPE | AL1: CURRENCY | AM1: CREATED BY | AN1: CREATED AT | AO1: UPDATED AT
A2: BUD-0001 | B2: CSMIA26 | C2: Event 00 · Venue Startup | D2: The Sanctuary MiMo | H2: 0000 Executive | I2: 0000.01 Executive Leadership & Strategy | J2: Production Leadership | K2: N/A | N2: 0000.01.01 | O2: Advance | P2: 04 Physical | Q2: X | R2: Scope | T2: =SUMIFS('PO Line Items'!$H:$H, 'PO Line Items'!$C:$C, $A2) + SUMIFS('Change Orders'!$M:$M, 'Change Orders'!$E:$E, $A2, 'Change Orders'!$W:$W, "Approved") -> 0 | V2: =IF(OR(S2="",T2=""),"",ROUND(S2*T2,2)) | W2: =IF(V2="","",V2) | X2: =SUMIFS('PO Line Items'!$H:$H, 'PO Line Items'!$C:$C, $A2) + SUMIFS('Change Orders'!$M:$M, 'Change Orders'!$E:$E, $A2, 'Change Orders'!$W:$W, "Approved") -> 0 | Y2: =IF(AND(W2="",X2=""),"",MAX(N(W2),N(X2))) -> 0 | AA2: =W2-Z2 -> 0 | AC2: Open | AD2: FALSE | AG2: 5000 | AH2: {=_xlfn.XLOOKUP(AG2, 'GL Accounts'!$A$2:$A271, 'GL Accounts'!$B$2:$B271, "")} -> Expense · Executive | AI2: CC-CORP | AJ2: 0000.01.01 | AK2: Tax on Purchases | AL2: USD | AM2: Julian Clarkson | AN2: 2026-09-30 13:05:00 | AO2: 2026-09-30 13:05:00
A3: BUD-0002 | B3: CSMIA26 | C3: Event 00 · Venue Startup | D3: The Sanctuary MiMo | H3: 0000 Executive | I3: 0000.02 Finance & Accounting | J3: Production Accounting | K3: N/A | N3: 0000.02.01 | O3: Advance | P3: 04 Physical | Q3: X | R3: Scope | T3: =SUMIFS('PO Line Items'!$H:$H, 'PO Line Items'!$C:$C, $A3) + SUMIFS('Change Orders'!$M:$M, 'Change Orders'!$E:$E, $A3, 'Change Orders'!$W:$W, "Approved") -> 0 | V3: =IF(OR(S3="",T3=""),"",ROUND(S3*T3,2)) | W3: =IF(V3="","",V3) | X3: =SUMIFS('PO Line Items'!$H:$H, 'PO Line Items'!$C:$C, $A3) + SUMIFS('Change Orders'!$M:$M, 'Change Orders'!$E:$E, $A3, 'Change Orders'!$W:$W, "Approved") -> 0 | Y3: =IF(AND(W3="",X3=""),"",MAX(N(W3),N(X3))) -> 0 | AA3: =W3-Z3 -> 0 | AC3: Open | AD3: FALSE | AG3: 5000 | AH3: {=_xlfn.XLOOKUP(AG3, 'GL Accounts'!$A$2:$A271, 'GL Accounts'!$B$2:$B271, "")} -> Expense · Executive | AI3: CC-VENUE | AJ3: 0000.02.01 | AK3: Tax on Purchases | AL3: USD | AM3: Julian Clarkson | AN3: 2026-09-30 13:05:00 | AO3: 2026-09-30 13:05:00
A4: BUD-0003 | B4: CSMIA26 | C4: Event 00 · Venue Startup | D4: The Sanctuary MiMo | H4: 0000 Executive | I4: 0000.03 Legal & Risk | J4: Legal Services | K4: N/A | N4: 0000.03.01 | O4: Advance | P4: 04 Physical | Q4: X | R4: Scope | T4: =SUMIFS('PO Line Items'!$H:$H, 'PO Line Items'!$C:$C, $A4) + SUMIFS('Change Orders'!$M:$M, 'Change Orders'!$E:$E, $A4, 'Change Orders'!$W:$W, "Approved") -> 0 | V4: =IF(OR(S4="",T4=""),"",ROUND(S4*T4,2)) | W4: =IF(V4="","",V4) | X4: =SUMIFS('PO Line Items'!$H:$H, 'PO Line Items'!$C:$C, $A4) + SUMIFS('Change Orders'!$M:$M, 'Change Orders'!$E:$E, $A4, 'Change Orders'!$W:$W, "Approved") -> 0 | Y4: =IF(AND(W4="",X4=""),"",MAX(N(W4),N(X4))) -> 0 | AA4: =W4-Z4 -> 0 | AC4: Open | AD4: FALSE | AG4: 5000 | AH4: {=_xlfn.XLOOKUP(AG4, 'GL Accounts'!$A$2:$A271, 'GL Accounts'!$B$2:$B271, "")} -> Expense · Executive | AI4: CC-VENUE | AJ4: 0000.03.01 | AK4: Tax on Purchases | AL4: USD | AM4: Julian Clarkson | AN4: 2026-09-30 13:05:00 | AO4: 2026-09-30 13:05:00
A5: BUD-0004 | B5: CSMIA26 | C5: Event 00 · Venue Startup | D5: The Sanctuary MiMo | H5: 0000 Executive | I5: 0000.04 Human Resources & People | J5: People Operations | K5: N/A | N5: 0000.04.01 | O5: Advance | P5: 04 Physical | Q5: X | R5: Scope | T5: =SUMIFS('PO Line Items'!$H:$H, 'PO Line Items'!$C:$C, $A5) + SUMIFS('Change Orders'!$M:$M, 'Change Orders'!$E:$E, $A5, 'Change Orders'!$W:$W, "Approved") -> 0 | V5: =IF(OR(S5="",T5=""),"",ROUND(S5*T5,2)) | W5: =IF(V5="","",V5) | X5: =SUMIFS('PO Line Items'!$H:$H, 'PO Line Items'!$C:$C, $A5) + SUMIFS('Change Orders'!$M:$M, 'Change Orders'!$E:$E, $A5, 'Change Orders'!$W:$W, "Approved") -> 0 | Y5: =IF(AND(W5="",X5=""),"",MAX(N(W5),N(X5))) -> 0 | AA5: =W5-Z5 -> 0 | AC5: Open | AD5: FALSE | AG5: 5000 | AH5: {=_xlfn.XLOOKUP(AG5, 'GL Accounts'!$A$2:$A271, 'GL Accounts'!$B$2:$B271, "")} -> Expense · Executive | AI5: CC-VENUE | AJ5: 0000.04.01 | AK5: Tax on Purchases | AL5: USD | AM5: Julian Clarkson | AN5: 2026-09-30 13:05:00 | AO5: 2026-09-30 13:05:00
A6: BUD-0005 | B6: CSMIA26 | C6: Event 00 · Venue Startup | D6: The Sanctuary MiMo | H6: 0000 Executive | I6: 0000.05 Business Development & Partnerships | J6: Business Development | K6: N/A | N6: 0000.05.01 | O6: Advance | P6: 04 Physical | Q6: X | R6: Scope | T6: =SUMIFS('PO Line Items'!$H:$H, 'PO Line Items'!$C:$C, $A6) + SUMIFS('Change Orders'!$M:$M, 'Change Orders'!$E:$E, $A6, 'Change Orders'!$W:$W, "Approved") -> 0 | V6: =IF(OR(S6="",T6=""),"",ROUND(S6*T6,2)) | W6: =IF(V6="","",V6) | X6: =SUMIFS('PO Line Items'!$H:$H, 'PO Line Items'!$C:$C, $A6) + SUMIFS('Change Orders'!$M:$M, 'Change Orders'!$E:$E, $A6, 'Change Orders'!$W:$W, "Approved") -> 0 | Y6: =IF(AND(W6="",X6=""),"",MAX(N(W6),N(X6))) -> 0 | AA6: =W6-Z6 -> 0 | AC6: Open | AD6: FALSE | AG6: 5000 | AH6: {=_xlfn.XLOOKUP(AG6, 'GL Accounts'!$A$2:$A271, 'GL Accounts'!$B$2:$B271, "")} -> Expense · Executive | AI6: CC-VENUE | AJ6: 0000.05.01 | AK6: Tax on Purchases | AL6: USD | AM6: Julian Clarkson | AN6: 2026-09-30 13:05:00 | AO6: 2026-09-30 13:05:00
A7: BUD-0006 | B7: CSMIA26 | C7: Event 00 · Venue Startup | D7: The Sanctuary MiMo | H7: 0000 Executive | I7: 0000.06 Insurance & Permitting | J7: Insurance | K7: N/A | N7: 0000.06.01 | O7: Advance | P7: 04 Physical | Q7: X | R7: Scope | T7: =SUMIFS('PO Line Items'!$H:$H, 'PO Line Items'!$C:$C, $A7) + SUMIFS('Change Orders'!$M:$M, 'Change Orders'!$E:$E, $A7, 'Change Orders'!$W:$W, "Approved") -> 0 | V7: =IF(OR(S7="",T7=""),"",ROUND(S7*T7,2)) | W7: =IF(V7="","",V7) | X7: =SUMIFS('PO Line Items'!$H:$H, 'PO Line Items'!$C:$C, $A7) + SUMIFS('Change Orders'!$M:$M, 'Change Orders'!$E:$E, $A7, 'Change Orders'!$W:$W, "Approved") -> 0 | Y7: =IF(AND(W7="",X7=""),"",MAX(N(W7),N(X7))) -> 0 | AA7: =W7-Z7 -> 0 | AC7: Open | AD7: FALSE | AG7: 5000 | AH7: {=_xlfn.XLOOKUP(AG7, 'GL Accounts'!$A$2:$A271, 'GL Accounts'!$B$2:$B271, "")} -> Expense · Executive | AI7: CC-VENUE | AJ7: 0000.06.01 | AK7: Tax on Purchases | AL7: USD | AM7: Julian Clarkson | AN7: 2026-09-30 13:05:00 | AO7: 2026-09-30 13:05:00
A8: BUD-0007 | B8: CSMIA26 | C8: Event 00 · Venue Startup | D8: The Sanctuary MiMo | H8: 0000 Executive | I8: 0000.06 Insurance & Permitting | J8: Permitting | K8: N/A | N8: 0000.06.02 | O8: Advance | P8: 04 Physical | Q8: X | R8: Scope | T8: =SUMIFS('PO Line Items'!$H:$H, 'PO Line Items'!$C:$C, $A8) + SUMIFS('Change Orders'!$M:$M, 'Change Orders'!$E:$E, $A8, 'Change Orders'!$W:$W, "Approved") -> 0 | V8: =IF(OR(S8="",T8=""),"",ROUND(S8*T8,2)) | W8: =IF(V8="","",V8) | X8: =SUMIFS('PO Line Items'!$H:$H, 'PO Line Items'!$C:$C, $A8) + SUMIFS('Change Orders'!$M:$M, 'Change Orders'!$E:$E, $A8, 'Change Orders'!$W:$W, "Approved") -> 0 | Y8: =IF(AND(W8="",X8=""),"",MAX(N(W8),N(X8))) -> 0 | AA8: =W8-Z8 -> 0 | AC8: Open | AD8: FALSE | AG8: 5000 | AH8: {=_xlfn.XLOOKUP(AG8, 'GL Accounts'!$A$2:$A271, 'GL Accounts'!$B$2:$B271, "")} -> Expense · Executive | AI8: CC-VENUE | AJ8: 0000.06.02 | AK8: Tax on Purchases | AL8: USD | AM8: Julian Clarkson | AN8: 2026-09-30 13:05:00 | AO8: 2026-09-30 13:05:00
A9: BUD-0008 | B9: CSMIA26 | C9: Event 00 · Venue Startup | D9: The Sanctuary MiMo | H9: 0000 Executive | I9: 0000.50 Governance and Client Relations | J9: Client Sponsorship | K9: N/A | N9: 0000.50.01 | O9: Advance | P9: 04 Physical | Q9: Y | R9: Scope | T9: =SUMIFS('PO Line Items'!$H:$H, 'PO Line Items'!$C:$C, $A9) + SUMIFS('Change Orders'!$M:$M, 'Change Orders'!$E:$E, $A9, 'Change Orders'!$W:$W, "Approved") -> 0 | V9: =IF(OR(S9="",T9=""),"",ROUND(S9*T9,2)) | W9: =IF(V9="","",V9) | X9: =SUMIFS('PO Line Items'!$H:$H, 'PO Line Items'!$C:$C, $A9) + SUMIFS('Change Orders'!$M:$M, 'Change Orders'!$E:$E, $A9, 'Change Orders'!$W:$W, "Approved") -> 0 | Y9: =IF(AND(W9="",X9=""),"",MAX(N(W9),N(X9))) -> 0 | AA9: =W9-Z9 -> 0 | AC9: Open | AD9: FALSE | AG9: 5000 | AH9: {=_xlfn.XLOOKUP(AG9, 'GL Accounts'!$A$2:$A271, 'GL Accounts'!$B$2:$B271, "")} -> Expense · Executive | AI9: CC-VENUE | AJ9: 0000.50.01 | AK9: Tax on Purchases | AL9: USD | AM9: Julian Clarkson | AN9: 2026-09-30 13:05:00 | AO9: 2026-09-30 13:05:00
A10: BUD-0009 | B10: CSMIA26 | C10: Event 00 · Venue Startup | D10: The Sanctuary MiMo | H10: 0000 Executive | I10: 0000.50 Governance and Client Relations | J10: Operator Leadership | K10: N/A | N10: 0000.50.02 | O10: Advance | P10: 04 Physical | Q10: Y | R10: Scope | T10: =SUMIFS('PO Line Items'!$H:$H, 'PO Line Items'!$C:$C, $A10) + SUMIFS('Change Orders'!$M:$M, 'Change Orders'!$E:$E, $A10, 'Change Orders'!$W:$W, "Approved") -> 0 | V10: =IF(OR(S10="",T10=""),"",ROUND(S10*T10,2)) | W10: =IF(V10="","",V10) | X10: =SUMIFS('PO Line Items'!$H:$H, 'PO Line Items'!$C:$C, $A10) + SUMIFS('Change Orders'!$M:$M, 'Change Orders'!$E:$E, $A10, 'Change Orders'!$W:$W, "Approved") -> 0 | Y10: =IF(AND(W10="",X10=""),"",MAX(N(W10),N(X10))) -> 0 | AA10: =W10-Z10 -> 0 | AC10: Open | AD10: FALSE | AG10: 5000 | AH10: {=_xlfn.XLOOKUP(AG10, 'GL Accounts'!$A$2:$A271, 'GL Accounts'!$B$2:$B271, "")} -> Expense · Executive | AI10: CC-VENUE | AJ10: 0000.50.02 | AK10: Tax on Purchases | AL10: USD | AM10: Julian Clarkson | AN10: 2026-09-30 13:05:00 | AO10: 2026-09-30 13:05:00
A11: BUD-0010 | B11: CSMIA26 | C11: Event 00 · Venue Startup | D11: The Sanctuary MiMo | H11: 0000 Executive | I11: 0000.50 Governance and Client Relations | J11: Approval Authority | K11: N/A | N11: 0000.50.03 | O11: Advance | P11: 04 Physical | Q11: Y | R11: Scope | T11: =SUMIFS('PO Line Items'!$H:$H, 'PO Line Items'!$C:$C, $A11) + SUMIFS('Change Orders'!$M:$M, 'Change Orders'!$E:$E, $A11, 'Change Orders'!$W:$W, "Approved") -> 0 | V11: =IF(OR(S11="",T11=""),"",ROUND(S11*T11,2)) | W11: =IF(V11="","",V11) | X11: =SUMIFS('PO Line Items'!$H:$H, 'PO Line Items'!$C:$C, $A11) + SUMIFS('Change Orders'!$M:$M, 'Change Orders'!$E:$E, $A11, 'Change Orders'!$W:$W, "Approved") -> 0 | Y11: =IF(AND(W11="",X11=""),"",MAX(N(W11),N(X11))) -> 0 | AA11: =W11-Z11 -> 0 | AC11: Open | AD11: FALSE | AG11: 5000 | AH11: {=_xlfn.XLOOKUP(AG11, 'GL Accounts'!$A$2:$A271, 'GL Accounts'!$B$2:$B271, "")} -> Expense · Executive | AI11: CC-VENUE | AJ11: 0000.50.03 | AK11: Tax on Purchases | AL11: USD | AM11: Julian Clarkson | AN11: 2026-09-30 13:05:00 | AO11: 2026-09-30 13:05:00
A12: BUD-0011 | B12: CSMIA26 | C12: Event 00 · Venue Startup | D12: The Sanctuary MiMo | H12: 0000 Executive | I12: 0000.51 Commercial and Finance | J12: Financial Control | K12: N/A | N12: 0000.51.01 | O12: Advance | P12: 04 Physical | Q12: Y | R12: Scope | T12: =SUMIFS('PO Line Items'!$H:$H, 'PO Line Items'!$C:$C, $A12) + SUMIFS('Change Orders'!$M:$M, 'Change Orders'!$E:$E, $A12, 'Change Orders'!$W:$W, "Approved") -> 0 | V12: =IF(OR(S12="",T12=""),"",ROUND(S12*T12,2)) | W12: =IF(V12="","",V12) | X12: =SUMIFS('PO Line Items'!$H:$H, 'PO Line Items'!$C:$C, $A12) + SUMIFS('Change Orders'!$M:$M, 'Change Orders'!$E:$E, $A12, 'Change Orders'!$W:$W, "Approved") -> 0 | Y12: =IF(AND(W12="",X12=""),"",MAX(N(W12),N(X12))) -> 0 | AA12: =W12-Z12 -> 0 | AC12: Open | AD12: FALSE | AG12: 5000 | AH12: {=_xlfn.XLOOKUP(AG12, 'GL Accounts'!$A$2:$A271, 'GL Accounts'!$B$2:$B271, "")} -> Expense · Executive | AI12: CC-CORP | AJ12: 0000.51.01 | AK12: Tax on Purchases | AL12: USD | AM12: Julian Clarkson | AN12: 2026-09-30 13:05:00 | AO12: 2026-09-30 13:05:00
A13: BUD-0012 | B13: CSMIA26 | C13: Event 00 · Venue Startup | D13: The Sanctuary MiMo | H13: 0000 Executive | I13: 0000.51 Commercial and Finance | J13: Insurance and Risk | K13: N/A | N13: 0000.51.02 | O13: Advance | P13: 04 Physical | Q13: Y | R13: Scope | T13: =SUMIFS('PO Line Items'!$H:$H, 'PO Line Items'!$C:$C, $A13) + SUMIFS('Change Orders'!$M:$M, 'Change Orders'!$E:$E, $A13, 'Change Orders'!$W:$W, "Approved") -> 0 | V13: =IF(OR(S13="",T13=""),"",ROUND(S13*T13,2)) | W13: =IF(V13="","",V13) | X13: =SUMIFS('PO Line Items'!$H:$H, 'PO Line Items'!$C:$C, $A13) + SUMIFS('Change Orders'!$M:$M, 'Change Orders'!$E:$E, $A13, 'Change Orders'!$W:$W, "Approved") -> 0 | Y13: =IF(AND(W13="",X13=""),"",MAX(N(W13),N(X13))) -> 0 | AA13: =W13-Z13 -> 0 | AC13: Open | AD13: FALSE | AG13: 5000 | AH13: {=_xlfn.XLOOKUP(AG13, 'GL Accounts'!$A$2:$A271, 'GL Accounts'!$B$2:$B271, "")} -> Expense · Executive | AI13: CC-CORP | AJ13: 0000.51.02 | AK13: Tax on Purchases | AL13: USD | AM13: Julian Clarkson | AN13: 2026-09-30 13:05:00 | AO13: 2026-09-30 13:05:00
A14: BUD-0013 | B14: CSMIA26 | C14: Event 00 · Venue Startup | D14: The Sanctuary MiMo | H14: 0000 Executive | I14: 0000.51 Commercial and Finance | J14: Legal Counsel | K14: N/A | N14: 0000.51.03 | O14: Advance | P14: 04 Physical | Q14: Y | R14: Scope | T14: =SUMIFS('PO Line Items'!$H:$H, 'PO Line Items'!$C:$C, $A14) + SUMIFS('Change Orders'!$M:$M, 'Change Orders'!$E:$E, $A14, 'Change Orders'!$W:$W, "Approved") -> 0 | V14: =IF(OR(S14="",T14=""),"",ROUND(S14*T14,2)) | W14: =IF(V14="","",V14) | X14: =SUMIFS('PO Line Items'!$H:$H, 'PO Line Items'!$C:$C, $A14) + SUMIFS('Change Orders'!$M:$M, 'Change Orders'!$E:$E, $A14, 'Change Orders'!$W:$W, "Approved") -> 0 | Y14: =IF(AND(W14="",X14=""),"",MAX(N(W14),N(X14))) -> 0 | AA14: =W14-Z14 -> 0 | AC14: Open | AD14: FALSE | AG14: 5000 | AH14: {=_xlfn.XLOOKUP(AG14, 'GL Accounts'!$A$2:$A271, 'GL Accounts'!$B$2:$B271, "")} -> Expense · Executive | AI14: CC-CORP | AJ14: 0000.51.03 | AK14: Tax on Purchases | AL14: USD | AM14: Julian Clarkson | AN14: 2026-09-30 13:05:00 | AO14: 2026-09-30 13:05:00
A15: BUD-0014 | B15: CSMIA26 | C15: Event 00 · Venue Startup | D15: The Sanctuary MiMo | H15: 1000 Creative | I15: 1000.01 Creative Direction | J15: Creative Direction | K15: N/A | N15: 1000.01.01 | O15: Advance | P15: 04 Physical | Q15: X | R15: Scope | T15: =SUMIFS('PO Line Items'!$H:$H, 'PO Line Items'!$C:$C, $A15) + SUMIFS('Change Orders'!$M:$M, 'Change Orders'!$E:$E, $A15, 'Change Orders'!$W:$W, "Approved") -> 0 | V15: =IF(OR(S15="",T15=""),"",ROUND(S15*T15,2)) | W15: =IF(V15="","",V15) | X15: =SUMIFS('PO Line Items'!$H:$H, 'PO Line Items'!$C:$C, $A15) + SUMIFS('Change Orders'!$M:$M, 'Change Orders'!$E:$E, $A15, 'Change Orders'!$W:$W, "Approved") -> 0 | Y15: =IF(AND(W15="",X15=""),"",MAX(N(W15),N(X15))) -> 0 | AA15: =W15-Z15 -> 0 | AC15: Open | AD15: FALSE | AG15: 5100 | AH15: {=_xlfn.XLOOKUP(AG15, 'GL Accounts'!$A$2:$A271, 'GL Accounts'!$B$2:$B271, "")} -> Expense · Creative | AI15: CC-VENUE | AJ15: 1000.01.01 | AK15: Tax on Purchases | AL15: USD | AM15: Julian Clarkson | AN15: 2026-09-30 13:05:00 | AO15: 2026-09-30 13:05:00
A16: BUD-0015 | B16: CSMIA26 | C16: Event 00 · Venue Startup | D16: The Sanctuary MiMo | H16: 1000 Creative | I16: 1000.02 Experiential & Environment Design | J16: Environment Design | K16: N/A | N16: 1000.02.01 | O16: Advance | P16: 04 Physical | Q16: X | R16: Scope | T16: =SUMIFS('PO Line Items'!$H:$H, 'PO Line Items'!$C:$C, $A16) + SUMIFS('Change Orders'!$M:$M, 'Change Orders'!$E:$E, $A16, 'Change Orders'!$W:$W, "Approved") -> 0 | V16: =IF(OR(S16="",T16=""),"",ROUND(S16*T16,2)) | W16: =IF(V16="","",V16) | X16: =SUMIFS('PO Line Items'!$H:$H, 'PO Line Items'!$C:$C, $A16) + SUMIFS('Change Orders'!$M:$M, 'Change Orders'!$E:$E, $A16, 'Change Orders'!$W:$W, "Approved") -> 0 | Y16: =IF(AND(W16="",X16=""),"",MAX(N(W16),N(X16))) -> 0 | AA16: =W16-Z16 -> 0 | AC16: Open | AD16: FALSE | AG16: 5100 | AH16: {=_xlfn.XLOOKUP(AG16, 'GL Accounts'!$A$2:$A271, 'GL Accounts'!$B$2:$B271, "")} -> Expense · Creative | AI16: CC-VENUE | AJ16: 1000.02.01 | AK16: Tax on Purchases | AL16: USD | AM16: Julian Clarkson | AN16: 2026-09-30 13:05:00 | AO16: 2026-09-30 13:05:00
A17: BUD-0016 | B17: CSMIA26 | C17: Event 00 · Venue Startup | D17: The Sanctuary MiMo | H17: 1000 Creative | I17: 1000.03 Brand & Identity Design | J17: Brand Design | K17: N/A | N17: 1000.03.01 | O17: Advance | P17: 04 Physical | Q17: X | R17: Scope | T17: =SUMIFS('PO Line Items'!$H:$H, 'PO Line Items'!$C:$C, $A17) + SUMIFS('Change Orders'!$M:$M, 'Change Orders'!$E:$E, $A17, 'Change Orders'!$W:$W, "Approved") -> 0 | V17: =IF(OR(S17="",T17=""),"",ROUND(S17*T17,2)) | W17: =IF(V17="","",V17) | X17: =SUMIFS('PO Line Items'!$H:$H, 'PO Line Items'!$C:$C, $A17) + SUMIFS('Change Orders'!$M:$M, 'Change Orders'!$E:$E, $A17, 'Change Orders'!$W:$W, "Approved") -> 0 | Y17: =IF(AND(W17="",X17=""),"",MAX(N(W17),N(X17))) -> 0 | AA17: =W17-Z17 -> 0 | AC17: Open | AD17: FALSE | AG17: 5100 | AH17: {=_xlfn.XLOOKUP(AG17, 'GL Accounts'!$A$2:$A271, 'GL Accounts'!$B$2:$B271, "")} -> Expense · Creative | AI17: CC-VENUE | AJ17: 1000.03.01 | AK17: Tax on Purchases | AL17: USD | AM17: Julian Clarkson | AN17: 2026-09-30 13:05:00 | AO17: 2026-09-30 13:05:00
A18: BUD-0017 | B18: CSMIA26 | C18: Event 00 · Venue Startup | D18: The Sanctuary MiMo | H18: 1000 Creative | I18: 1000.04 Graphic & 2D Design | J18: Graphic Design | K18: N/A | N18: 1000.04.01 | O18: Advance | P18: 04 Physical | Q18: X | R18: Scope | T18: =SUMIFS('PO Line Items'!$H:$H, 'PO Line Items'!$C:$C, $A18) + SUMIFS('Change Orders'!$M:$M, 'Change Orders'!$E:$E, $A18, 'Change Orders'!$W:$W, "Approved") -> 0 | V18: =IF(OR(S18="",T18=""),"",ROUND(S18*T18,2)) | W18: =IF(V18="","",V18) | X18: =SUMIFS('PO Line Items'!$H:$H, 'PO Line Items'!$C:$C, $A18) + SUMIFS('Change Orders'!$M:$M, 'Change Orders'!$E:$E, $A18, 'Change Orders'!$W:$W, "Approved") -> 0 | Y18: =IF(AND(W18="",X18=""),"",MAX(N(W18),N(X18))) -> 0 | AA18: =W18-Z18 -> 0 | AC18: Open | AD18: FALSE | AG18: 5100 | AH18: {=_xlfn.XLOOKUP(AG18, 'GL Accounts'!$A$2:$A271, 'GL Accounts'!$B$2:$B271, "")} -> Expense · Creative | AI18: CC-VENUE | AJ18: 1000.04.01 | AK18: Tax on Purchases | AL18: USD | AM18: Julian Clarkson | AN18: 2026-09-30 13:05:00 | AO18: 2026-09-30 13:05:00
A19: BUD-0018 | B19: CSMIA26 | C19: Event 00 · Venue Startup | D19: The Sanctuary MiMo | H19: 1000 Creative | I19: 1000.04 Graphic & 2D Design | J19: Print Collateral | K19: N/A | N19: 1000.04.02 | O19: Advance | P19: 04 Physical | Q19: X | R19: Scope | T19: =SUMIFS('PO Line Items'!$H:$H, 'PO Line Items'!$C:$C, $A19) + SUMIFS('Change Orders'!$M:$M, 'Change Orders'!$E:$E, $A19, 'Change Orders'!$W:$W, "Approved") -> 0 | V19: =IF(OR(S19="",T19=""),"",ROUND(S19*T19,2)) | W19: =IF(V19="","",V19) | X19: =SUMIFS('PO Line Items'!$H:$H, 'PO Line Items'!$C:$C, $A19) + SUMIFS('Change Orders'!$M:$M, 'Change Orders'!$E:$E, $A19, 'Change Orders'!$W:$W, "Approved") -> 0 | Y19: =IF(AND(W19="",X19=""),"",MAX(N(W19),N(X19))) -> 0 | AA19: =W19-Z19 -> 0 | AC19: Open | AD19: FALSE | AG19: 5100 | AH19: {=_xlfn.XLOOKUP(AG19, 'GL Accounts'!$A$2:$A271, 'GL Accounts'!$B$2:$B271, "")} -> Expense · Creative | AI19: CC-VENUE | AJ19: 1000.04.02 | AK19: Tax on Purchases | AL19: USD | AM19: Julian Clarkson | AN19: 2026-09-30 13:05:00 | AO19: 2026-09-30 13:05:00
A20: BUD-0019 | B20: CSMIA26 | C20: Event 00 · Venue Startup | D20: The Sanctuary MiMo | H20: 1000 Creative | I20: 1000.05 Content Production | J20: Content Production | K20: N/A | N20: 1000.05.01 | O20: Advance | P20: 04 Physical | Q20: X | R20: Scope | T20: =SUMIFS('PO Line Items'!$H:$H, 'PO Line Items'!$C:$C, $A20) + SUMIFS('Change Orders'!$M:$M, 'Change Orders'!$E:$E, $A20, 'Change Orders'!$W:$W, "Approved") -> 0 | V20: =IF(OR(S20="",T20=""),"",ROUND(S20*T20,2)) | W20: =IF(V20="","",V20) | X20: =SUMIFS('PO Line Items'!$H:$H, 'PO Line Items'!$C:$C, $A20) + SUMIFS('Change Orders'!$M:$M, 'Change Orders'!$E:$E, $A20, 'Change Orders'!$W:$W, "Approved") -> 0 | Y20: =IF(AND(W20="",X20=""),"",MAX(N(W20),N(X20))) -> 0 | AA20: =W20-Z20 -> 0 | AC20: Open | AD20: FALSE | AG20: 5100 | AH20: {=_xlfn.XLOOKUP(AG20, 'GL Accounts'!$A$2:$A271, 'GL Accounts'!$B$2:$B271, "")} -> Expense · Creative | AI20: CC-VENUE | AJ20: 1000.05.01 | AK20: Tax on Purchases | AL20: USD | AM20: Julian Clarkson | AN20: 2026-09-30 13:05:00 | AO20: 2026-09-30 13:05:00
A21: BUD-0020 | B21: CSMIA26 | C21: Event 00 · Venue Startup | D21: The Sanctuary MiMo | H21: 1000 Creative | I21: 1000.05 Content Production | J21: Sonic Branding | K21: N/A | N21: 1000.05.02 | O21: Advance | P21: 04 Physical | Q21: X | R21: Scope | T21: =SUMIFS('PO Line Items'!$H:$H, 'PO Line Items'!$C:$C, $A21) + SUMIFS('Change Orders'!$M:$M, 'Change Orders'!$E:$E, $A21, 'Change Orders'!$W:$W, "Approved") -> 0 | V21: =IF(OR(S21="",T21=""),"",ROUND(S21*T21,2)) | W21: =IF(V21="","",V21) | X21: =SUMIFS('PO Line Items'!$H:$H, 'PO Line Items'!$C:$C, $A21) + SUMIFS('Change Orders'!$M:$M, 'Change Orders'!$E:$E, $A21, 'Change Orders'!$W:$W, "Approved") -> 0 | Y21: =IF(AND(W21="",X21=""),"",MAX(N(W21),N(X21))) -> 0 | AA21: =W21-Z21 -> 0 | AC21: Open | AD21: FALSE | AG21: 5100 | AH21: {=_xlfn.XLOOKUP(AG21, 'GL Accounts'!$A$2:$A271, 'GL Accounts'!$B$2:$B271, "")} -> Expense · Creative | AI21: CC-VENUE | AJ21: 1000.05.02 | AK21: Tax on Purchases | AL21: USD | AM21: Julian Clarkson | AN21: 2026-09-30 13:05:00 | AO21: 2026-09-30 13:05:00
A22: BUD-0021 | B22: CSMIA26 | C22: Event 00 · Venue Startup | D22: The Sanctuary MiMo | H22: 1000 Creative | I22: 1000.06 Copywriting & Verbal Identity | J22: Verbal Identity | K22: N/A | N22: 1000.06.01 | O22: Advance | P22: 04 Physical | Q22: X | R22: Scope | T22: =SUMIFS('PO Line Items'!$H:$H, 'PO Line Items'!$C:$C, $A22) + SUMIFS('Change Orders'!$M:$M, 'Change Orders'!$E:$E, $A22, 'Change Orders'!$W:$W, "Approved") -> 0 | V22: =IF(OR(S22="",T22=""),"",ROUND(S22*T22,2)) | W22: =IF(V22="","",V22) | X22: =SUMIFS('PO Line Items'!$H:$H, 'PO Line Items'!$C:$C, $A22) + SUMIFS('Change Orders'!$M:$M, 'Change Orders'!$E:$E, $A22, 'Change Orders'!$W:$W, "Approved") -> 0 | Y22: =IF(AND(W22="",X22=""),"",MAX(N(W22),N(X22))) -> 0 | AA22: =W22-Z22 -> 0 | AC22: Open | AD22: FALSE | AG22: 5100 | AH22: {=_xlfn.XLOOKUP(AG22, 'GL Accounts'!$A$2:$A271, 'GL Accounts'!$B$2:$B271, "")} -> Expense · Creative | AI22: CC-VENUE | AJ22: 1000.06.01 | AK22: Tax on Purchases | AL22: USD | AM22: Julian Clarkson | AN22: 2026-09-30 13:05:00 | AO22: 2026-09-30 13:05:00
A23: BUD-0022 | B23: CSMIA26 | C23: Event 00 · Venue Startup | D23: The Sanctuary MiMo | H23: 1000 Creative | I23: 1000.07 Digital & Interactive Design | J23: Digital Design | K23: N/A | N23: 1000.07.01 | O23: Advance | P23: 04 Physical | Q23: X | R23: Scope | T23: =SUMIFS('PO Line Items'!$H:$H, 'PO Line Items'!$C:$C, $A23) + SUMIFS('Change Orders'!$M:$M, 'Change Orders'!$E:$E, $A23, 'Change Orders'!$W:$W, "Approved") -> 0 | V23: =IF(OR(S23="",T23=""),"",ROUND(S23*T23,2)) | W23: =IF(V23="","",V23) | X23: =SUMIFS('PO Line Items'!$H:$H, 'PO Line Items'!$C:$C, $A23) + SUMIFS('Change Orders'!$M:$M, 'Change Orders'!$E:$E, $A23, 'Change Orders'!$W:$W, "Approved") -> 0 | Y23: =IF(AND(W23="",X23=""),"",MAX(N(W23),N(X23))) -> 0 | AA23: =W23-Z23 -> 0 | AC23: Open | AD23: FALSE | AG23: 5100 | AH23: {=_xlfn.XLOOKUP(AG23, 'GL Accounts'!$A$2:$A271, 'GL Accounts'!$B$2:$B271, "")} -> Expense · Creative | AI23: CC-VENUE | AJ23: 1000.07.01 | AK23: Tax on Purchases | AL23: USD | AM23: Julian Clarkson | AN23: 2026-09-30 13:05:00 | AO23: 2026-09-30 13:05:00
A24: BUD-0023 | B24: CSMIA26 | C24: Event 00 · Venue Startup | D24: The Sanctuary MiMo | H24: 1000 Creative | I24: 1000.08 Intellectual Property & Licensing | J24: Intellectual Property & Licensing | K24: N/A | N24: 1000.08.01 | O24: Advance | P24: 04 Physical | Q24: X | R24: Scope | T24: =SUMIFS('PO Line Items'!$H:$H, 'PO Line Items'!$C:$C, $A24) + SUMIFS('Change Orders'!$M:$M, 'Change Orders'!$E:$E, $A24, 'Change Orders'!$W:$W, "Approved") -> 0 | V24: =IF(OR(S24="",T24=""),"",ROUND(S24*T24,2)) | W24: =IF(V24="","",V24) | X24: =SUMIFS('PO Line Items'!$H:$H, 'PO Line Items'!$C:$C, $A24) + SUMIFS('Change Orders'!$M:$M, 'Change Orders'!$E:$E, $A24, 'Change Orders'!$W:$W, "Approved") -> 0 | Y24: =IF(AND(W24="",X24=""),"",MAX(N(W24),N(X24))) -> 0 | AA24: =W24-Z24 -> 0 | AC24: Open | AD24: FALSE | AG24: 5100 | AH24: {=_xlfn.XLOOKUP(AG24, 'GL Accounts'!$A$2:$A271, 'GL Accounts'!$B$2:$B271, "")} -> Expense · Creative | AI24: CC-VENUE | AJ24: 1000.08.01 | AK24: Tax on Purchases | AL24: USD | AM24: Julian Clarkson | AN24: 2026-09-30 13:05:00 | AO24: 2026-09-30 13:05:00
A25: BUD-0024 | B25: CSMIA26 | C25: Event 00 · Venue Startup | D25: The Sanctuary MiMo | H25: 1000 Creative | I25: 1000.50 Programming and Creative Direction | J25: Creative Direction | K25: N/A | N25: 1000.50.01 | O25: Advance | P25: 04 Physical | Q25: Y | R25: Scope | T25: =SUMIFS('PO Line Items'!$H:$H, 'PO Line Items'!$C:$C, $A25) + SUMIFS('Change Orders'!$M:$M, 'Change Orders'!$E:$E, $A25, 'Change Orders'!$W:$W, "Approved") -> 0 | V25: =IF(OR(S25="",T25=""),"",ROUND(S25*T25,2)) | W25: =IF(V25="","",V25) | X25: =SUMIFS('PO Line Items'!$H:$H, 'PO Line Items'!$C:$C, $A25) + SUMIFS('Change Orders'!$M:$M, 'Change Orders'!$E:$E, $A25, 'Change Orders'!$W:$W, "Approved") -> 0 | Y25: =IF(AND(W25="",X25=""),"",MAX(N(W25),N(X25))) -> 0 | AA25: =W25-Z25 -> 0 | AC25: Open | AD25: FALSE | AG25: 5100 | AH25: {=_xlfn.XLOOKUP(AG25, 'GL Accounts'!$A$2:$A271, 'GL Accounts'!$B$2:$B271, "")} -> Expense · Creative | AI25: CC-VENUE | AJ25: 1000.50.01 | AK25: Tax on Purchases | AL25: USD | AM25: Julian Clarkson | AN25: 2026-09-30 13:05:00 | AO25: 2026-09-30 13:05:00
A26: BUD-0025 | B26: CSMIA26 | C26: Event 00 · Venue Startup | D26: The Sanctuary MiMo | H26: 1000 Creative | I26: 1000.50 Programming and Creative Direction | J26: Programming Lead | K26: N/A | N26: 1000.50.02 | O26: Advance | P26: 04 Physical | Q26: Y | R26: Scope | T26: =SUMIFS('PO Line Items'!$H:$H, 'PO Line Items'!$C:$C, $A26) + SUMIFS('Change Orders'!$M:$M, 'Change Orders'!$E:$E, $A26, 'Change Orders'!$W:$W, "Approved") -> 0 | V26: =IF(OR(S26="",T26=""),"",ROUND(S26*T26,2)) | W26: =IF(V26="","",V26) | X26: =SUMIFS('PO Line Items'!$H:$H, 'PO Line Items'!$C:$C, $A26) + SUMIFS('Change Orders'!$M:$M, 'Change Orders'!$E:$E, $A26, 'Change Orders'!$W:$W, "Approved") -> 0 | Y26: =IF(AND(W26="",X26=""),"",MAX(N(W26),N(X26))) -> 0 | AA26: =W26-Z26 -> 0 | AC26: Open | AD26: FALSE | AG26: 5100 | AH26: {=_xlfn.XLOOKUP(AG26, 'GL Accounts'!$A$2:$A271, 'GL Accounts'!$B$2:$B271, "")} -> Expense · Creative | AI26: CC-VENUE | AJ26: 1000.50.02 | AK26: Tax on Purchases | AL26: USD | AM26: Julian Clarkson | AN26: 2026-09-30 13:05:00 | AO26: 2026-09-30 13:05:00
A27: BUD-0026 | B27: CSMIA26 | C27: Event 00 · Venue Startup | D27: The Sanctuary MiMo | H27: 1000 Creative | I27: 1000.51 Scenic and Graphics Production | J27: Signage Fabrication | K27: N/A | N27: 1000.51.01 | O27: Advance | P27: 04 Physical | Q27: Y | R27: Scope | T27: =SUMIFS('PO Line Items'!$H:$H, 'PO Line Items'!$C:$C, $A27) + SUMIFS('Change Orders'!$M:$M, 'Change Orders'!$E:$E, $A27, 'Change Orders'!$W:$W, "Approved") -> 5200 | V27: =IF(OR(S27="",T27=""),"",ROUND(S27*T27,2)) | W27: =IF(V27="","",V27) | X27: =SUMIFS('PO Line Items'!$H:$H, 'PO Line Items'!$C:$C, $A27) + SUMIFS('Change Orders'!$M:$M, 'Change Orders'!$E:$E, $A27, 'Change Orders'!$W:$W, "Approved") -> 5200 | Y27: =IF(AND(W27="",X27=""),"",MAX(N(W27),N(X27))) -> 5200 | AA27: =W27-Z27 -> 0 | AC27: Open | AD27: FALSE | AG27: 5100 | AH27: {=_xlfn.XLOOKUP(AG27, 'GL Accounts'!$A$2:$A271, 'GL Accounts'!$B$2:$B271, "")} -> Expense · Creative | AI27: CC-VENUE | AJ27: 1000.51.01 | AK27: Tax on Purchases | AL27: USD | AM27: Julian Clarkson | AN27: 2026-09-30 13:05:00 | AO27: 2026-09-30 13:05:00
A28: BUD-0027 | B28: CSMIA26 | C28: Event 00 · Venue Startup | D28: The Sanctuary MiMo | H28: 1000 Creative | I28: 1000.51 Scenic and Graphics Production | J28: Scenic Fabrication | K28: N/A | N28: 1000.51.02 | O28: Advance | P28: 04 Physical | Q28: Y | R28: Scope | T28: =SUMIFS('PO Line Items'!$H:$H, 'PO Line Items'!$C:$C, $A28) + SUMIFS('Change Orders'!$M:$M, 'Change Orders'!$E:$E, $A28, 'Change Orders'!$W:$W, "Approved") -> 0 | V28: =IF(OR(S28="",T28=""),"",ROUND(S28*T28,2)) | W28: =IF(V28="","",V28) | X28: =SUMIFS('PO Line Items'!$H:$H, 'PO Line Items'!$C:$C, $A28) + SUMIFS('Change Orders'!$M:$M, 'Change Orders'!$E:$E, $A28, 'Change Orders'!$W:$W, "Approved") -> 0 | Y28: =IF(AND(W28="",X28=""),"",MAX(N(W28),N(X28))) -> 0 | AA28: =W28-Z28 -> 0 | AC28: Open | AD28: FALSE | AG28: 5100 | AH28: {=_xlfn.XLOOKUP(AG28, 'GL Accounts'!$A$2:$A271, 'GL Accounts'!$B$2:$B271, "")} -> Expense · Creative | AI28: CC-VENUE | AJ28: 1000.51.02 | AK28: Tax on Purchases | AL28: USD | AM28: Julian Clarkson | AN28: 2026-09-30 13:05:00 | AO28: 2026-09-30 13:05:00
A29: BUD-0028 | B29: CSMIA26 | C29: Event 00 · Venue Startup | D29: The Sanctuary MiMo | H29: 2000 Talent | I29: 2000.01 Artist Booking & Programming | J29: Booking | K29: N/A | N29: 2000.01.01 | O29: Engage | P29: 04 Physical | Q29: X | R29: Scope | T29: =SUMIFS('PO Line Items'!$H:$H, 'PO Line Items'!$C:$C, $A29) + SUMIFS('Change Orders'!$M:$M, 'Change Orders'!$E:$E, $A29, 'Change Orders'!$W:$W, "Approved") -> 0 | V29: =IF(OR(S29="",T29=""),"",ROUND(S29*T29,2)) | W29: =IF(V29="","",V29) | X29: =SUMIFS('PO Line Items'!$H:$H, 'PO Line Items'!$C:$C, $A29) + SUMIFS('Change Orders'!$M:$M, 'Change Orders'!$E:$E, $A29, 'Change Orders'!$W:$W, "Approved") -> 0 | Y29: =IF(AND(W29="",X29=""),"",MAX(N(W29),N(X29))) -> 0 | AA29: =W29-Z29 -> 0 | AC29: Open | AD29: FALSE | AG29: 5200 | AH29: {=_xlfn.XLOOKUP(AG29, 'GL Accounts'!$A$2:$A271, 'GL Accounts'!$B$2:$B271, "")} -> Expense · Talent | AI29: CC-VENUE | AJ29: 2000.01.01 | AK29: Tax on Purchases | AL29: USD | AM29: Julian Clarkson | AN29: 2026-09-30 13:05:00 | AO29: 2026-09-30 13:05:00
A30: BUD-0029 | B30: CSMIA26 | C30: Event 00 · Venue Startup | D30: The Sanctuary MiMo | H30: 2000 Talent | I30: 2000.02 Music Programming & Curation | J30: Curation | K30: N/A | N30: 2000.02.01 | O30: Engage | P30: 04 Physical | Q30: X | R30: Scope | T30: =SUMIFS('PO Line Items'!$H:$H, 'PO Line Items'!$C:$C, $A30) + SUMIFS('Change Orders'!$M:$M, 'Change Orders'!$E:$E, $A30, 'Change Orders'!$W:$W, "Approved") -> 0 | V30: =IF(OR(S30="",T30=""),"",ROUND(S30*T30,2)) | W30: =IF(V30="","",V30) | X30: =SUMIFS('PO Line Items'!$H:$H, 'PO Line Items'!$C:$C, $A30) + SUMIFS('Change Orders'!$M:$M, 'Change Orders'!$E:$E, $A30, 'Change Orders'!$W:$W, "Approved") -> 0 | Y30: =IF(AND(W30="",X30=""),"",MAX(N(W30),N(X30))) -> 0 | AA30: =W30-Z30 -> 0 | AC30: Open | AD30: FALSE | AG30: 5200 | AH30: {=_xlfn.XLOOKUP(AG30, 'GL Accounts'!$A$2:$A271, 'GL Accounts'!$B$2:$B271, "")} -> Expense · Talent | AI30: CC-VENUE | AJ30: 2000.02.01 | AK30: Tax on Purchases | AL30: USD | AM30: Julian Clarkson | AN30: 2026-09-30 13:05:00 | AO30: 2026-09-30 13:05:00
